Workbook
Name ALTA_VERAPAZ: #REF!
Name ALTA_VERAPAZ: #REF!
Name ALTA_VERAPAZ: #REF!
Name BAJA_VERAPAZ: #REF!
Name BAJA_VERAPAZ: #REF!
Name BAJA_VERAPAZ: #REF!
Name CHIMALTENANGO: #REF!
Name CHIMALTENANGO: #REF!
Name CHIMALTENANGO: #REF!
Name CHIQUIMULA: #REF!
Name CHIQUIMULA: #REF!
Name CHIQUIMULA: #REF!
Name CIUDAD_PORTUARIA: #REF!
Name CIUDAD_PORTUARIA: #REF!
Name CIUDAD_PORTUARIA: #REF!
Name CIUDAD_TURISTICA: #REF!
Name CIUDAD_TURISTICA: #REF!
Name CIUDAD_TURISTICA: #REF!
Name CORREDOR: #REF!
Name CORREDOR: #REF!
Name CORREDOR: #REF!
Name DEPTO00: 'ICL 2023 (12 pilares)'!$D$10:$D$385
Name DEPTO00: 'ICL 2024 (12 pilares)'!$D$10:$D$385
Name DEPTO00: 'ICL 2024 (datos serie original)'!$D$10:$D$385
Name DEPTO00: 'ICL 2024 (Indicadores base 100)'!$D$10:$D$385
Name DEPTO00: 'ICL 2024 (Resumen)'!$D$10:$D$385
Name DEPTO01: #REF!
Name DEPTO01: #REF!
Name DEPTO01: #REF!
Name DEPTO02: #REF!
Name DEPTO02: #REF!
Name DEPTO02: #REF!
Name DEPTO03: #REF!
Name DEPTO03: #REF!
Name DEPTO03: #REF!
Name DEPTO04: #REF!
Name DEPTO04: #REF!
Name DEPTO04: #REF!
Name DEPTO05: #REF!
Name DEPTO05: #REF!
Name DEPTO05: #REF!
Name DEPTO06: #REF!
Name DEPTO06: #REF!
Name DEPTO06: #REF!
Name DEPTO07: #REF!
Name DEPTO07: #REF!
Name DEPTO07: #REF!
Name DEPTO08: #REF!
Name DEPTO08: #REF!
Name DEPTO08: #REF!
Name DEPTO09: #REF!
Name DEPTO09: #REF!
Name DEPTO09: #REF!
Name DEPTO10: #REF!
Name DEPTO10: #REF!
Name DEPTO10: #REF!
Name DEPTO11: #REF!
Name DEPTO11: #REF!
Name DEPTO11: #REF!
Name DEPTO12: #REF!

Sheet ICL 2024 (Resumen)
D2: ÍNDICE DE COMPETITIVIDAD LOCAL
D4: Fundación para el Desarrollo de Guatemala - FUNDESA -
D5: RESUMEN: variables sociodemográficas y económicas
D6: Datos Generales por Territorio
B9: NO. | C9: CÓDIGO DEPARTAMENTO | D9: DEPARTAMENTO | E9: CÓDIGO MUNICIPIO | F9: MUNICIPIO | G9: ICL 2024 | H9: RANKING (s/340) | I9: PIB per cápita 2023 (US$ al año) | J9: Población (2023) | K9: % No Ladinos (2018) | L9: Extensión Territorial (Km2) | M9: Urbanización (2018)
B10: 1 | C10: 1 | D10: GUATEMALA | E10: 101 | F10: Guatemala | G10: 79.015635 | H10: 1 | I10: 24741.856 | J10: 1221739 | K10: 0.0868 | L10: 184 | M10: 1
B11: 17 | C11: 1 | D11: GUATEMALA | E11: 117 | F11: San Miguel Petapa | G11: 73.881582 | H11: 2 | I11: 7589.0774 | J11: 152666 | K11: 0.0658 | L11: 30 | M11: 0.95333225
B12: 8 | C12: 1 | D12: GUATEMALA | E12: 108 | F12: Mixco | G12: 72.164621 | H12: 3 | I12: 12394.887 | J12: 527828 | K12: 0.1065 | L12: 132 | M12: 0.99412315
B13: 2 | C13: 1 | D13: GUATEMALA | E13: 102 | F13: Santa Catarina Pinula | G13: 72.003823 | H13: 4 | I13: 18727.882 | J13: 87717 | K13: 0.0549 | L13: 51 | M13: 0.88424284
B14: 26 | C14: 3 | D14: SACATEPEQUEZ | E14: 301 | F14: Antigua Guatemala | G14: 70.820475 | H14: 5 | I14: 9514.2496 | J14: 60608 | K14: 0.1273 | L14: 78 | M14: 1
B15: 13 | C15: 1 | D15: GUATEMALA | E15: 113 | F15: Fraijanes | G15: 70.801771 | H15: 6 | I15: 16475.126 | J15: 64519 | K15: 0.0692 | L15: 96 | M15: 0.75156791
B16: 15 | C16: 1 | D16: GUATEMALA | E16: 115 | F16: Villa Nueva | G16: 70.751706 | H16: 7 | I16: 11333.587 | J16: 492480 | K16: 0.059 | L16: 114 | M16: 0.98402329
B17: 33 | C17: 3 | D17: SACATEPEQUEZ | E17: 308 | F17: San Lucas Sacatepéquez | G17: 69.024305 | H17: 8 | I17: 12885.563 | J17: 29549 | K17: 0.1146 | L17: 5 | M17: 0.8858844
B18: 27 | C18: 3 | D18: SACATEPEQUEZ | E18: 302 | F18: Jocotenango | G18: 67.898638 | H18: 9 | I18: 4875.6138 | J18: 24144 | K18: 0.0837 | L18: 9 | M18: 0.8892391
B19: 16 | C19: 1 | D19: GUATEMALA | E19: 116 | F19: Villa Canales | G19: 67.712181 | H19: 10 | I19: 9203.2103 | J19: 168680 | K19: 0.0373 | L19: 160 | M19: 0.80523873
B20: 9 | C20: 1 | D20: GUATEMALA | E20: 109 | F20: San Pedro Sacatepéquez | G20: 67.079 | H20: 11 | I20: 9364.7475 | J20: 57362 | K20: 0.7653 | L20: 48 | M20: 0.72284181
B21: 3 | C21: 1 | D21: GUATEMALA | E21: 103 | F21: San José Pinula | G21: 67.050387 | H21: 12 | I21: 5706.5877 | J21: 90247 | K21: 0.0503 | L21: 220 | M21: 0.84641673
... B349: 234 | C349: 14 | D349: QUICHE | E349: 1405 | F349: Chajul | G349: 35.67105 | H349: 340 | I349: 1260.7837 | J349: 54355 | K349: 0.9156 | L349: 1524 | M349: 0.52343554
C351: 0 | D351: REPUBLICA | E351: 0 | G351: 56.501748 | I351: 6676.3278 | J351: 17602431 | K351: 0.4399 | L351: 108888.94 | M351: 0.5393545
C352: 1 | D352: GUATEMALA | E352: 100 | G352: 72.680385 | H352: 1 | I352: 14654.865 | J352: 3639725 | K352: 0.1449 | L352: 2126 | M352: 0.91286255
C353: 2 | D353: EL_PROGRESO | E353: 200 | G353: 55.222036 | H353: 5 | I353: 5502.5834 | J353: 196917 | K353: 0.0181 | L353: 1922 | M353: 0.52145903
C354: 3 | D354: SACATEPEQUEZ | E354: 300 | G354: 62.735935 | H354: 2 | I354: 6413.8096 | J354: 408476 | K354: 0.4096 | L354: 465 | M354: 0.88407387
C355: 4 | D355: CHIMALTENANGO | E355: 400 | G355: 49.971522 | H355: 14 | I355: 2841.711 | J355: 771887 | K355: 0.7862 | L355: 1979 | M355: 0.54332701
C356: 5 | D356: ESCUINTLA | E356: 500 | G356: 56.50077 | H356: 3 | I356: 10861.055 | J356: 823684 | K356: 0.0563 | L356: 4384 | M356: 0.61444991
C357: 6 | D357: SANTA_ROSA | E357: 600 | G357: 50.913855 | H357: 10 | I357: 4447.2812 | J357: 456928 | K357: 0.1676 | L357: 2955 | M357: 0.46716508
C358: 7 | D358: SOLOLA | E358: 700 | G358: 49.184076 | H358: 15 | I358: 3253.9791 | J358: 487906 | K358: 0.9667 | L358: 1061 | M358: 0.61772731
C359: 8 | D359: TOTONICAPAN | E359: 800 | G359: 44.66202 | H359: 19 | I359: 3705.3634 | J359: 507905 | K359: 0.982 | L359: 1061 | M359: 0.49062965
C360: 9 | D360: QUETZALTENANGO | E360: 900 | G360: 52.056907 | H360: 6 | I360: 7089.646 | J360: 936385 | K360: 0.5134 | L360: 1951 | M360: 0.61723814
C361: 10 | D361: SUCHITEPEQUEZ | E361: 1000 | G361: 50.225065 | H361: 13 | I361: 4277.2876 | J361: 626419 | K361: 0.3898 | L361: 2510 | M361: 0.48276779
C362: 11 | D362: RETALHULEU | E362: 1100 | G362: 50.541497 | H362: 12 | I362: 5334.3289 | J362: 386783 | K362: 0.1538 | L362: 1856 | M362: 0.57773431
C363: 12 | D363: SAN_MARCOS | E363: 1200 | G363: 46.318867 | H363: 17 | I363: 4681.3898 | J363: 1222951 | K363: 0.3104 | L363: 3791 | M363: 0.25614401
... C373: 22 | D373: JUTIAPA | E373: 2200 | G373: 51.951018 | H373: 7 | I373: 3875.9549 | J373: 563958 | K373: 0.209 | L373: 3219 | M373: 0.51543781
C375: 0 | D375: CIUDADES_INTERMEDIAS | G375: 63.27797 | I375: 11703.733 | J375: 6274407 | K375: 0.22691472 | L375: 20745 | M375: 0.80491224
C376: 1 | D376: NODO_REGIONAL | F376: AREA_METROPOLITANA | G376: 74.130042 | H376: 1 | I376: 16445.574 | J376: 2995219 | K376: 0.082218621 | L376: 1051 | M376: 0.96281288
C377: 2 | D377: CIUDAD_TURISTICA | F377: ANTIGUA_GUATEMALA | G377: 63.292104 | H377: 2 | I377: 5479.6404 | J377: 238138 | K377: 0.29259781 | L377: 369 | M377: 0.9383388
C378: 3 | D378: CIUDAD_PORTUARIA | F378: PUERTO_SAN_JOSE | G378: 56.660045 | H378: 5 | I378: 12681.478 | J378: 495196 | K378: 0.038008216 | L378: 2195 | M378: 0.64882954
C379: 4 | D379: NODO_REGIONAL | F379: LOS_ALTOS | G379: 58.342997 | H379: 3 | I379: 8711.4755 | J379: 475393 | K379: 0.6508448 | L379: 348 | M379: 0.81895003
C380: 5 | D380: NODO_REGIONAL | F380: GUATEMAGICA | G380: 51.512563 | H380: 8 | I380: 6423.4079 | J380: 493006 | K380: 0.11853179 | L380: 2264 | M380: 0.63699753
C381: 6 | D381: NODO_REGIONAL | F381: HUEHUETENANGO | G381: 49.136108 | H381: 9 | I381: 3959.905 | J381: 235078 | K381: 0.08615947 | L381: 697 | M381: 0.63049546
C382: 7 | D382: NODO_REGIONAL | F382: VERAPACES | G382: 42.006502 | H382: 10 | I382: 4483.3962 | J382: 689668 | K382: 0.91423686 | L382: 3534 | M382: 0.4464802
C383: 8 | D383: CIUDAD_TURISTICA | F383: PETEN | G383: 56.427304 | H383: 6 | I383: 8589.5139 | J383: 100625 | K383: 0.078013988 | L383: 4448 | M383: 0.88914793
C384: 9 | D384: CIUDAD_PORTUARIA | F384: PUERTO_BARRIOS | G384: 52.462797 | H384: 7 | I384: 7984.5427 | J384: 306099 | K384: 0.19053152 | L384: 4527 | M384: 0.52144045
C385: 10 | D385: NODO_REGIONAL | F385: ORIENTE | G385: 57.849741 | H385: 4 | I385: 7934.1817 | J385: 245985 | K385: 0.017085095 | L385: 1312 | M385: 0.86660274

Sheet ICL 2024 (12 pilares)
D2: ÍNDICE DE COMPETITIVIDAD LOCAL
D4: Fundación para el Desarrollo de Guatemala - FUNDESA -
D5: PILARES 1 a 12: Resumen e Integración
D6: (valores en escala de 0 -negativo- a 100 -positivo-)
H7: 1 | I7: 2 | J7: 3 | K7: 4 | L7: 5 | M7: 6 | N7: 7 | O7: 8 | P7: 9 | Q7: 10 | R7: 11 | S7: 12
B9: NO. | C9: CÓDIGO DEPARTAMENTO | D9: DEPARTAMENTO | E9: CÓDIGO MUNICIPIO | F9: MUNICIPIO | G9: ICL 2024 | H9: INSTITUCIONES | I9: INFRAESTRUCTURA | J9: ADOPCIÓN DE TICs | K9: ENTORNO ECONÓMICO | L9: SALUD | M9: FUERZA LABORAL Y TALENTO | N9: INVERSIÓN PRODUCTIVA | O9: MERCADO LABORAL | P9: SISTEMA FINANCIERO | Q9: TAMAÑO DEL MERCADO | R9: DINAMISMO DE LOS NEGOCIOS | S9: CAPACIDAD DE INNOVACIÓN
B10: 1 | C10: 1 | D10: GUATEMALA | E10: 101 | F10: Guatemala | G10: 79.015635 | H10: 63.020156 | I10: 83.406544 | J10: 91.937435 | K10: 71.965838 | L10: 100 | M10: 71.109202 | N10: 47.485444 | O10: 88.723663 | P10: 81.77624 | Q10: 71.785304 | R10: 97.962154 | S10: 100
B11: 2 | C11: 1 | D11: GUATEMALA | E11: 102 | F11: Santa Catarina Pinula | G11: 72.003823 | H11: 55.210101 | I11: 80.621535 | J11: 97.018252 | K11: 73.388915 | L11: 51.193315 | M11: 51.500824 | N11: 97.131292 | O11: 83.083501 | P11: 85.959279 | Q11: 44.984588 | R11: 71.950454 | S11: 0
B12: 3 | C12: 1 | D12: GUATEMALA | E12: 103 | F12: San José Pinula | G12: 67.050387 | H12: 51.832904 | I12: 81.194054 | J12: 72.630748 | K12: 72.580986 | L12: 51.407344 | M12: 54.686963 | N12: 81.543345 | O12: 78.747203 | P12: 100 | Q12: 29.277801 | R12: 63.652905 | S12: 0
B13: 4 | C13: 1 | D13: GUATEMALA | E13: 104 | F13: San José Del Golfo | G13: 66.261395 | H13: 59.83803 | I13: 81.750942 | J13: 57.398469 | K13: 69.83963 | L13: 58.835302 | M13: 59.108929 | N13: 100 | O13: 74.585141 | P13: 100 | Q13: 5.2376046 | R13: 62.281303 | S13: 0
B14: 5 | C14: 1 | D14: GUATEMALA | E14: 105 | F14: Palencia | G14: 60.606081 | H14: 57.801265 | I14: 75.894171 | J14: 31.289931 | K14: 61.232854 | L14: 52.308548 | M14: 47.654074 | N14: 97.462168 | O14: 75.283632 | P14: 100 | Q14: 5.5867893 | R14: 62.153452 | S14: 0
B15: 6 | C15: 1 | D15: GUATEMALA | E15: 106 | F15: Chinautla | G15: 66.667577 | H15: 56.746811 | I15: 78.206332 | J15: 69.743507 | K15: 72.914556 | L15: 51.777239 | M15: 48.563217 | N15: 85.616338 | O15: 74.751047 | P15: 100 | Q15: 39.038639 | R15: 55.985659 | S15: 0
B16: 7 | C16: 1 | D16: GUATEMALA | E16: 107 | F16: San Pedro Ayampuc | G16: 61.609089 | H16: 48.620826 | I16: 66.758686 | J16: 58.620379 | K16: 68.849843 | L16: 51.55114 | M16: 41.603123 | N16: 92.25494 | O16: 73.504828 | P16: 100 | Q16: 19.186183 | R16: 56.750037 | S16: 0
B17: 8 | C17: 1 | D17: GUATEMALA | E17: 108 | F17: Mixco | G17: 72.164621 | H17: 61.154067 | I17: 82.932825 | J17: 95.643939 | K17: 71.01712 | L17: 51.072555 | M17: 60.235636 | N17: 72.97318 | O17: 83.948307 | P17: 94.752121 | Q17: 48.505846 | R17: 71.575235 | S17: 0
B18: 9 | C18: 1 | D18: GUATEMALA | E18: 109 | F18: San Pedro Sacatepéquez | G18: 67.079 | H18: 70.323934 | I18: 77.509198 | J18: 76.412956 | K18: 66.506876 | L18: 46.634857 | M18: 40.16841 | N18: 91.914048 | O18: 74.203015 | P18: 100 | Q18: 30.96274 | R18: 63.232968 | S18: 0
B19: 10 | C19: 1 | D19: GUATEMALA | E19: 110 | F19: San Juan Sacatepéquez | G19: 60.982244 | H19: 74.055659 | I19: 71.959931 | J19: 40.215115 | K19: 61.478463 | L19: 39.984394 | M19: 43.771895 | N19: 76.094304 | O19: 74.091187 | P19: 100 | Q19: 28.254686 | R19: 60.899048 | S19: 0
B20: 11 | C20: 1 | D20: GUATEMALA | E20: 111 | F20: San Raymundo | G20: 62.474739 | H20: 74.71297 | I20: 75.566307 | J20: 30.08153 | K20: 57.498619 | L20: 50.223132 | M20: 53.684327 | N20: 97.266907 | O20: 73.74363 | P20: 100 | Q20: 12.539634 | R20: 61.905076 | S20: 0
B21: 12 | C21: 1 | D21: GUATEMALA | E21: 112 | F21: Chuarrancho | G21: 59.648101 | H21: 70.139924 | I21: 74.434343 | J21: 18.230262 | K21: 62.376707 | L21: 50.806709 | M21: 34.736423 | N21: 100 | O21: 73.835674 | P21: 100 | Q21: 11.780576 | R21: 59.788494 | S21: 0
... B349: 340 | C349: 22 | D349: JUTIAPA | E349: 2217 | F349: Quesada | G349: 55.412217 | H349: 70.555221 | I349: 73.175578 | J349: 40.618631 | K349: 50.86352 | L349: 53.19485 | M349: 49.011415 | N349: 50.797283 | O349: 58.589623 | P349: 84.650891 | Q349: 23.598206 | R349: 54.479169 | S349: 0
C351: 0 | D351: REPUBLICA | E351: 0 | G351: 56.501748 | H351: 55.712844 | I351: 72.677546 | J351: 25.35294 | K351: 59.342055 | L351: 50.33246 | M351: 48.680911 | N351: 50.532556 | O351: 69.867749 | P351: 89.969114 | Q351: 31.663287 | R351: 67.387768 | S351: 0
C352: 1 | D352: GUATEMALA | E352: 100 | G352: 72.680385 | H352: 59.234972 | I352: 80.874823 | J352: 89.548043 | K352: 73.230795 | L352: 75.867125 | M352: 60.699556 | N352: 57.362597 | O352: 89.204357 | P352: 90.742243 | Q352: 43.539432 | R352: 79.180297 | S352: 81.053887
C353: 2 | D353: EL_PROGRESO | E353: 200 | G353: 55.222036 | H353: 62.857283 | I353: 73.943895 | J353: 25.945493 | K353: 64.399435 | L353: 58.304458 | M353: 51.154282 | N353: 44.705866 | O353: 69.673362 | P353: 62.079096 | Q353: 31.297193 | R353: 63.082028 | S353: 0
C354: 3 | D354: SACATEPEQUEZ | E354: 300 | G354: 62.735935 | H354: 51.181049 | I354: 81.369362 | J354: 56.231272 | K354: 76.112058 | L354: 51.657344 | M354: 49.406051 | N354: 44.215444 | O354: 77.507394 | P354: 69.075865 | Q354: 67.806218 | R354: 65.533232 | S354: 0
C355: 4 | D355: CHIMALTENANGO | E355: 400 | G355: 49.971522 | H355: 56.024252 | I355: 73.514673 | J355: 24.626034 | K355: 72.162278 | L355: 39.498819 | M355: 43.043772 | N355: 42.780189 | O355: 56.592018 | P355: 79.632786 | Q355: 7.3885738 | R355: 54.423345 | S355: 0
C356: 5 | D356: ESCUINTLA | E356: 500 | G356: 56.50077 | H356: 42.796039 | I356: 69.124143 | J356: 26.21342 | K356: 76.555782 | L356: 57.957072 | M356: 59.129836 | N356: 40.836248 | O356: 88.793012 | P356: 52.477416 | Q356: 37.40745 | R356: 70.218055 | S356: 0
C357: 6 | D357: SANTA_ROSA | E357: 600 | G357: 50.913855 | H357: 63.35852 | I357: 68.495322 | J357: 26.450532 | K357: 49.724896 | L357: 63.145352 | M357: 42.724099 | N357: 31.835789 | O357: 57.83469 | P357: 66.855818 | Q357: 29.515233 | R357: 60.112158 | S357: 0
C358: 7 | D358: SOLOLA | E358: 700 | G358: 49.184076 | H358: 67.044948 | I358: 69.510127 | J358: 24.172315 | K358: 59.810109 | L358: 36.11885 | M358: 45.573851 | N358: 42.290247 | O358: 46.666328 | P358: 74.347601 | Q358: 18.60115 | R358: 56.88931 | S358: 0
C359: 8 | D359: TOTONICAPAN | E359: 800 | G359: 44.66202 | H359: 76.575837 | I359: 56.514775 | J359: 20.954942 | K359: 60.050949 | L359: 29.977595 | M359: 37.174307 | N359: 31.937782 | O359: 40.74521 | P359: 60.834415 | Q359: 19.256203 | R359: 57.260208 | S359: 0
C360: 9 | D360: QUETZALTENANGO | E360: 900 | G360: 52.056907 | H360: 53.083693 | I360: 60.717072 | J360: 37.366973 | K360: 68.946763 | L360: 49.193517 | M360: 49.724693 | N360: 32.5912 | O360: 61.004402 | P360: 67.547538 | Q360: 25.899638 | R360: 66.550493 | S360: 0
C361: 10 | D361: SUCHITEPEQUEZ | E361: 1000 | G361: 50.225065 | H361: 62.698016 | I361: 58.093536 | J361: 25.517268 | K361: 64.721127 | L361: 48.119495 | M361: 45.183408 | N361: 34.270365 | O361: 66.367503 | P361: 65.2957 | Q361: 21.686662 | R361: 60.522639 | S361: 0
C362: 11 | D362: RETALHULEU | E362: 1100 | G362: 50.541497 | H362: 56.713171 | I362: 48.54767 | J362: 26.264584 | K362: 66.487842 | L362: 54.227296 | M362: 54.967365 | N362: 32.697774 | O362: 65.884417 | P362: 63.919746 | Q362: 21.267424 | R362: 64.979175 | S362: 0
... C373: 22 | D373: JUTIAPA | E373: 2200 | G373: 51.951018 | H373: 67.359171 | I373: 70.442039 | J373: 26.47917 | K373: 49.400741 | L373: 56.20159 | M373: 44.696516 | N373: 32.911694 | O373: 60.351822 | P373: 80.042821 | Q373: 24.833667 | R373: 58.741962 | S373: 0
C375: 0 | D375: CIUDADES_INTERMEDIAS | G375: 63.27797 | H375: 47.796467 | I375: 69.040129 | J375: 42.57307 | K375: 69.967288 | L375: 69.460911 | M375: 57.941942 | N375: 55.990631 | O375: 81.08552 | P375: 87.577059 | Q375: 38.788213 | R375: 75.836438 | S375: 65.945949
C376: 1 | D376: NODO_REGIONAL | F376: AREA_METROPOLITANA | G376: 74.130042 | H376: 60.732009 | I376: 80.84134 | J376: 93.11648 | K376: 72.949693 | L376: 81.10166 | M376: 62.344458 | N376: 56.696373 | O376: 89.257435 | P376: 88.347574 | Q376: 47.95885 | R376: 82.084587 | S376: 91.337961
C377: 2 | D377: CIUDAD_TURISTICA | F377: ANTIGUA_GUATEMALA | G377: 63.292104 | H377: 49.39039 | I377: 81.272794 | J377: 48.744616 | K377: 76.516457 | L377: 59.979624 | M377: 51.457753 | N377: 45.586032 | O377: 77.847692 | P377: 73.393419 | Q377: 67.380518 | R377: 64.643848 | S377: 0
C378: 3 | D378: CIUDAD_PORTUARIA | F378: PUERTO_SAN_JOSE | G378: 56.660045 | H378: 42.524199 | I378: 67.81123 | J378: 28.684344 | K378: 77.177498 | L378: 60.497069 | M378: 60.857517 | N378: 37.535926 | O378: 88.834418 | P378: 51.225632 | Q378: 37.573918 | R378: 70.538745 | S378: 0
C379: 4 | D379: NODO_REGIONAL | F379: LOS_ALTOS | G379: 58.342997 | H379: 58.287442 | I379: 66.110036 | J379: 72.831074 | K379: 77.012105 | L379: 57.309822 | M379: 54.014559 | N379: 28.861154 | O379: 61.956578 | P379: 62.191823 | Q379: 34.14898 | R379: 69.049396 | S379: 0
C380: 5 | D380: NODO_REGIONAL | F380: GUATEMAGICA | G380: 51.512563 | H380: 47.108486 | I380: 51.432394 | J380: 30.281418 | K380: 69.523799 | L380: 66.518538 | M380: 57.529563 | N380: 30.670546 | O380: 66.177294 | P380: 62.348936 | Q380: 17.771391 | R380: 67.275826 | S380: 0
C381: 6 | D381: NODO_REGIONAL | F381: HUEHUETENANGO | G381: 49.136108 | H381: 67.131903 | I381: 58.810776 | J381: 32.323615 | K381: 60.058556 | L381: 61.653564 | M381: 47.453932 | N381: 16.676706 | O381: 50.729546 | P381: 60.118366 | Q381: 21.480707 | R381: 64.059523 | S381: 0
C382: 7 | D382: NODO_REGIONAL | F382: VERAPACES | G382: 42.006502 | H382: 62.948998 | I382: 56.129971 | J382: 15.457149 | K382: 36.619092 | L382: 44.692018 | M382: 35.604817 | N382: 21.51754 | O382: 56.20378 | P382: 39.254007 | Q382: 33.237789 | R382: 60.40636 | S382: 0
C383: 8 | D383: CIUDAD_TURISTICA | F383: PETEN | G383: 56.427304 | H383: 53.677553 | I383: 69.804509 | J383: 28.971129 | K383: 69.558973 | L383: 94.886676 | M383: 61.278533 | N383: 23.021192 | O383: 72.839753 | P383: 37.573949 | Q383: 38.13503 | R383: 70.953045 | S383: 0
C384: 9 | D384: CIUDAD_PORTUARIA | F384: PUERTO_BARRIOS | G384: 52.462797 | H384: 57.486252 | I384: 65.733709 | J384: 26.017171 | K384: 64.192895 | L384: 67.209545 | M384: 51.76331 | N384: 27.390223 | O384: 74.867019 | P384: 39.671565 | Q384: 34.392124 | R384: 68.366958 | S384: 0
C385: 10 | D385: NODO_REGIONAL | F385: ORIENTE | G385: 57.849741 | H385: 81.0502 | I385: 76.939949 | J385: 32.586419 | K385: 66.493812 | L385: 62.690736 | M385: 55.039454 | N385: 27.54986 | O385: 73.612727 | P385: 60.681754 | Q385: 28.222201 | R385: 71.480037 | S385: 0

Sheet ICL 2023 (12 pilares)
D2: ÍNDICE DE COMPETITIVIDAD LOCAL
D4: Fundación para el Desarrollo de Guatemala - FUNDESA -
D5: PILARES 1 a 12: Resumen e Integración
D6: (valores en escala de 0 -negativo- a 100 -positivo-)
H7: 1 | I7: 2 | J7: 3 | K7: 4 | L7: 5 | M7: 6 | N7: 7 | O7: 8 | P7: 9 | Q7: 10 | R7: 11 | S7: 12
B9: NO. | C9: CÓDIGO DEPARTAMENTO | D9: DEPARTAMENTO | E9: CÓDIGO MUNICIPIO | F9: MUNICIPIO | G9: ICL 2023 | H9: INSTITUCIONES | I9: INFRAESTRUCTURA | J9: ADOPCIÓN DE TICs | K9: ENTORNO ECONÓMICO | L9: SALUD | M9: FUERZA LABORAL Y TALENTO | N9: INVERSIÓN PRODUCTIVA | O9: MERCADO LABORAL | P9: SISTEMA FINANCIERO | Q9: TAMAÑO DEL MERCADO | R9: DINAMISMO DE LOS NEGOCIOS | S9: CAPACIDAD DE INNOVACIÓN
B10: 1 | C10: 1 | D10: GUATEMALA | E10: 101 | F10: Guatemala | G10: 78.722893 | H10: 62.547426 | I10: 82.986585 | J10: 92.216914 | K10: 68.318666 | L10: 100 | M10: 66.164609 | N10: 48.952481 | O10: 91.249888 | P10: 83.121577 | Q10: 72.431525 | R10: 97.962154 | S10: 100
B11: 2 | C11: 1 | D11: GUATEMALA | E11: 102 | F11: Santa Catarina Pinula | G11: 72.028875 | H11: 52.48098 | I11: 80.20491 | J11: 97.209313 | K11: 70.123424 | L11: 51.375311 | M11: 50.603928 | N11: 99.902096 | O11: 84.996506 | P11: 87.879287 | Q11: 45.598861 | R11: 71.943004 | S11: 0
B12: 3 | C12: 1 | D12: GUATEMALA | E12: 103 | F12: San José Pinula | G12: 64.635782 | H12: 51.902802 | I12: 80.769095 | J12: 56.052809 | K12: 60.184574 | L12: 51.490185 | M12: 55.212991 | N12: 83.040003 | O12: 80.783042 | P12: 100 | Q12: 27.643814 | R12: 63.91429 | S12: 0
B13: 4 | C13: 1 | D13: GUATEMALA | E13: 104 | F13: San José Del Golfo | G13: 64.167365 | H13: 66.95834 | I13: 81.29765 | J13: 38.221381 | K13: 56.234802 | L13: 60.810807 | M13: 57.686887 | N13: 100 | O13: 76.438951 | P13: 100 | Q13: 5.8810638 | R13: 62.311137 | S13: 0
B14: 5 | C14: 1 | D14: GUATEMALA | E14: 105 | F14: Palencia | G14: 62.609445 | H14: 64.895078 | I14: 75.424213 | J14: 45.809196 | K14: 44.142128 | L14: 52.166712 | M14: 45.373608 | N14: 100 | O14: 78.076054 | P14: 100 | Q14: 20.412533 | R14: 62.404367 | S14: 0
B15: 6 | C15: 1 | D15: GUATEMALA | E15: 106 | F15: Chinautla | G15: 68.019652 | H15: 61.886297 | I15: 77.756373 | J15: 90.370683 | K15: 67.754945 | L15: 51.789021 | M15: 45.088958 | N15: 83.632251 | O15: 77.543702 | P15: 100 | Q15: 36.100864 | R15: 56.293081 | S15: 0
B16: 7 | C16: 1 | D16: GUATEMALA | E16: 107 | F16: San Pedro Ayampuc | G16: 58.802089 | H16: 35.149406 | I16: 66.288727 | J16: 55.909941 | K16: 52.319626 | L16: 51.413104 | M16: 37.820916 | N16: 100 | O16: 75.893676 | P16: 100 | Q16: 14.754705 | R16: 57.272877 | S16: 0
B17: 8 | C17: 1 | D17: GUATEMALA | E17: 108 | F17: Mixco | G17: 72.688283 | H17: 63.265744 | I17: 82.507866 | J17: 100 | K17: 67.115495 | L17: 51.435875 | M17: 59.295239 | N17: 72.197951 | O17: 85.799568 | P17: 97.186291 | Q17: 49.108799 | R17: 71.658286 | S17: 0
B18: 9 | C18: 1 | D18: GUATEMALA | E18: 109 | F18: San Pedro Sacatepéquez | G18: 65.514498 | H18: 71.263364 | I18: 77.092572 | J18: 76.794588 | K18: 47.816639 | L18: 47.438082 | M18: 36.783556 | N18: 88.321855 | O18: 76.865733 | P18: 100 | Q18: 34.932906 | R18: 63.350181 | S18: 0
B19: 10 | C19: 1 | D19: GUATEMALA | E19: 110 | F19: San Juan Sacatepéquez | G19: 60.614883 | H19: 72.584988 | I19: 71.529972 | J19: 53.851148 | K19: 41.854693 | L19: 40.260788 | M19: 41.458017 | N19: 73.774343 | O19: 76.943313 | P19: 100 | Q19: 33.433038 | R19: 61.073412 | S19: 0
B20: 11 | C20: 1 | D20: GUATEMALA | E20: 111 | F20: San Raymundo | G20: 60.544509 | H20: 74.011589 | I20: 75.149681 | J20: 38.039661 | K20: 39.034468 | L20: 50.609893 | M20: 52.801795 | N20: 93.250911 | O20: 75.023024 | P20: 100 | Q20: 6.2414028 | R20: 61.827174 | S20: 0
B21: 12 | C21: 1 | D21: GUATEMALA | E21: 112 | F21: Chuarrancho | G21: 58.503747 | H21: 70.130616 | I21: 73.86605 | J21: 22.697636 | K21: 43.861961 | L21: 52.963512 | M21: 36.893977 | N21: 100 | O21: 75.851072 | P21: 100 | Q21: 7.4084253 | R21: 59.867963 | S21: 0
... B349: 340 | C349: 22 | D349: JUTIAPA | E349: 2217 | F349: Quesada | G349: 56.580528 | H349: 72.600663 | I349: 73.104024 | J349: 48.907847 | K349: 51.370483 | L349: 53.075486 | M349: 47.595772 | N349: 50.265962 | O349: 61.687525 | P349: 84.127525 | Q349: 24.857176 | R349: 54.79335 | S349: 0
C351: 0 | D351: REPUBLICA | E351: 0 | G351: 56.69944 | H351: 55.321127 | I351: 72.25243 | J351: 28.495078 | K351: 53.978545 | L351: 52.258655 | M351: 47.050902 | N351: 50.030404 | O351: 72.670931 | P351: 91.710479 | Q351: 32.35818 | R351: 67.567104 | S351: 0
C352: 1 | D352: GUATEMALA | E352: 100 | G352: 73.078197 | H352: 59.180653 | I352: 80.424864 | J352: 89.992698 | K352: 69.922895 | L352: 80.173454 | M352: 58.255616 | N352: 57.627038 | O352: 91.964521 | P352: 92.902177 | Q352: 44.185967 | R352: 79.230288 | S352: 80.541269
C353: 2 | D353: EL_PROGRESO | E353: 200 | G353: 56.344762 | H353: 67.863921 | I353: 73.458154 | J353: 28.762571 | K353: 57.86645 | L353: 59.575197 | M353: 46.972708 | N353: 42.876932 | O353: 73.100959 | P353: 70.797932 | Q353: 35.151422 | R353: 63.366137 | S353: 0
C354: 3 | D354: SACATEPEQUEZ | E354: 300 | G354: 65.248254 | H354: 55.401862 | I354: 80.704794 | J354: 77.394329 | K354: 70.600991 | L354: 53.12482 | M354: 48.628133 | N354: 44.066814 | O354: 82.777193 | P354: 71.656883 | Q354: 67.799428 | R354: 65.575547 | S354: 0
C355: 4 | D355: CHIMALTENANGO | E355: 400 | G355: 49.038061 | H355: 58.611328 | I355: 73.383927 | J355: 29.57596 | K355: 56.935182 | L355: 40.574364 | M355: 41.846144 | N355: 39.226196 | O355: 57.592768 | P355: 79.992743 | Q355: 6.9413684 | R355: 54.738695 | S355: 0
C356: 5 | D356: ESCUINTLA | E356: 500 | G356: 55.923106 | H356: 49.083972 | I356: 69.029143 | J356: 30.880893 | K356: 66.353731 | L356: 60.225464 | M356: 54.575079 | N356: 32.943651 | O356: 94.028455 | P356: 52.443737 | Q356: 34.657384 | R356: 70.932656 | S356: 0
C357: 6 | D357: SANTA_ROSA | E357: 600 | G357: 51.623907 | H357: 60.789684 | I357: 68.453656 | J357: 30.096478 | K357: 54.414739 | L357: 63.903671 | M357: 41.25788 | N357: 30.379412 | O357: 59.594949 | P357: 69.276751 | Q357: 29.33755 | R357: 60.358212 | S357: 0
C358: 7 | D358: SOLOLA | E358: 700 | G358: 47.176688 | H358: 64.96971 | I358: 68.210669 | J358: 31.055063 | K358: 47.890767 | L358: 34.50082 | M358: 44.916871 | N358: 37.453443 | O358: 46.143097 | P358: 73.512431 | Q358: 13.231738 | R358: 57.058954 | S358: 0
C359: 8 | D359: TOTONICAPAN | E359: 800 | G359: 43.943548 | H359: 80.094933 | I359: 56.227577 | J359: 26.17664 | K359: 47.768074 | L359: 31.405093 | M359: 36.069881 | N359: 28.963296 | O359: 38.32965 | P359: 61.165989 | Q359: 19.643238 | R359: 57.53466 | S359: 0
C360: 9 | D360: QUETZALTENANGO | E360: 900 | G360: 51.411829 | H360: 51.013632 | I360: 60.378513 | J360: 46.452804 | K360: 54.612683 | L360: 51.369255 | M360: 49.132941 | N360: 28.804187 | O360: 61.218024 | P360: 69.422146 | Q360: 26.479318 | R360: 66.646616 | S360: 0
C361: 10 | D361: SUCHITEPEQUEZ | E361: 1000 | G361: 49.635219 | H361: 61.687299 | I361: 57.891138 | J361: 29.704836 | K361: 54.350586 | L361: 48.628025 | M361: 43.995013 | N361: 31.389639 | O361: 69.47728 | P361: 66.318997 | Q361: 21.675125 | R361: 60.869467 | S361: 0
C362: 11 | D362: RETALHULEU | E362: 1100 | G362: 50.624933 | H362: 57.296677 | I362: 48.455622 | J362: 30.577333 | K362: 58.569871 | L362: 55.213048 | M362: 53.005858 | N362: 33.732949 | O362: 67.775323 | P362: 64.382519 | Q362: 22.358954 | R362: 65.506112 | S362: 0
... C373: 22 | D373: JUTIAPA | E373: 2200 | G373: 53.154508 | H373: 69.732359 | I373: 70.230485 | J373: 30.434261 | K373: 48.485469 | L373: 57.821137 | M373: 42.478361 | N373: 31.685835 | O373: 63.499156 | P373: 80.922292 | Q373: 30.370947 | R373: 59.039283 | S373: 0
C375: 0 | D375: CIUDADES_INTERMEDIAS | G375: 63.957294 | H375: 48.183227 | I375: 68.582187 | J375: 50.965983 | K375: 62.200957 | L375: 73.108761 | M375: 55.850193 | N375: 55.542574 | O375: 84.514236 | P375: 89.518007 | Q375: 39.1444 | R375: 75.919703 | S375: 66.007263
C376: 1 | D376: NODO_REGIONAL | F376: AREA_METROPOLITANA | G376: 74.60102 | H376: 61.010118 | I376: 80.417493 | J376: 93.613448 | K376: 69.5664 | L376: 86.282958 | M376: 59.645502 | N376: 57.071492 | O376: 92.010817 | P376: 90.26208 | Q376: 48.607534 | R376: 82.123375 | S376: 91.689113
C377: 2 | D377: CIUDAD_TURISTICA | F377: ANTIGUA_GUATEMALA | G377: 65.524657 | H377: 54.761128 | I377: 80.589337 | J377: 65.285898 | K377: 70.716789 | L377: 62.283388 | M377: 50.930956 | N377: 44.715087 | O377: 82.975765 | P377: 76.408058 | Q377: 67.376448 | R377: 64.72837 | S377: 0
C378: 3 | D378: CIUDAD_PORTUARIA | F378: PUERTO_SAN_JOSE | G378: 56.58469 | H378: 50.058292 | I378: 67.717064 | J378: 34.72003 | K378: 66.707313 | L378: 63.361978 | M378: 56.347968 | N378: 32.111946 | O378: 94.173799 | P378: 51.201102 | Q378: 34.822143 | R378: 71.209954 | S378: 0
C379: 4 | D379: NODO_REGIONAL | F379: LOS_ALTOS | G379: 58.495752 | H379: 56.57667 | I379: 65.802289 | J379: 81.99772 | K379: 67.660136 | L379: 61.862801 | M379: 53.726606 | N379: 26.576343 | O379: 61.936361 | P379: 63.597676 | Q379: 34.648111 | R379: 69.068557 | S379: 0
C380: 5 | D380: NODO_REGIONAL | F380: GUATEMAGICA | G380: 51.474594 | H380: 52.02199 | I380: 51.259011 | J380: 35.369204 | K380: 60.068617 | L380: 65.989288 | M380: 55.928198 | N380: 29.811978 | O380: 67.076801 | P380: 63.311869 | Q380: 17.781012 | R380: 67.602565 | S380: 0
C381: 6 | D381: NODO_REGIONAL | F381: HUEHUETENANGO | G381: 48.822254 | H381: 61.267305 | I381: 58.778585 | J381: 35.903403 | K381: 57.936412 | L381: 64.994049 | M381: 48.756563 | N381: 13.896332 | O381: 49.571803 | P381: 50.654418 | Q381: 27.574191 | R381: 67.711731 | S381: 0
C382: 7 | D382: NODO_REGIONAL | F382: VERAPACES | G382: 41.81215 | H382: 59.535207 | I382: 55.683789 | J382: 17.045974 | K382: 35.777589 | L382: 46.261054 | M382: 34.048826 | N382: 20.19274 | O382: 58.263743 | P382: 39.008422 | Q382: 33.470858 | R382: 60.645455 | S382: 0
C383: 8 | D383: CIUDAD_TURISTICA | F383: PETEN | G383: 55.141917 | H383: 58.326391 | I383: 68.499014 | J383: 29.858289 | K383: 64.934693 | L383: 89.958308 | M383: 59.59539 | N383: 10.736637 | O383: 74.481706 | P383: 39.409771 | Q383: 40.145535 | R383: 70.615356 | S383: 0
C384: 9 | D384: CIUDAD_PORTUARIA | F384: PUERTO_BARRIOS | G384: 51.839714 | H384: 60.684267 | I384: 65.605931 | J384: 27.993456 | K384: 55.732483 | L384: 70.286795 | M384: 49.82135 | N384: 17.942306 | O384: 78.754514 | P384: 41.520145 | Q384: 33.31185 | R384: 68.583754 | S384: 0
C385: 10 | D385: NODO_REGIONAL | F385: ORIENTE | G385: 58.239528 | H385: 77.252913 | I385: 76.77445 | J385: 36.707003 | K385: 61.516275 | L385: 66.814567 | M385: 52.675417 | N385: 25.178652 | O385: 75.628129 | P385: 61.789193 | Q385: 35.02901 | R385: 71.269198 | S385: 0

Sheet ICL 2024 (Indicadores base 100)
D2: ÍNDICE DE COMPETITIVIDAD LOCAL
D4: Fundación para el Desarrollo de Guatemala - FUNDESA -
D5: PILARES 1 a 12: Indicadores
D6: (valores en escala de 0 -negativo- a 100 -positivo-)
G8: 1.1 | H8: 1.2 | I8: 1.3 | J8: 1.4 | K8: 1.5 | L8: 1.6 | M8: 2.1 | N8: 2.2 | O8: 2.3 | P8: 2.4 | Q8: 2.5 | R8: 2.6 | S8: 3.1 | T8: 3.2 | U8: 4.1 | V8: 4.2 | W8: 4.3 | X8: 5.1 | Y8: 5.2 | Z8: 6.1 | AA8: 6.2 | AB8: 6.3 | AC8: 6.4 | AD8: 6.5 | AE8: 7.1 | AF8: 7.2 | AG8: 8.1 | AH8: 8.2 | AI8: 8.3 | AJ8: 8.4 | AK8: 8.5 | AL8: 8.6 | AM8: 9.1 | AN8: 9.2 | AO8: 9.3 | AP8: 9.4 | AQ8: 10.1 | AR8: 10.2 | AS8: 10.3 | AT8: 11.1 | AU8: 11.2 | AV8: 11.3 | AW8: 12.1
B9: NO. | C9: CÓDIGO DEPARTAMENTO | D9: DEPARTAMENTO | E9: CÓDIGO MUNICIPIO | F9: MUNICIPIO | G9: Tasa de Extorsiones | H9: Tasa de Homicidios | I9: Faltas Judiciales | J9: Conflictividad | K9: Gestión Municipal | L9: Información Catastral | M9: Brecha de la RED VIAL | N9: Distancia Promedio a Aeropuertos | O9: Distancia Promedio a Puertos | P9: Tasa de Electrificación | Q9: Cobertura de Agua y Saneamiento | R9: Déficit de Vivienda | S9: Radiobases de Telefonía Celular por Km2 | T9: Usuarios de Internet | U9: Tasa de Inflación | V9: Tasa de Pobreza | W9: Coeficiente de GINI | X9: Gasto Público en Salud, per cápita (al año) | Y9: Tasa de Desnutrición Crónica | Z9: Gasto Público en Educación, per cápita (al año) | AA9: Tasa Neta de Cobertura (todos niveles) | AB9: Alumnos por Docente (todos niveles) | AC9: Capacitación Técnica (% de la PEA) | AD9: % de LOGRO Graduandos (Mate y Lectura) | AE9: Carga Tributaria Local (% PIB) | AF9: Inversión Pública (% Presupuesto Local) | AG9: % de la PEA afiliada al IGSS | AH9: Afiliados por Patrono Particular | AI9: Peso del Gobierno en la contratación | AJ9: Salario Mínimo como No. veces Ingreso Medio | AK9: Ingreso Medio como % del Salario Formal | AL9: Tasa de Deportados | AM9: Km2 a cargo de cada Agencia | AN9: Agentes Bancarios por 100,000 hab. | AO9: Depósitos en relación al PIB per cápita | AP9: Cartera de Créditos en relación al PIB | AQ9: PIB local (US$ al año por Km2) | AR9: Remesas como % del PIB | AS9: Tasa de Turistas | AT9: Costo Iniciar un Negocio (% PIB per cápita) | AU9: Tiempo Iniciar un Negocio (días) | AV9: Fuerza Laboral Sector Servicios (% de la PEA) | AW9: Inversión I+D (% presupuesto local)
B10: 1 | C10: 1 | D10: GUATEMALA | E10: 101 | F10: Guatemala | G10: 0 | H10: 65.635712 | I10: 100 | J10: 50 | K10: 62.485224 | L10: 100 | M10: 53.26557 | N10: 95.663253 | O10: 74.679328 | P10: 99.99 | Q10: 95.448822 | R10: 81.392289 | S10: 100 | T10: 83.87487 | U10: 56.692385 | V10: 100 | W10: 59.205128 | X10: 100 | Y10: 100 | Z10: 89.931539 | AA10: 100 | AB10: 92.974353 | AC10: 52.304284 | AD10: 20.335834 | AE10: 84.971157 | AF10: 9.9997304 | AG10: 100 | AH10: 100 | AI10: 89.923551 | AJ10: 100 | AK10: 49.9512 | AL10: 92.467228 | AM10: 100 | AN10: 100 | AO10: 27.10496 | AP10: 100 | AQ10: 100 | AR10: 100 | AS10: 15.355912 | AT10: 100 | AU10: 93.886463 | AV10: 100 | AW10: 100
B11: 2 | C11: 1 | D11: GUATEMALA | E11: 102 | F11: Santa Catarina Pinula | G11: 0 | H11: 69.708059 | I11: 64.496556 | J11: 50 | K11: 47.055993 | L11: 100 | M11: 53.26557 | N11: 93.801147 | O11: 73.669719 | P11: 100 | Q11: 82.493521 | R11: 80.499253 | S11: 100 | T11: 94.036504 | U11: 56.692385 | V11: 100 | W11: 63.474359 | X11: 2.3866293 | Y11: 100 | Z11: 21.786235 | AA11: 100 | AB11: 53.007626 | AC11: 52.939813 | AD11: 29.770445 | AE11: 100 | AF11: 94.262584 | AG11: 59.817496 | AH11: 100 | AI11: 89.923551 | AJ11: 100 | AK11: 49.9512 | AL11: 98.808758 | AM11: 100 | AN11: 100 | AO11: 43.837117 | AP11: 100 | AQ11: 19.597851 | AR11: 100 | AS11: 15.355912 | AT11: 98.351048 | AU11: 93.886463 | AV11: 23.61385 | AW11: 0
B12: 3 | C12: 1 | D12: GUATEMALA | E12: 103 | F12: San José Pinula | G12: 0 | H12: 85.922171 | I12: 33.792444 | J12: 50 | K12: 41.282808 | L12: 100 | M12: 53.26557 | N12: 91.903368 | O12: 73.575408 | P12: 99.89 | Q12: 82.910037 | R12: 85.619938 | S12: 74.772727 | T12: 70.48877 | U12: 56.692385 | V12: 99.948009 | W12: 61.102564 | X12: 2.8146884 | Y12: 100 | Z12: 25.749598 | AA12: 100 | AB12: 70.78734 | AC12: 56.968591 | AD12: 19.929283 | AE12: 100 | AF12: 63.08669 | AG12: 36.578393 | AH12: 100 | AI12: 89.923551 | AJ12: 100 | AK12: 49.9512 | AL12: 96.030072 | AM12: 100 | AN12: 100 | AO12: 100 | AP12: 100 | AQ12: 1.4138106 | AR12: 71.063679 | AS12: 15.355912 | AT12: 82.871566 | AU12: 93.886463 | AV12: 14.200687 | AW12: 0
B13: 4 | C13: 1 | D13: GUATEMALA | E13: 104 | F13: San José Del Golfo | G13: 12.40575 | H13: 77.012895 | I13: 100 | J13: 50 | K13: 19.609533 | L13: 100 | M13: 53.26557 | N13: 93.698894 | O13: 76.933114 | P13: 100 | Q13: 68.504966 | R13: 98.10311 | S13: 52.97619 | T13: 61.820748 | U13: 56.692385 | V13: 88.877787 | W13: 63.948718 | X13: 17.670604 | Y13: 100 | Z13: 45.469882 | AA13: 100 | AB13: 75.428739 | AC13: 69.517816 | AD13: 5.1282051 | AE13: 100 | AF13: 100 | AG13: 23.947483 | AH13: 100 | AI13: 89.923551 | AJ13: 100 | AK13: 49.9512 | AL13: 83.688614 | AM13: 100 | AN13: 100 | AO13: 100 | AP13: 100 | AQ13: 0.35690126 | AR13: 0 | AS13: 15.355912 | AT13: 83.872998 | AU13: 93.886463 | AV13: 9.0844472 | AW13: 0
B14: 5 | C14: 1 | D14: GUATEMALA | E14: 105 | F14: Palencia | G14: 0 | H14: 82.473573 | I14: 66.748885 | J14: 50 | K14: 47.585135 | L14: 100 | M14: 53.26557 | N14: 91.331602 | O14: 74.836041 | P14: 97.59 | Q14: 65.892252 | R14: 72.449564 | S14: 9.6938776 | T14: 52.885985 | U14: 56.692385 | V14: 65.429255 | W14: 61.576923 | X14: 6.1320937 | Y14: 98.485002 | Z14: 35.370382 | AA14: 86.844216 | AB14: 44.34345 | AC14: 66.453422 | AD14: 5.2588997 | AE14: 100 | AF14: 94.924336 | AG14: 22.214573 | AH14: 100 | AI14: 89.923551 | AJ14: 100 | AK14: 49.9512 | AL14: 89.612469 | AM14: 100 | AN14: 100 | AO14: 100 | AP14: 100 | AQ14: 1.4044554 | AR14: 0 | AS14: 15.355912 | AT14: 84.191374 | AU14: 93.886463 | AV14: 8.3825198 | AW14: 0
B15: 6 | C15: 1 | D15: GUATEMALA | E15: 106 | F15: Chinautla | G15: 19.602788 | H15: 80.079376 | I15: 42.676127 | J15: 50 | K15: 48.122575 | L15: 100 | M15: 53.26557 | N15: 92.232817 | O15: 73.97855 | P15: 99.11 | Q15: 85.500588 | R15: 65.150468 | S15: 59.375 | T15: 80.112014 | U15: 56.692385 | V15: 100 | W15: 62.051282 | X15: 3.554479 | Y15: 100 | Z15: 30.833764 | AA15: 98.649898 | AB15: 47.365349 | AC15: 59.108895 | AD15: 6.8581781 | AE15: 100 | AF15: 71.232676 | AG15: 9.8014371 | AH15: 100 | AI15: 89.923551 | AJ15: 100 | AK15: 49.9512 | AL15: 98.830092 | AM15: 100 | AN15: 100 | AO15: 100 | AP15: 100 | AQ15: 3.5094517 | AR15: 98.250551 | AS15: 15.355912 | AT15: 70.716024 | AU15: 93.886463 | AV15: 3.3544914 | AW15: 0
B16: 7 | C16: 1 | D16: GUATEMALA | E16: 107 | F16: San Pedro Ayampuc | G16: 0 | H16: 66.902045 | I16: 44.077694 | J16: 50 | K16: 30.745217 | L16: 100 | M16: 53.26557 | N16: 90.944122 | O16: 72.893675 | P16: 98.7 | Q16: 78.808158 | R16: 5.9405894 | S16: 67.123288 | T16: 50.11747 | U16: 56.692385 | V16: 88.28022 | W16: 61.576923 | X16: 3.1022803 | Y16: 100 | Z16: 33.002151 | AA16: 79.089629 | AB16: 28.32436 | AC16: 66.012173 | AD16: 1.5873016 | AE16: 100 | AF16: 84.509881 | AG16: 5.7561193 | AH16: 100 | AI16: 89.923551 | AJ16: 100 | AK16: 49.9512 | AL16: 95.398097 | AM16: 100 | AN16: 100 | AO16: 100 | AP16: 100 | AQ16: 2.3850273 | AR16: 39.817608 | AS16: 15.355912 | AT16: 74.64774 | AU16: 93.886463 | AV16: 1.7159068 | AW16: 0
B17: 8 | C17: 1 | D17: GUATEMALA | E17: 108 | F17: Mixco | G17: 0 | H17: 83.772744 | I17: 82.734864 | J17: 50 | K17: 50.416795 | L17: 100 | M17: 53.26557 | N17: 92.778773 | O17: 73.984397 | P17: 99.83 | Q17: 94.724318 | R17: 83.01389 | S17: 91.287879 | T17: 100 | U17: 56.692385 | V17: 100 | W17: 56.358974 | X17: 2.1451103 | Y17: 100 | Z17: 18.76409 | AA17: 100 | AB17: 99.438662 | AC17: 55.270084 | AD17: 27.705346 | AE17: 100 | AF17: 45.94636 | AG17: 65.595642 | AH17: 100 | AI17: 89.923551 | AJ17: 100 | AK17: 49.9512 | AL17: 98.219447 | AM17: 100 | AN17: 100 | AO17: 79.008485 | AP17: 100 | AQ17: 30.161627 | AR17: 100 | AS17: 15.355912 | AT17: 94.884914 | AU17: 93.886463 | AV17: 25.954329 | AW17: 0
B18: 9 | C18: 1 | D18: GUATEMALA | E18: 109 | F18: San Pedro Sacatepéquez | G18: 73.149472 | H18: 100 | I18: 72.370791 | J18: 50 | K18: 26.423341 | L18: 100 | M18: 53.26557 | N18: 90.307419 | O18: 71.765279 | P18: 100 | Q18: 75.024907 | R18: 74.692011 | S18: 100 | T18: 52.825913 | U18: 56.692385 | V18: 71.764141 | W18: 71.064103 | X18: 2.229814 | Y18: 91.039899 | Z18: 34.624912 | AA18: 94.478054 | AB18: 2.9651046 | AC18: 55.915423 | AD18: 12.858556 | AE18: 100 | AF18: 83.828096 | AG18: 11.99773 | AH18: 100 | AI18: 89.923551 | AJ18: 100 | AK18: 49.9512 | AL18: 93.345607 | AM18: 100 | AN18: 100 | AO18: 100 | AP18: 100 | AQ18: 6.8016696 | AR18: 70.730637 | AS18: 15.355912 | AT18: 91.568327 | AU18: 93.886463 | AV18: 4.2441154 | AW18: 0
B19: 10 | C19: 1 | D19: GUATEMALA | E19: 110 | F19: San Juan Sacatepéquez | G19: 59.397097 | H19: 99.306371 | I19: 91.668287 | J19: 50 | K19: 43.962198 | L19: 100 | M19: 53.26557 | N19: 89.179832 | O19: 70.75425 | P19: 99.7 | Q19: 60.378501 | R19: 58.481435 | S19: 44.008264 | T19: 36.421965 | U19: 56.692385 | V19: 65.217363 | W19: 62.525641 | X19: 1.5085462 | Y19: 78.460243 | Z19: 33.548859 | AA19: 81.103043 | AB19: 33.581805 | AC19: 65.446863 | AD19: 5.1789077 | AE19: 100 | AF19: 52.188607 | AG19: 9.7377928 | AH19: 100 | AI19: 89.923551 | AJ19: 100 | AK19: 49.9512 | AL19: 94.934579 | AM19: 100 | AN19: 100 | AO19: 100 | AP19: 100 | AQ19: 4.6726307 | AR19: 64.735515 | AS19: 15.355912 | AT19: 85.481968 | AU19: 93.886463 | AV19: 3.3287118 | AW19: 0
B20: 11 | C20: 1 | D20: GUATEMALA | E20: 111 | F20: San Raymundo | G20: 78.295423 | H20: 100 | I20: 97.447459 | J20: 50 | K20: 22.534938 | L20: 100 | M20: 53.26557 | N20: 87.213829 | O20: 69.436645 | P20: 99.71 | Q20: 72.024062 | R20: 71.747733 | S20: 25.438596 | T20: 34.724464 | U20: 56.692385 | V20: 57.547061 | W20: 58.25641 | X20: 6.1972693 | Y20: 94.248995 | Z20: 42.572386 | AA20: 97.74091 | AB20: 59.876889 | AC20: 64.890691 | AD20: 3.3407572 | AE20: 100 | AF20: 94.533814 | AG20: 12.437816 | AH20: 100 | AI20: 89.923551 | AJ20: 100 | AK20: 49.9512 | AL20: 90.149215 | AM20: 100 | AN20: 100 | AO20: 100 | AP20: 100 | AQ20: 1.4824677 | AR20: 20.780522 | AS20: 15.355912 | AT20: 87.406389 | AU20: 93.886463 | AV20: 4.4223754 | AW20: 0
B21: 12 | C21: 1 | D21: GUATEMALA | E21: 112 | F21: Chuarrancho | G21: 86.951214 | H21: 100 | I21: 62.143617 | J21: 50 | K21: 21.744714 | L21: 100 | M21: 53.26557 | N21: 85.458087 | O21: 68.807039 | P21: 98.22 | Q21: 81.797411 | R21: 59.057948 | S21: 12.755102 | T21: 23.705422 | U21: 56.692385 | V21: 58.424915 | W21: 72.012821 | X21: 5.9524196 | Y21: 95.660998 | Z21: 26.881185 | AA21: 64.770459 | AB21: 0 | AC21: 82.030473 | AD21: 0 | AE21: 100 | AF21: 100 | AG21: 10.676452 | AH21: 100 | AI21: 89.923551 | AJ21: 100 | AK21: 49.9512 | AL21: 92.46284 | AM21: 100 | AN21: 100 | AO21: 100 | AP21: 100 | AQ21: 0.57122191 | AR21: 19.414593 | AS21: 15.355912 | AT21: 81.770097 | AU21: 93.886463 | AV21: 3.7089222 | AW21: 0
... B101: 92 | C101: 7 | D101: SOLOLA | E101: 707 | F101: Santa Clara La Laguna | G101: 95.356037 | H101: 100 | I101: 48.366013 | J101: 8.3333333 | K101: 35.73174 | L101: 100 | M101: 89.624241 | N101: 44.983149 | O101: 41.051059 | P101: 99.46 | Q101: 88.991477 | R101: 65.4949 | S101: 29.166667 | T101: 40.752941 | U101: 53.872414 | V101: 62.988195 | W101: 63.333333 | X101: 8.0046716 | Y101: 45.946662 | Z101: 60.064652 | AA101: 83.319577 | AB101: 68.537641 | AC101: 13.521608 | AD101: 0 | AE101: 11.640814 | AF101: 100 | AG101: 13.455674 | AH101: 100 | AI101: 47.792823 | AJ101: 16.886511 | AK101: 5.5944847 | AL101: 91.138599 | AM101: 82.357724 | AN101: 100 | AO101: 91.595142 | AP101: 82.109203 | AQ101: 1.2247823 | AR101: 0 | AS101: 36.549093 | AT101: 49.732274 | AU101: 93.886463 | AV101: 7.5134055 | AW101: 0
B102: 93 | C102: 7 | D102: SOLOLA | E102: 708 | F102: Concepción | G102: 100 | H102: 100 | I102: 99.1701 | J102: 8.3333333 | K102: 45.139134 | L102: 100 | M102: 89.624241 | N102: 50.889214 | O102: 45.5527 | P102: 98.68 | Q102: 68.321014 | R102: 56.341777 | S102: 5 | T102: 10.612574 | U102: 53.872414 | V102: 47.13937 | W102: 85.333333 | X102: 20.256632 | Y102: 24.415091 | Z102: 37.177633 | AA102: 83.433158 | AB102: 12.384521 | AC102: 14.384085 | AE102: 5.7540622 | AF102: 100 | AG102: 16.618222 | AH102: 100 | AI102: 47.792823 | AJ102: 16.886511 | AK102: 5.5944847 | AL102: 86.791873 | AM102: 82.357724 | AN102: 100 | AO102: 32.633056 | AP102: 40.586634 | AQ102: 0.51431052 | AR102: 15.689892 | AS102: 36.549093 | AT102: 77.749364 | AU102: 93.886463 | AV102: 9.4240145 | AW102: 0
B103: 94 | C103: 7 | D103: SOLOLA | E103: 709 | F103: San Andrés Semetabaj | G103: 100 | H103: 100 | I103: 53.055537 | J103: 8.3333333 | K103: 47.360971 | L103: 100 | M103: 89.624241 | N103: 63.089316 | O103: 54.858629 | P103: 99.98 | Q103: 69.01435 | R103: 72.616533 | S103: 14.583333 | T103: 39.4357 | U103: 53.872414 | V103: 74.754544 | W103: 67 | X103: 6.5396445 | Y103: 46.584635 | Z103: 44.762113 | AA103: 81.644019 | AB103: 85.312547 | AC103: 12.772001 | AD103: 16.260163 | AE103: 5.2869314 | AF103: 91.836433 | AG103: 14.559091 | AH103: 100 | AI103: 47.792823 | AJ103: 16.886511 | AK103: 5.5944847 | AL103: 94.378534 | AM103: 82.357724 | AN103: 100 | AO103: 27.954244 | AP103: 37.291698 | AQ103: 0.96919066 | AR103: 81.595003 | AS103: 36.549093 | AT103: 79.972601 | AU103: 93.886463 | AV103: 8.1800193 | AW103: 0
B104: 95 | C104: 7 | D104: SOLOLA | E104: 710 | F104: Panajachel | G104: 73.631702 | H104: 100 | I104: 0 | J104: 8.3333333 | K104: 48.061282 | L104: 100 | M104: 89.624241 | N104: 50.436469 | O104: 45.207615 | P104: 100 | Q104: 94.686907 | R104: 87.640283 | S104: 100 | T104: 83.093936 | U104: 53.872414 | V104: 100 | W104: 41.333333 | X104: 20.559275 | Y104: 92.518654 | Z104: 40.276085 | AA104: 100 | AB104: 98.306054 | AC104: 10.528719 | AD104: 5.2434457 | AE104: 4.7601051 | AF104: 96.300967 | AG104: 46.288848 | AH104: 100 | AI104: 47.792823 | AJ104: 16.886511 | AK104: 5.5944847 | AL104: 96.167672 | AM104: 82.357724 | AN104: 100 | AO104: 22.677518 | AP104: 33.575696 | AQ104: 2.570767 | AR104: 98.029426 | AS104: 36.549093 | AT104: 82.47995 | AU104: 93.886463 | AV104: 27.349104 | AW104: 0
B105: 96 | C105: 7 | D105: SOLOLA | E105: 711 | F105: Santa Catarina Palopó | G105: 73.480803 | H105: 100 | I105: 66.38039 | J105: 8.3333333 | K105: 26.55564 | L105: 100 | M105: 89.624241 | N105: 60.711338 | O105: 52.330513 | P105: 94.32 | Q105: 71.794872 | R105: 68.30797 | S105: 31.25 | T105: 17.028986 | U105: 53.872414 | V105: 54.636663 | W105: 75.555556 | X105: 6.0892112 | Y105: 56.632701 | Z105: 47.937091 | AA105: 86.775218 | AB105: 38.883445 | AC105: 14.003345 | AE105: 10.607359 | AF105: 100 | AG105: 15.400461 | AH105: 100 | AI105: 47.792823 | AJ105: 16.886511 | AK105: 5.5944847 | AL105: 93.479392 | AM105: 82.357724 | AN105: 100 | AO105: 81.243988 | AP105: 74.819663 | AQ105: 0.94011372 | AR105: 24.353991 | AS105: 36.549093 | AT105: 54.650845 | AU105: 93.886463 | AV105: 8.6883214 | AW105: 0
B106: 97 | C106: 7 | D106: SOLOLA | E106: 712 | F106: San Antonio Palopó | G106: 100 | H106: 100 | I106: 97.204839 | J106: 8.3333333 | K106: 30.43683 | L106: 100 | M106: 89.624241 | N106: 64.835194 | O106: 54.660399 | P106: 97.01 | Q106: 66.080171 | R106: 68.345633 | S106: 30.882353 | T106: 25.05632 | U106: 53.872414 | V106: 41.579591 | W106: 66.388889 | X106: 4.8963085 | Y106: 45.787169 | Z106: 44.956471 | AA106: 66.906283 | AB106: 52.288218 | AC106: 16.885669 | AD106: 0 | AE106: 7.8672811 | AF106: 96.147117 | AG106: 13.417605 | AH106: 100 | AI106: 47.792823 | AJ106: 16.886511 | AK106: 5.5944847 | AL106: 91.162572 | AM106: 82.357724 | AN106: 100 | AO106: 53.799193 | AP106: 55.492354 | AQ106: 0.95956331 | AR106: 24.436386 | AS106: 36.549093 | AT106: 67.691824 | AU106: 93.886463 | AV106: 7.4904066 | AW106: 0
B107: 98 | C107: 7 | D107: SOLOLA | E107: 713 | F107: San Lucas Tolimán | G107: 93.842436 | H107: 97.818509 | I107: 67.023501 | J107: 8.3333333 | K107: 35.157277 | L107: 100 | M107: 89.624241 | N107: 60.043072 | O107: 53.333356 | P107: 97.88 | Q107: 66.135583 | R107: 72.309653 | S107: 11.637931 | T107: 29.504944 | U107: 53.872414 | V107: 55.16134 | W107: 46.833333 | X107: 20.82273 | Y107: 54.240305 | Z107: 39.14637 | AA107: 99.842594 | AB107: 49.421303 | AC107: 13.087919 | AD107: 7.3839662 | AE107: 8.6994655 | AF107: 79.337138 | AG107: 15.311519 | AH107: 100 | AI107: 47.792823 | AJ107: 16.886511 | AK107: 5.5944847 | AL107: 89.418889 | AM107: 82.357724 | AN107: 100 | AO107: 62.134405 | AP107: 61.362218 | AQ107: 0.50820862 | AR107: 0 | AS107: 36.549093 | AT107: 63.731171 | AU107: 93.886463 | AV107: 8.6345884 | AW107: 0
B108: 99 | C108: 7 | D108: SOLOLA | E108: 714 | F108: Santa Cruz La Laguna | G108: 100 | H108: 100 | I108: 89.021427 | J108: 8.3333333 | K108: 31.957587 | L108: 100 | M108: 89.624241 | N108: 48.79712 | O108: 43.958092 | P108: 95.67 | Q108: 72.098022 | R108: 43.863241 | S108: 45.833333 | T108: 28.205765 | U108: 53.872414 | V108: 40.912935 | W108: 79.222222 | X108: 15.875501 | Y108: 26.010022 | Z108: 40.364483 | AA108: 76.486225 | AB108: 55.43477 | AC108: 16.161598 | AE108: 11.627782 | AF108: 100 | AG108: 18.895963 | AH108: 100 | AI108: 47.792823 | AJ108: 16.886511 | AK108: 5.5944847 | AL108: 92.371618 | AM108: 82.357724 | AN108: 100 | AO108: 91.464612 | AP108: 82.017281 | AQ108: 0.92603545 | AR108: 0 | AS108: 36.549093 | AT108: 49.794298 | AU108: 93.886463 | AV108: 10.80008 | AW108: 0
B109: 100 | C109: 7 | D109: SOLOLA | E109: 715 | F109: San Pablo La Laguna | G109: 100 | H109: 100 | I109: 39.991247 | J109: 8.3333333 | K109: 22.122191 | L109: 100 | M109: 89.624241 | N109: 42.922948 | O109: 39.480761 | P109: 96.36 | Q109: 60.144509 | R109: 68.600219 | S109: 29.166667 | T109: 19.10389 | U109: 53.872414 | V109: 42.820156 | W109: 78 | X109: 15.435673 | Y109: 32.708733 | Z109: 71.606597 | AA109: 87.85545 | AB109: 62.639027 | AC109: 13.07588 | AD109: 0 | AE109: 22.090206 | AF109: 100 | AG109: 8.6311097 | AH109: 100 | AI109: 47.792823 | AJ109: 16.886511 | AK109: 5.5944847 | AL109: 91.537567 | AM109: 82.357724 | AN109: 100 | AO109: 100 | AP109: 100 | AQ109: 0.48676039 | AR109: 0 | AS109: 36.549093 | AT109: 0 | AU109: 93.886463 | AV109: 4.5987131 | AW109: 0
B110: 101 | C110: 7 | D110: SOLOLA | E110: 716 | F110: San Marcos La Laguna | G110: 100 | H110: 100 | I110: 0 | J110: 8.3333333 | K110: 49.407335 | L110: 100 | M110: 89.624241 | N110: 42.220651 | O110: 38.945466 | P110: 99.89 | Q110: 93.486239 | R110: 59.664676 | S110: 12.5 | T110: 64.563268 | U110: 53.872414 | V110: 62.688834 | W110: 78.611111 | X110: 14.323413 | Y110: 46.106155 | Z110: 43.686625 | AA110: 100 | AB110: 80.156682 | AC110: 10.953147 | AE110: 4.5952852 | AF110: 100 | AG110: 11.593872 | AH110: 100 | AI110: 47.792823 | AJ110: 16.886511 | AK110: 5.5944847 | AL110: 96.482432 | AM110: 82.357724 | AN110: 100 | AO110: 21.026671 | AP110: 32.413128 | AQ110: 0.87606594 | AR110: 100 | AS110: 36.549093 | AT110: 83.264385 | AU110: 93.886463 | AV110: 6.3886239 | AW110: 0
B111: 102 | C111: 7 | D111: SOLOLA | E111: 717 | F111: San Juan La Laguna | G111: 82.663181 | H111: 100 | I111: 0 | J111: 8.3333333 | K111: 20.260914 | L111: 100 | M111: 89.624241 | N111: 41.579839 | O111: 40.850407 | P111: 99.13 | Q111: 75.3703 | R111: 73.17424 | S111: 12.5 | T111: 48.407643 | U111: 53.872414 | V111: 60.310642 | W111: 68.833333 | X111: 11.307345 | Y111: 37.493527 | Z111: 53.5905 | AA111: 89.594072 | AB111: 83.448034 | AC111: 11.602488 | AD111: 2.3474178 | AE111: 12.268463 | AF111: 100 | AG111: 10.291704 | AH111: 100 | AI111: 47.792823 | AJ111: 16.886511 | AK111: 5.5944847 | AL111: 94.352879 | AM111: 82.357724 | AN111: 100 | AO111: 97.881711 | AP111: 86.536361 | AQ111: 0.5028497 | AR111: 23.830048 | AS111: 36.549093 | AT111: 46.745077 | AU111: 93.886463 | AV111: 5.601938 | AW111: 0
B112: 103 | C112: 7 | D112: SOLOLA | E112: 718 | F112: San Pedro La Laguna | G112: 96.702394 | H112: 100 | I112: 24.362033 | J112: 8.3333333 | K112: 46.492451 | L112: 100 | M112: 89.624241 | N112: 40.630949 | O112: 40.512172 | P112: 99.38 | Q112: 91.318389 | R112: 89.277987 | S112: 25 | T112: 57.530904 | U112: 53.872414 | V112: 97.892269 | W112: 46.833333 | X112: 13.481371 | Y112: 93.475613 | Z112: 33.211474 | AA112: 100 | AB112: 84.463862 | AC112: 12.026067 | AD112: 14.124294 | AE112: 8.4561144 | AF112: 100 | AG112: 13.161372 | AH112: 100 | AI112: 47.792823 | AJ112: 16.886511 | AK112: 5.5944847 | AL112: 90.566119 | AM112: 82.357724 | AN112: 100 | AO112: 59.696985 | AP112: 59.645726 | AQ112: 0.97331521 | AR112: 9.7382138 | AS112: 36.549093 | AT112: 64.889363 | AU112: 93.886463 | AV112: 7.3356073 | AW112: 0
B113: 104 | C113: 7 | D113: SOLOLA | E113: 719 | F113: Santiago Atitlán | G113: 98.480884 | H113: 100 | I113: 80.565757 | J113: 8.3333333 | K113: 32.447965 | L113: 100 | M113: 89.624241 | N113: 55.273636 | O113: 49.698061 | P113: 98.24 | Q113: 75.069486 | R113: 82.59205 | S113: 8.4558824 | T113: 27.284637 | U113: 53.872414 | V113: 59.890097 | W113: 52.944444 | X113: 10.922017 | Y113: 61.895975 | Z113: 39.797455 | AA113: 87.679938 | AB113: 71.379777 | AC113: 9.9438308 | AD113: 15.258216 | AE113: 12.795772 | AF113: 62.86051 | AG113: 9.4860566 | AH113: 100 | AI113: 47.792823 | AJ113: 16.886511 | AK113: 5.5944847 | AL113: 96.59247 | AM113: 82.357724 | AN113: 100 | AO113: 100 | AP113: 90.255768 | AQ113: 0.42352296 | AR113: 60.228334 | AS113: 36.549093 | AT113: 44.235432 | AU113: 93.886463 | AV113: 5.1152172 | AW113: 0
B114: 105 | C114: 8 | D114: TOTONICAPAN | E114: 801 | F114: Totonicapán | G114: 84.093879 | H114: 100 | I114: 100 | J114: 41.666667 | K114: 48.817119 | L114: 100 | M114: 74.679342 | N114: 39.392066 | O114: 36.789583 | P114: 98.57 | Q114: 52.580927 | R114: 50.82775 | S114: 17.22561 | T114: 46.712908 | U114: 53.872414 | V114: 68.014022 | W114: 85.230769 | X114: 47.244827 | Y114: 46.920918 | Z114: 66.633236 | AA114: 82.433759 | AB114: 77.979056 | AC114: 11.702734 | AD114: 8.0240722 | AE114: 6.5743005 | AF114: 27.617994 | AG114: 22.237275 | AH114: 100 | AI114: 43.193793 | AJ114: 0.88593861 | AK114: 0 | AL114: 81.405778 | AM114: 73.082437 | AN114: 100 | AO114: 22.153441 | AP114: 26.951066 | AQ114: 1.0656647 | AR114: 43.537766 | AS114: 0 | AT114: 78.460673 | AU114: 93.886463 | AV114: 13.052087 | AW114: 0
B115: 106 | C115: 8 | D115: TOTONICAPAN | E115: 802 | F115: San Cristóbal Totonicapán | G115: 92.127355 | H115: 100 | I115: 100 | J115: 41.666667 | K115: 32.874636 | L115: 100 | M115: 74.679342 | N115: 36.373112 | O115: 34.488433 | P115: 97.3 | Q115: 45.59199 | R115: 49.412636 | S115: 50 | T115: 28.697191 | U115: 53.872414 | V115: 68.807954 | W115: 82.769231 | X115: 27.377435 | Y115: 50.810415 | Z115: 38.013234 | AA115: 75.904854 | AB115: 81.744712 | AC115: 13.042811 | AD115: 12.717537 | AE115: 5.2365977 | AF115: 99.998854 | AG115: 13.270023 | AH115: 100 | AI115: 43.193793 | AJ115: 0.88593861 | AK115: 0 | AL115: 88.953188 | AM115: 73.082437 | AN115: 100 | AO115: 12.558916 | AP115: 21.46721 | AQ115: 4.4453986 | AR115: 86.236495 | AS115: 0 | AT115: 83.888206 | AU115: 93.886463 | AV115: 7.5405287 | AW115: 0
B116: 107 | C116: 8 | D116: TOTONICAPAN | E116: 803 | F116: San Francisco El Alto | G116: 100 | H116: 100 | I116: 100 | J116: 41.666667 | K116: 40.2526 | L116: 66.666667 | M116: 74.679342 | N116: 68.971379 | O116: 33.462952 | P116: 97.12 | Q116: 48.317173 | R116: 57.014223 | S116: 13.257576 | T116: 24.431835 | U116: 53.872414 | V116: 76.474634 | W116: 83.589744 | X116: 6.2601586 | Y116: 44.471975 | Z116: 40.050752 | AA116: 72.925482 | AB116: 19.976054 | AC116: 14.75232 | AD116: 0 | AE116: 6.9363571 | AF116: 61.55449 | AG116: 8.6834276 | AH116: 100 | AI116: 43.193793 | AJ116: 0.88593861 | AK116: 0 | AL116: 94.141942 | AM116: 73.082437 | AN116: 100 | AO116: 24.750252 | AP116: 28.435302 | AQ116: 1.4050028 | AR116: 97.44306 | AS116: 1.4394102e-16 | AT116: 76.991681 | AU116: 93.886463 | AV116: 4.7214611 | AW116: 0
B117: 108 | C117: 8 | D117: TOTONICAPAN | E117: 804 | F117: San Andrés Xecul | G117: 100 | H117: 100 | I117: 99.575714 | J117: 41.666667 | K117: 29.782641 | L117: 100 | M117: 74.679342 | N117: 35.107597 | O117: 33.52385 | P117: 98.37 | Q117: 50.930188 | R117: 48.231071 | S117: 29.411765 | T117: 28.30354 | U117: 53.872414 | V117: 61.899196 | W117: 57.333333 | X117: 7.9617112 | Y117: 41.590866 | Z117: 43.894926 | AA117: 69.630697 | AB117: 28.042662 | AC117: 14.335155 | AD117: 100 | AE117: 10.315149 | AF117: 100 | AG117: 7.7531575 | AH117: 100 | AI117: 43.193793 | AJ117: 0.88593861 | AK117: 0 | AL117: 90.113901 | AM117: 73.082437 | AN117: 100 | AO117: 48.984263 | AP117: 42.286517 | AQ117: 3.339385 | AR117: 56.556629 | AS117: 0 | AT117: 63.282725 | AU117: 93.886463 | AV117: 4.1496874 | AW117: 0
B118: 109 | C118: 8 | D118: TOTONICAPAN | E118: 805 | F118: Momostenango | G118: 99.084889 | H118: 100 | I118: 59.245961 | J118: 41.666667 | K118: 26.534971 | L118: 100 | M118: 74.679342 | N118: 68.914334 | O118: 29.776284 | P118: 95.52 | Q118: 40.059636 | R118: 32.103334 | S118: 15.081967 | T118: 15.825162 | U118: 53.872414 | V118: 53.862517 | W118: 54.051282 | X118: 4.3612716 | Y118: 34.099983 | Z118: 36.878699 | AA118: 61.789758 | AB118: 29.039571 | AC118: 15.901446 | AD118: 1.8315018 | AE118: 12.883367 | AF118: 54.12443 | AG118: 7.7620581 | AH118: 100 | AI118: 43.193793 | AJ118: 0.88593861 | AK118: 0 | AL118: 88.146934 | AM118: 73.082437 | AN118: 100 | AO118: 67.404518 | AP118: 52.814816 | AQ118: 0.69127374 | AR118: 22.766243 | AS118: 1.4394102e-16 | AT118: 52.862557 | AU118: 93.886463 | AV118: 4.155158 | AW118: 0
B119: 110 | C119: 8 | D119: TOTONICAPAN | E119: 806 | F119: Santa María Chiquimula | G119: 100 | H119: 100 | I119: 100 | J119: 41.666667 | K119: 29.490478 | L119: 100 | M119: 74.679342 | N119: 68.349143 | O119: 27.982194 | P119: 88.03 | Q119: 46.50442 | R119: 43.452097 | S119: 23.75 | T119: 12.71401 | U119: 53.872414 | V119: 34.806511 | W119: 77.025641 | X119: 5.661774 | Y119: 32.083206 | Z119: 39.873945 | AA119: 66.843281 | AB119: 20.412177 | AC119: 13.312354 | AD119: 5.3763441 | AE119: 10.835519 | AF119: 57.723531 | AG119: 5.9824815 | AH119: 100 | AI119: 43.193793 | AJ119: 0.88593861 | AK119: 0 | AL119: 90.454838 | AM119: 73.082437 | AN119: 100 | AO119: 52.716557 | AP119: 44.419751 | AQ119: 1.3001404 | AR119: 55.545619 | AS119: 1.4394102e-16 | AT119: 61.171401 | AU119: 93.886463 | AV119: 3.0613736 | AW119: 0
B120: 111 | C120: 8 | D120: TOTONICAPAN | E120: 807 | F120: Santa Lucía La Reforma | G120: 100 | H120: 100 | I120: 100 | J120: 41.666667 | K120: 38.162924 | L120: 100 | M120: 74.679342 | N120: 77.615447 | O120: 36.157053 | P120: 90.82 | Q120: 32.500785 | R120: 35.163541 | S120: 1.8382353 | T120: 12.011666 | U120: 53.872414 | V120: 26.771341 | W120: 56.512821 | X120: 8.1880516 | Y120: 43.175476 | Z120: 29.450298 | AA120: 67.757456 | AB120: 36.178235 | AC120: 17.577355 | AE120: 11.579405 | AF120: 96.263899 | AG120: 7.579771 | AH120: 100 | AI120: 43.193793 | AJ120: 0.88593861 | AK120: 0 | AL120: 97.18398 | AM120: 73.082437 | AN120: 100 | AO120: 58.052001 | AP120: 47.469282 | AQ120: 0.30414464 | AR120: 100 | AS120: 0 | AT120: 58.15319 | AU120: 93.886463 | AV120: 4.0431186 | AW120: 0
B121: 112 | C121: 8 | D121: TOTONICAPAN | E121: 808 | F121: San Bartolo Aguas Calientes | G121: 100 | H121: 100 | I121: 68.930367 | J121: 41.666667 | K121: 28.363304 | L121: 100 | M121: 74.679342 | N121: 65.002384 | O121: 27.041167 | P121: 93.14 | Q121: 52.300613 | R121: 37.326313 | S121: 24.074074 | T121: 19.566593 | U121: 53.872414 | V121: 47.344816 | W121: 49.948718 | X121: 13.814554 | Y121: 44.904141 | Z121: 62.309967 | AA121: 76.245167 | AB121: 48.638444 | AC121: 16.551743 | AE121: 9.2645138 | AF121: 99.448885 | AG121: 15.469323 | AH121: 100 | AI121: 43.193793 | AJ121: 0.88593861 | AK121: 0 | AL121: 74.806744 | AM121: 73.082437 | AN121: 100 | AO121: 41.448697 | AP121: 37.979482 | AQ121: 0.95227923 | AR121: 0 | AS121: 1.4394102e-16 | AT121: 67.545525 | AU121: 93.886463 | AV121: 8.8922882 | AW121: 0
B122: 113 | C122: 9 | D122: QUETZALTENANGO | E122: 901 | F122: Quetzaltenango | G122: 54.816745 | H122: 100 | I122: 75.147973 | J122: 0 | K122: 59.484984 | L122: 66.666667 | M122: 65.257159 | N122: 32.157359 | O122: 31.27516 | P122: 98.8 | Q122: 90.485906 | R122: 95.840397 | S122: 100 | T122: 86.783547 | U122: 53.872414 | V122: 100 | W122: 72.823529 | X122: 71.284046 | Y122: 90.887819 | Z122: 69.09631 | AA122: 100 | AB122: 98.760401 | AC122: 22.954059 | AD122: 18.292289 | AE122: 9.6707234 | AF122: 23.593542 | AG122: 94.932715 | AH122: 100 | AI122: 78.50604 | AJ122: 38.241855 | AK122: 19.279766 | AL122: 86.384779 | AM122: 97.729767 | AN122: 100 | AO122: 13.907349 | AP122: 24.299108 | AQ122: 11.502959 | AR122: 92.840101 | AS122: 3.9844213 | AT122: 93.513062 | AU122: 93.886463 | AV122: 40.127557 | AW122: 0
B123: 114 | C123: 9 | D123: QUETZALTENANGO | E123: 902 | F123: Salcajá | G123: 76.446306 | H123: 100 | I123: 50.275534 | J123: 0 | K123: 59.031315 | L123: 66.666667 | M123: 65.257159 | N123: 35.66128 | O123: 33.945871 | P123: 99.92 | Q123: 94.444444 | R123: 87.764448 | S123: 87.5 | T123: 77.601862 | U123: 53.872414 | V123: 100 | W123: 70.235294 | X123: 4.5438841 | Y123: 100 | Z123: 41.451955 | AA123: 100 | AB123: 70.091865 | AC123: 23.570477 | AD123: 5.988024 | AE123: 6.8216946 | AF123: 100 | AG123: 45.43544 | AH123: 100 | AI123: 78.50604 | AJ123: 38.241855 | AK123: 19.279766 | AL123: 93.261692 | AM123: 97.729767 | AN123: 100 | AO123: 2.4451083 | AP123: 17.140506 | AQ123: 17.219854 | AR123: 100 | AS123: 3.9844213 | AT123: 96.936907 | AU123: 93.886463 | AV123: 18.884324 | AW123: 0
B124: 115 | C124: 9 | D124: QUETZALTENANGO | E124: 903 | F124: Olintepeque | G124: 85.498645 | H124: 100 | I124: 100 | J124: 0 | K124: 39.472518 | L124: 100 | M124: 65.257159 | N124: 31.832843 | O124: 31.027811 | P124: 99.27 | Q124: 80.809681 | R124: 85.777913 | S124: 37.5 | T124: 67.068896 | U124: 53.872414 | V124: 100 | W124: 82.529412 | X124: 1.6475657 | Y124: 73.320434 | Z124: 26.884079 | AA124: 60.966326 | AB124: 19.858087 | AC124: 25.605031 | AD124: 0 | AE124: 17.109177 | AF124: 48.875215 | AG124: 15.225769 | AH124: 100 | AI124: 78.50604 | AJ124: 38.241855 | AK124: 19.279766 | AL124: 92.12952 | AM124: 97.729767 | AN124: 100 | AO124: 43.833807 | AP124: 42.989311 | AQ124: 4.1624674 | AR124: 91.844163 | AS124: 3.9844213 | AT124: 84.573837 | AU124: 93.886463 | AV124: 5.9189431 | AW124: 0
B125: 116 | C125: 9 | D125: QUETZALTENANGO | E125: 904 | F125: San Carlos Sija | G125: 93.744511 | H125: 100 | I125: 98.952539 | J125: 0 | K125: 30.043354 | L125: 100 | M125: 65.257159 | N125: 30.005096 | O125: 29.634691 | P125: 97.48 | Q125: 40.155167 | R125: 53.384546 | S125: 25.675676 | T125: 27.613941 | U125: 53.872414 | V125: 100 | W125: 66.352941 | X125: 5.0591969 | Y125: 83.613824 | Z125: 51.834704 | AA125: 85.118256 | AB125: 69.460435 | AC125: 44.95365 | AD125: 0 | AE125: 15.473405 | AF125: 69.002896 | AG125: 15.526451 | AH125: 100 | AI125: 78.50604 | AJ125: 38.241855 | AK125: 19.279766 | AL125: 87.253845 | AM125: 97.729767 | AN125: 100 | AO125: 37.252752 | AP125: 38.879194 | AQ125: 1.0160106 | AR125: 76.791444 | AS125: 3.9844213 | AT125: 86.53964 | AU125: 93.886463 | AV125: 6.0479896 | AW125: 0
B126: 117 | C126: 9 | D126: QUETZALTENANGO | E126: 905 | F126: Sibilia | G126: 65.304258 | H126: 99.230921 | I126: 0 | J126: 0 | K126: 16.490677 | L126: 100 | M126: 65.257159 | N126: 26.862187 | O126: 27.239146 | P126: 99.99 | Q126: 69.764398 | R126: 60.703819 | S126: 28.571429 | T126: 39.718004 | U126: 53.872414 | V126: 100 | W126: 71.529412 | X126: 13.663594 | Y126: 78.261261 | Z126: 68.554073 | AA126: 95.573235 | AB126: 99.98294 | AC126: 37.488634 | AD126: 15.151515 | AE126: 17.110393 | AF126: 100 | AG126: 19.275472 | AH126: 100 | AI126: 78.50604 | AJ126: 38.241855 | AK126: 19.279766 | AL126: 83.372643 | AM126: 97.729767 | AN126: 100 | AO126: 43.8387 | AP126: 42.992368 | AQ126: 1.2272854 | AR126: 55.650787 | AS126: 3.9844213 | AT126: 84.572375 | AU126: 93.886463 | AV126: 7.6569939 | AW126: 0
B127: 118 | C127: 9 | D127: QUETZALTENANGO | E127: 906 | F127: Cabricán | G127: 92.346074 | H127: 100 | I127: 100 | J127: 0 | K127: 17.458307 | L127: 33.333333 | M127: 65.257159 | N127: 57.626625 | O127: 24.606527 | P127: 93.4 | Q127: 57.525656 | R127: 45.59295 | S127: 16.666667 | T127: 18.561111 | U127: 53.872414 | V127: 42.624642 | W127: 67 | X127: 6.0438782 | Y127: 45.047923 | Z127: 47.765204 | AA127: 67.187978 | AB127: 64.299768 | AC127: 74.274576 | AD127: 7.0175439 | AE127: 31.365004 | AF127: 77.578736 | AG127: 26.289422 | AH127: 100 | AI127: 78.50604 | AJ127: 38.241855 | AK127: 19.279766 | AL127: 86.591903 | AM127: 97.729767 | AN127: 100 | AO127: 100 | AP127: 78.809163 | AQ127: 0.96413489 | AR127: 22.265137 | AS127: 3.9844213 | AT127: 67.441774 | AU127: 93.886463 | AV127: 10.66724 | AW127: 0
B128: 119 | C128: 9 | D128: QUETZALTENANGO | E128: 907 | F128: Cajolá | G128: 94.492896 | H128: 100 | I128: 79.279003 | J128: 0 | K128: 13.247542 | L128: 100 | M128: 65.257159 | N128: 27.60098 | O128: 27.802258 | P128: 96.99 | Q128: 65.500686 | R128: 53.855406 | S128: 12.5 | T128: 18.376221 | U128: 53.872414 | V128: 42.350407 | W128: 85.117647 | X128: 4.8915076 | Y128: 47.792827 | Z128: 38.478244 | AA128: 58.293269 | AB128: 9.8970035 | AC128: 51.580834 | AE128: 26.074153 | AF128: 90.853821 | AG128: 12.898534 | AH128: 100 | AI128: 78.50604 | AJ128: 38.241855 | AK128: 19.279766 | AL128: 81.496216 | AM128: 97.729767 | AN128: 100 | AO128: 79.901786 | AP128: 65.515126 | AQ128: 1.3289319 | AR128: 7.5025416 | AS128: 3.9844213 | AT128: 73.8001 | AU128: 93.886463 | AV128: 4.9201405 | AW128: 0
B129: 120 | C129: 9 | D129: QUETZALTENANGO | E129: 908 | F129: San Miguel Siguilá | G129: 99.997367 | H129: 100 | I129: 100 | J129: 0 | K129: 9.4901561 | L129: 100 | M129: 65.257159 | N129: 28.445314 | O129: 28.445815 | P129: 98.39 | Q129: 64.542373 | R129: 53.212166 | S129: 8.9285714 | T129: 37.378689 | U129: 53.872414 | V129: 54.390589 | W129: 85.117647 | X129: 11.766048 | Y129: 53.41988 | Z129: 40.856148 | AA129: 63.911347 | AB129: 31.841978 | AC129: 38.730296 | AD129: 0 | AE129: 13.895147 | AF129: 100 | AG129: 10.469832 | AH129: 100 | AI129: 78.50604 | AJ129: 38.241855 | AK129: 19.279766 | AL129: 95.730045 | AM129: 97.729767 | AN129: 100 | AO129: 30.903089 | AP129: 34.91359 | AQ129: 1.6420812 | AR129: 100 | AS129: 3.9844213 | AT129: 88.436326 | AU129: 93.886463 | AV129: 3.8777908 | AW129: 0
B130: 121 | C130: 9 | D130: QUETZALTENANGO | E130: 909 | F130: San Juan Ostuncalco | G130: 86.556057 | H130: 100 | I130: 32.843623 | J130: 0 | K130: 15.003725 | L130: 100 | M130: 65.257159 | N130: 28.311825 | O130: 28.344069 | P130: 97.5 | Q130: 63.132817 | R130: 60.774337 | S130: 54.545455 | T130: 23.885227 | U130: 53.872414 | V130: 49.552336 | W130: 65.705882 | X130: 5.1466786 | Y130: 58.223462 | Z130: 40.712844 | AA130: 86.35556 | AB130: 68.478392 | AC130: 31.286732 | AD130: 5.5325035 | AE130: 20.405081 | AF130: 63.884574 | AG130: 13.905758 | AH130: 100 | AI130: 78.50604 | AJ130: 38.241855 | AK130: 19.279766 | AL130: 87.000279 | AM130: 97.729767 | AN130: 100 | AO130: 57.093922 | AP130: 51.270754 | AQ130: 4.4256012 | AR130: 60.17669 | AS130: 3.9844213 | AT130: 80.612955 | AU130: 93.886463 | AV130: 5.3524208 | AW130: 0
B131: 122 | C131: 9 | D131: QUETZALTENANGO | E131: 910 | F131: San Mateo | G131: 82.079994 | H131: 100 | I131: 0 | J131: 0 | K131: 24.03689 | L131: 100 | M131: 65.257159 | N131: 29.753243 | O131: 29.442727 | P131: 99.74 | Q131: 97.291321 | R131: 98.308038 | S131: 20 | T131: 46.426605 | U131: 53.872414 | V131: 100 | W131: 77.352941 | X131: 3.604307 | Y131: 84.57454 | Z131: 32.070868 | AA131: 87.231969 | AB131: 57.910107 | AC131: 25.237933 | AD131: 13.333333 | AE131: 7.3906765 | AF131: 100 | AG131: 18.977715 | AH131: 100 | AI131: 78.50604 | AJ131: 38.241855 | AK131: 19.279766 | AL131: 92.851095 | AM131: 97.729767 | AN131: 100 | AO131: 4.7342416 | AP131: 18.570157 | AQ131: 3.9426202 | AR131: 100 | AS131: 3.9844213 | AT131: 96.253128 | AU131: 93.886463 | AV131: 7.5292026 | AW131: 0
B132: 123 | C132: 9 | D132: QUETZALTENANGO | E132: 911 | F132: Concepción Chiquirichapa | G132: 100 | H132: 100 | I132: 100 | J132: 0 | K132: 25.538916 | L132: 66.666667 | M132: 65.257159 | N132: 28.362459 | O132: 28.382662 | P132: 100 | Q132: 90.645252 | R132: 62.18217 | S132: 21.875 | T132: 29.507271 | U132: 53.872414 | V132: 53.864783 | W132: 78.647059 | X132: 1.9116835 | Y132: 54.929577 | Z132: 39.623966 | AA132: 68.657938 | AB132: 61.268262 | AC132: 31.971567 | AE132: 21.497442 | AF132: 91.309154 | AG132: 9.4611604 | AH132: 100 | AI132: 78.50604 | AJ132: 38.241855 | AK132: 19.279766 | AL132: 88.711223 | AM132: 97.729767 | AN132: 100 | AO132: 61.488719 | AP132: 54.01547 | AQ132: 1.3140272 | AR132: 65.590567 | AS132: 3.9844213 | AT132: 79.300201 | AU132: 93.886463 | AV132: 3.4448892 | AW132: 0
B133: 124 | C133: 9 | D133: QUETZALTENANGO | E133: 912 | F133: San Martín Sacatepéquez | G133: 88.404378 | H133: 100 | I133: 89.109552 | J133: 0 | K133: 32.014387 | L133: 66.666667 | M133: 65.257159 | N133: 26.507094 | O133: 26.968491 | P133: 96.07 | Q133: 83.638522 | R133: 42.565918 | S133: 16 | T133: 18.642439 | U133: 53.872414 | V133: 44.980868 | W133: 47.588235 | X133: 3.5347936 | Y133: 52.184674 | Z133: 46.624 | AA133: 76.34389 | AB133: 72.797057 | AC133: 29.615679 | AD133: 0 | AE133: 25.974313 | AF133: 74.519514 | AG133: 10.972802 | AH133: 100 | AI133: 78.50604 | AJ133: 38.241855 | AK133: 19.279766 | AL133: 91.67862 | AM133: 97.729767 | AN133: 100 | AO133: 79.500109 | AP133: 65.264264 | AQ133: 0.83961274 | AR133: 71.83554 | AS133: 3.9844213 | AT133: 73.920083 | AU133: 93.886463 | AV133: 4.0936552 | AW133: 0
B134: 125 | C134: 9 | D134: QUETZALTENANGO | E134: 913 | F134: Almolonga | G134: 87.333817 | H134: 100 | I134: 88.400613 | J134: 0 | K134: 7.889122 | L134: 33.333333 | M134: 65.257159 | N134: 31.03158 | O134: 33.694346 | P134: 99 | Q134: 94.921764 | R134: 84.762234 | S134: 40 | T134: 29.285187 | U134: 53.872414 | V134: 100 | W134: 95.470588 | X134: 1.9336746 | Y134: 61.929082 | Z134: 23.385779 | AA134: 88.497729 | AB134: 30.733942 | AC134: 27.590841 | AE134: 15.690241 | AF134: 100 | AG134: 6.6951433 | AH134: 100 | AI134: 78.50604 | AJ134: 38.241855 | AK134: 19.279766 | AL134: 86.55843 | AM134: 97.729767 | AN134: 100 | AO134: 38.12513 | AP134: 39.424027 | AQ134: 3.6009878 | AR134: 73.480361 | AS134: 3.9844213 | AT134: 86.279055 | AU134: 93.886463 | AV134: 2.2577704 | AW134: 0
B135: 126 | C135: 9 | D135: QUETZALTENANGO | E135: 914 | F135: Cantel | G135: 83.306345 | H135: 100 | I135: 85.153279 | J135: 0 | K135: 34.839998 | L135: 66.666667 | M135: 65.257159 | N135: 31.576715 | O135: 30.832589 | P135: 97.12 | Q135: 78.815717 | R135: 72.865346 | S135: 53.571429 | T135: 43.557706 | U135: 53.872414 | V135: 100 | W135: 87.058824 | X135: 2.3043138 | Y135: 75.104621 | Z135: 38.633727 | AA135: 69.075607 | AB135: 59.159132 | AC135: 22.743923 | AD135: 17.156863 | AE135: 20.596352 | AF135: 46.212928 | AG135: 12.072496 | AH135: 100 | AI135: 78.50604 | AJ135: 38.241855 | AK135: 19.279766 | AL135: 90.471236 | AM135: 97.729767 | AN135: 100 | AO135: 57.863442 | AP135: 51.751348 | AQ135: 5.3388582 | AR135: 76.836623 | AS135: 3.9844213 | AT135: 80.383095 | AU135: 93.886463 | AV135: 4.5656216 | AW135: 0
B136: 127 | C136: 9 | D136: QUETZALTENANGO | E136: 915 | F136: Huitán | G136: 100 | H136: 100 | I136: 66.684437 | J136: 0 | K136: 35.603685 | L136: 100 | M136: 65.257159 | N136: 57.923688 | O136: 25.691652 | P136: 89.27 | Q136: 51.566894 | R136: 51.239939 | S136: 59.375 | T136: 13.821138 | U136: 53.872414 | V136: 35.064605 | W136: 73.470588 | X136: 4.8761843 | Y136: 39.42087 | Z136: 48.621619 | AA136: 77.384365 | AB136: 57.457376 | AC136: 50.069359 | AD136: 0 | AE136: 21.192492 | AF136: 100 | AG136: 17.129015 | AH136: 100 | AI136: 78.50604 | AJ136: 38.241855 | AK136: 19.279766 | AL136: 80.514593 | AM136: 97.729767 | AN136: 100 | AO136: 60.261842 | AP136: 53.249239 | AQ136: 2.836911 | AR136: 24.475884 | AS136: 3.9844213 | AT136: 79.666677 | AU136: 93.886463 | AV136: 6.7357779 | AW136: 0
B137: 128 | C137: 9 | D137: QUETZALTENANGO | E137: 916 | F137: Zunil | G137: 88.939239 | H137: 100 | I137: 97.326469 | J137: 0 | K137: 18.248332 | L137: 100 | M137: 65.257159 | N137: 29.535583 | O137: 33.268816 | P137: 99.05 | Q137: 99.10045 | R137: 77.644572 | S137: 11.956522 | T137: 29.588735 | U137: 53.872414 | V137: 92.12298 | W137: 53.411765 | X137: 5.0431563 | Y137: 71.399001 | Z137: 28.506245 | AA137: 93.091238 | AB137: 66.551003 | AC137: 23.152518 | AE137: 17.029119 | AF137: 98.290258 | AG137: 12.699534 | AH137: 100 | AI137: 78.50604 | AJ137: 38.241855 | AK137: 19.279766 | AL137: 88.04225 | AM137: 97.729767 | AN137: 100 | AO137: 43.511716 | AP137: 42.788153 | AQ137: 0.6509637 | AR137: 75.187396 | AS137: 3.9844213 | AT137: 84.670048 | AU137: 93.886463 | AV137: 4.8347337 | AW137: 0
B138: 129 | C138: 9 | D138: QUETZALTENANGO | E138: 917 | F138: Colomba Costa Cuca | G138: 79.459299 | H138: 97.948333 | I138: 41.072064 | J138: 0 | K138: 33.490648 | L138: 100 | M138: 65.257159 | N138: 18.687468 | O138: 27.011679 | P138: 93.77 | Q138: 66.544591 | R138: 47.150109 | S138: 11.320755 | T138: 23.886817 | U138: 53.872414 | V138: 57.407892 | W138: 41.117647 | X138: 4.0429855 | Y138: 82.790352 | Z138: 38.755752 | AA138: 73.074655 | AB138: 41.001748 | AC138: 31.179729 | AD138: 1.8315018 | AE138: 27.891341 | AF138: 60.575228 | AG138: 16.869889 | AH138: 100 | AI138: 78.50604 | AJ138: 38.241855 | AK138: 19.279766 | AL138: 86.091821 | AM138: 97.729767 | AN138: 100 | AO138: 87.212716 | AP138: 70.081078 | AQ138: 0.61033335 | AR138: 30.273976 | AS138: 3.9844213 | AT138: 71.616278 | AU138: 93.886463 | AV138: 6.6245662 | AW138: 0
B139: 130 | C139: 9 | D139: QUETZALTENANGO | E139: 918 | F139: San Francisco La Unión | G139: 99.899157 | H139: 100 | I139: 97.522308 | J139: 0 | K139: 18.724198 | L139: 100 | M139: 65.257159 | N139: 28.214174 | O139: 28.269639 | P139: 95.65 | Q139: 43.564356 | R139: 56.195283 | S139: 12.5 | T139: 38.36119 | U139: 53.872414 | V139: 79.769536 | W139: 94.823529 | X139: 6.6460681 | Y139: 67.693381 | Z139: 31.75193 | AA139: 59.082031 | AB139: 61.033468 | AC139: 41.243878 | AD139: 0 | AE139: 18.884458 | AF139: 100 | AG139: 8.4663229 | AH139: 100 | AI139: 78.50604 | AJ139: 38.241855 | AK139: 19.279766 | AL139: 91.517973 | AM139: 97.729767 | AN139: 100 | AO139: 50.976136 | AP139: 47.449965 | AQ139: 1.0337026 | AR139: 85.614351 | AS139: 3.9844213 | AT139: 82.440377 | AU139: 93.886463 | AV139: 3.017925 | AW139: 0
B140: 131 | C140: 9 | D140: QUETZALTENANGO | E140: 919 | F140: El Palmar | G140: 77.359311 | H140: 100 | I140: 14.085971 | J140: 0 | K140: 9.9511977 | L140: 66.666667 | M140: 65.257159 | N140: 29.757517 | O140: 34.60438 | P140: 95.76 | Q140: 83.606423 | R140: 44.236651 | S140: 5.3691275 | T140: 43.29331 | U140: 53.872414 | V140: 47.931887 | W140: 39.823529 | X140: 5.654943 | Y140: 82.378617 | Z140: 46.624742 | AA140: 83.485717 | AB140: 48.582101 | AC140: 32.578142 | AD140: 2.4875622 | AE140: 26.087068 | AF140: 67.488985 | AG140: 32.243086 | AH140: 100 | AI140: 78.50604 | AJ140: 38.241855 | AK140: 19.279766 | AL140: 83.265364 | AM140: 97.729767 | AN140: 100 | AO140: 79.953746 | AP140: 65.547577 | AQ140: 0.51963556 | AR140: 18.591936 | AS140: 3.9844213 | AT140: 73.784579 | AU140: 93.886463 | AV140: 13.222432 | AW140: 0
B141: 132 | C141: 9 | D141: QUETZALTENANGO | E141: 920 | F141: Coatepeque | G141: 29.534886 | H141: 100 | I141: 0 | J141: 0 | K141: 17.777947 | L141: 66.666667 | M141: 65.257159 | N141: 18.052902 | O141: 25.683048 | P141: 95.56 | Q141: 52.68124 | R141: 53.996333 | S141: 23.387097 | T141: 42.437521 | U141: 53.872414 | V141: 95.727103 | W141: 40.470588 | X141: 58.920525 | Y141: 98.024569 | Z141: 40.179029 | AA141: 100 | AB141: 62.349221 | AC141: 28.918788 | AD141: 12.716763 | AE141: 12.594843 | AF141: 56.37791 | AG141: 57.013948 | AH141: 100 | AI141: 78.50604 | AJ141: 38.241855 | AK141: 19.279766 | AL141: 74.435083 | AM141: 97.729767 | AN141: 100 | AO141: 25.671696 | AP141: 31.646387 | AQ141: 1.6689605 | AR141: 46.762891 | AS141: 3.9844213 | AT141: 89.998976 | AU141: 93.886463 | AV141: 23.853587 | AW141: 0
B142: 133 | C142: 9 | D142: QUETZALTENANGO | E142: 921 | F142: Génova Costa Cuca | G142: 92.906218 | H142: 100 | I142: 54.194295 | J142: 0 | K142: 20.827838 | L142: 66.666667 | M142: 65.257159 | N142: 17.957553 | O142: 25.610372 | P142: 90.26 | Q142: 17.708854 | R142: 36.319243 | S142: 8.974359 | T142: 26.509007 | U142: 53.872414 | V142: 49.664606 | W142: 42.411765 | X142: 3.7496229 | Y142: 79.084732 | Z142: 41.746643 | AA142: 71.539645 | AB142: 37.37085 | AC142: 40.297752 | AD142: 1.618123 | AE142: 36.30379 | AF142: 58.524739 | AG142: 17.133755 | AH142: 100 | AI142: 78.50604 | AJ142: 38.241855 | AK142: 19.279766 | AL142: 76.172889 | AM142: 97.729767 | AN142: 100 | AO142: 100 | AP142: 91.218586 | AQ142: 0.34366887 | AR142: 0 | AS142: 3.9844213 | AT142: 61.506546 | AU142: 93.886463 | AV142: 6.7378122 | AW142: 0
B143: 134 | C143: 9 | D143: QUETZALTENANGO | E143: 922 | F143: Flores Costa Cuca | G143: 67.976932 | H143: 100 | I143: 0 | J143: 0 | K143: 31.658754 | L143: 66.666667 | M143: 65.257159 | N143: 19.655428 | O143: 26.904503 | P143: 93.58 | Q143: 61.092437 | R143: 0 | S143: 34.722222 | T143: 21.394836 | U143: 53.872414 | V143: 80.307704 | W143: 39.823529 | X143: 4.9013817 | Y143: 96.240382 | Z143: 43.188473 | AA143: 70.470338 | AB143: 54.758169 | AC143: 33.4401 | AD143: 1.5151515 | AE143: 27.45711 | AF143: 82.098228 | AG143: 15.678981 | AH143: 100 | AI143: 78.50604 | AJ143: 38.241855 | AK143: 19.279766 | AL143: 87.394531 | AM143: 97.729767 | AN143: 100 | AO143: 85.465712 | AP143: 68.990008 | AQ143: 1.6430391 | AR143: 40.388344 | AS143: 3.9844213 | AT143: 72.138119 | AU143: 93.886463 | AV143: 6.1134525 | AW143: 0
B144: 135 | C144: 9 | D144: QUETZALTENANGO | E144: 923 | F144: La Esperanza | G144: 26.23364 | H144: 100 | I144: 0 | J144: 0 | K144: 40.716076 | L144: 100 | M144: 65.257159 | N144: 30.744875 | O144: 30.190369 | P144: 100 | Q144: 97.806005 | R144: 100 | S144: 45.3125 | T144: 71.347848 | U144: 53.872414 | V144: 100 | W144: 60.529412 | X144: 2.1423292 | Y144: 97.338343 | Z144: 35.237336 | AA144: 100 | AB144: 61.189346 | AC144: 25.269035 | AD144: 9.97151 | AE144: 12.964098 | AF144: 97.904271 | AG144: 25.997577 | AH144: 100 | AI144: 78.50604 | AJ144: 38.241855 | AK144: 19.279766 | AL144: 96.076991 | AM144: 97.729767 | AN144: 100 | AO144: 27.157287 | AP144: 32.574195 | AQ144: 3.9147588 | AR144: 100 | AS144: 3.9844213 | AT144: 89.555221 | AU144: 93.886463 | AV144: 10.541986 | AW144: 0
B145: 136 | C145: 9 | D145: QUETZALTENANGO | E145: 924 | F145: Palestina De Los Altos | G145: 100 | H145: 100 | I145: 0 | J145: 0 | K145: 21.721592 | L145: 100 | M145: 65.257159 | N145: 22.53629 | O145: 23.941919 | P145: 96.5 | Q145: 50.268176 | R145: 56.704104 | S145: 18.75 | T145: 20.064941 | U145: 53.872414 | V145: 43.51748 | W145: 74.764706 | X145: 4.2798631 | Y145: 56.439275 | Z145: 39.267341 | AA145: 72.376805 | AB145: 15.325209 | AC145: 46.280107 | AD145: 10.204082 | AE145: 18.279987 | AF145: 96.408381 | AG145: 36.69458 | AH145: 100 | AI145: 78.50604 | AJ145: 38.241855 | AK145: 19.279766 | AL145: 81.859488 | AM145: 97.729767 | AN145: 100 | AO145: 48.544223 | AP145: 45.931144 | AQ145: 1.5247763 | AR145: 44.229224 | AS145: 3.9844213 | AT145: 83.166805 | AU145: 93.886463 | AV145: 15.132924 | AW145: 0
B146: 137 | C146: 10 | D146: SUCHITEPEQUEZ | E146: 1001 | F146: Mazatenango | G146: 0 | H146: 91.891398 | I146: 46.995156 | J146: 58.333333 | K146: 27.0214 | L146: 100 | M146: 61.98794 | N146: 37.778034 | O146: 40.717669 | P146: 98.26 | Q146: 69.891387 | R146: 50.638015 | S146: 14.747191 | T146: 58.730741 | U146: 53.872414 | V146: 98.378422 | W146: 68.626506 | X146: 57.444853 | Y146: 95.655098 | Z146: 87.732492 | AA146: 100 | AB146: 100 | AC146: 18.316645 | AD146: 10.087552 | AE146: 7.2154031 | AF146: 23.071058 | AG146: 76.247192 | AH146: 100 | AI146: 78.06149 | AJ146: 60.681624 | AK146: 34.600654 | AL146: 66.569928 | AM146: 72.907154 | AN146: 100 | AO146: 21.804725 | AP146: 40.740098 | AQ146: 0.78909121 | AR146: 10.936704 | AS146: 1.0054167 | AT146: 82.179112 | AU146: 93.886463 | AV146: 24.717085 | AW146: 0
B147: 138 | C147: 10 | D147: SUCHITEPEQUEZ | E147: 1002 | F147: Cuyotenango | G147: 61.845599 | H147: 100 | I147: 50.386831 | J147: 58.333333 | K147: 22.960535 | L147: 100 | M147: 61.98794 | N147: 34.374229 | O147: 38.117546 | P147: 95.39 | Q147: 71.376952 | R147: 66.928036 | S147: 41.758242 | T147: 41.097162 | U147: 53.872414 | V147: 78.741802 | W147: 70.120482 | X147: 5.5423533 | Y147: 93.503194 | Z147: 37.071687 | AA147: 72.033155 | AB147: 59.890877 | AC147: 21.076516 | AD147: 2.4509804 | AE147: 8.4703971 | AF147: 37.758108 | AG147: 42.460126 | AH147: 100 | AI147: 78.06149 | AJ147: 60.681624 | AK147: 34.600654 | AL147: 84.579129 | AM147: 72.907154 | AN147: 100 | AO147: 29.945594 | AP147: 47.82613 | AQ147: 1.2121434 | AR147: 62.904693 | AS147: 1.0054167 | AT147: 78.186345 | AU147: 93.886463 | AV147: 13.491507 | AW147: 0
B148: 139 | C148: 10 | D148: SUCHITEPEQUEZ | E148: 1003 | F148: San Francisco Zapotitlán | G148: 54.116867 | H148: 100 | I148: 0 | J148: 58.333333 | K148: 26.045631 | L148: 100 | M148: 61.98794 | N148: 35.689227 | O148: 39.125568 | P148: 96.97 | Q148: 95.311617 | R148: 67.206034 | S148: 15.833333 | T148: 50.291534 | U148: 53.872414 | V148: 83.645712 | W148: 64.891566 | X148: 0.52461537 | Y148: 81.533231 | Z148: 54.438584 | AA148: 83.705511 | AB148: 63.331652 | AC148: 19.856554 | AD148: 5.6818182 | AE148: 9.3756305 | AF148: 97.316825 | AG148: 11.962808 | AH148: 100 | AI148: 78.06149 | AJ148: 60.681624 | AK148: 34.600654 | AL148: 94.711514 | AM148: 72.907154 | AN148: 100 | AO148: 35.817643 | AP148: 52.93732 | AQ148: 1.1004811 | AR148: 100 | AS148: 1.0054167 | AT148: 75.306342 | AU148: 93.886463 | AV148: 3.3589311 | AW148: 0
B149: 140 | C149: 10 | D149: SUCHITEPEQUEZ | E149: 1004 | F149: San Bernardino | G149: 45.799166 | H149: 98.819856 | I149: 65.918478 | J149: 58.333333 | K149: 26.12018 | L149: 100 | M149: 61.98794 | N149: 39.581121 | O149: 42.091994 | P149: 93.95 | Q149: 73.910006 | R149: 18.333377 | S149: 23.4375 | T149: 36.990171 | U149: 53.872414 | V149: 65.053705 | W149: 70.120482 | X149: 4.9531688 | Y149: 74.674039 | Z149: 43.90107 | AA149: 74.699767 | AB149: 59.744193 | AC149: 23.457538 | AD149: 0 | AE149: 8.5444561 | AF149: 85.208759 | AG149: 20.711117 | AH149: 100 | AI149: 78.06149 | AJ149: 60.681624 | AK149: 34.600654 | AL149: 90.58047 | AM149: 72.907154 | AN149: 100 | AO149: 30.425999 | AP149: 48.244287 | AQ149: 1.5626267 | AR149: 86.499882 | AS149: 1.0054167 | AT149: 77.950726 | AU149: 93.886463 | AV149: 6.2655114 | AW149: 0
... B151: 142 | C151: 10 | D151: SUCHITEPEQUEZ | E151: 1006 | F151: Santo Domingo Suchitepéquez | G151: 54.836687 | H151: 100 | I151: 74.738684 | J151: 58.333333 | K151: 30.768431 | L151: 100 | M151: 61.98794 | N151: 35.802989 | O151: 39.212278 | P151: 92.9 | Q151: 43.241695 | R151: 41.053056 | S151: 7.0247934 | T151: 32.731192 | U151: 53.872414 | V151: 69.148612 | W151: 70.493976 | X151: 3.6586167 | Y151: 91.754773 | Z151: 38.388957 | AA151: 71.025921 | AB151: 24.62572 | AC151: 27.083259 | AD151: 2.6455026 | AE151: 10.493313 | AF151: 85.158588 | AG151: 53.323412 | AH151: 100 | AI151: 78.06149 | AJ151: 60.681624 | AK151: 34.600654 | AL151: 86.991364 | AM151: 72.907154 | AN151: 100 | AO151: 43.067803 | AP151: 59.248056 | AQ151: 0.46833381 | AR151: 59.990213 | AS151: 1.0054167 | AT151: 71.750432 | AU151: 93.886463 | AV151: 17.100778 | AW151: 0
B152: 143 | C152: 10 | D152: SUCHITEPEQUEZ | E152: 1007 | F152: San Lorenzo | G152: 53.237308 | H152: 100 | I152: 100 | J152: 58.333333 | K152: 25.788185 | L152: 100 | M152: 61.98794 | N152: 35.959164 | O152: 39.331316 | P152: 93.14 | Q152: 63.07893 | R152: 34.102906 | S152: 36.666667 | T152: 31.942385 | U152: 53.872414 | V152: 61.094772 | W152: 69.746988 | X152: 0.84142252 | Y152: 84.357605 | Z152: 60.284264 | AA152: 100 | AB152: 7.4209308 | AC152: 23.354372 | AE152: 6.5182505 | AF152: 88.406236 | AG152: 19.154502 | AH152: 100 | AI152: 78.06149 | AJ152: 60.681624 | AK152: 34.600654 | AL152: 93.130255 | AM152: 72.907154 | AN152: 100 | AO152: 17.282451 | AP152: 36.803788 | AQ152: 0.86908719 | AR152: 100 | AS152: 1.0054167 | AT152: 84.397105 | AU152: 93.886463 | AV152: 5.7483341 | AW152: 0
B153: 144 | C153: 10 | D153: SUCHITEPEQUEZ | E153: 1008 | F153: Samayac | G153: 62.774726 | H153: 100 | I153: 71.970253 | J153: 58.333333 | K153: 38.879421 | L153: 100 | M153: 61.98794 | N153: 38.150224 | O153: 41.001356 | P153: 97.98 | Q153: 71.96487 | R153: 55.901628 | S153: 46.875 | T153: 52.186995 | U153: 53.872414 | V153: 69.265689 | W153: 67.13253 | X153: 0.39322343 | Y153: 92.158255 | Z153: 45.901132 | AA153: 76.117593 | AB153: 49.521129 | AC153: 18.665336 | AD153: 7.9365079 | AE153: 10.992518 | AF153: 75.520601 | AG153: 11.732881 | AH153: 100 | AI153: 78.06149 | AJ153: 60.681624 | AK153: 34.600654 | AL153: 91.772164 | AM153: 72.907154 | AN153: 100 | AO153: 46.306036 | AP153: 62.066701 | AQ153: 3.7555182 | AR153: 81.63567 | AS153: 1.0054167 | AT153: 70.16221 | AU153: 93.886463 | AV153: 3.2825389 | AW153: 0
B154: 145 | C154: 10 | D154: SUCHITEPEQUEZ | E154: 1009 | F154: San Pablo Jocopilas | G154: 76.008389 | H154: 100 | I154: 73.104916 | J154: 58.333333 | K154: 21.889452 | L154: 100 | M154: 61.98794 | N154: 37.883904 | O154: 40.798365 | P154: 98.24 | Q154: 84.75 | R154: 53.953377 | S154: 15.441176 | T154: 42.936549 | U154: 53.872414 | V154: 75.225223 | W154: 86.554217 | X154: 0.72744289 | Y154: 75.481003 | Z154: 49.327146 | AA154: 94.989807 | AB154: 43.788228 | AC154: 21.271152 | AD154: 7.2115385 | AE154: 15.071787 | AF154: 89.811223 | AG154: 7.0035439 | AH154: 100 | AI154: 78.06149 | AJ154: 60.681624 | AK154: 34.600654 | AL154: 86.292631 | AM154: 72.907154 | AN154: 100 | AO154: 72.76735 | AP154: 85.099344 | AQ154: 0.54348638 | AR154: 26.667639 | AS154: 1.0054167 | AT154: 57.184005 | AU154: 93.886463 | AV154: 1.7112412 | AW154: 0
B155: 146 | C155: 10 | D155: SUCHITEPEQUEZ | E155: 1010 | F155: San Antonio Suchitepéquez | G155: 64.023766 | H155: 100 | I155: 72.344354 | J155: 58.333333 | K155: 15.263857 | L155: 100 | M155: 61.98794 | N155: 41.23954 | O155: 43.356052 | P155: 94.52 | Q155: 53.622304 | R155: 44.406767 | S155: 54.6875 | T155: 27.356189 | U155: 53.872414 | V155: 59.787506 | W155: 65.638554 | X155: 4.0195839 | Y155: 69.832256 | Z155: 39.261268 | AA155: 79.154403 | AB155: 62.985075 | AC155: 24.365529 | AD155: 8.0287929 | AE155: 9.2096756 | AF155: 56.673785 | AG155: 47.026462 | AH155: 100 | AI155: 78.06149 | AJ155: 60.681624 | AK155: 34.600654 | AL155: 89.369885 | AM155: 72.907154 | AN155: 100 | AO155: 34.74113 | AP155: 52.000294 | AQ155: 2.7785442 | AR155: 78.254303 | AS155: 1.0054167 | AT155: 75.834329 | AU155: 93.886463 | AV155: 15.008649 | AW155: 0
B156: 147 | C156: 10 | D156: SUCHITEPEQUEZ | E156: 1011 | F156: San Miguel Panán | G156: 88.95593 | H156: 100 | I156: 52.586281 | J156: 58.333333 | K156: 12.612262 | L156: 100 | M156: 61.98794 | N156: 41.491723 | O156: 43.548267 | P156: 92.75 | Q156: 72.084309 | R156: 34.283831 | S156: 17.5 | T156: 33.989156 | U156: 53.872414 | V156: 52.419634 | W156: 68.253012 | X156: 12.001609 | Y156: 67.142377 | Z156: 37.231002 | AA156: 82.349175 | AB156: 0 | AC156: 28.864385 | AE156: 8.1111669 | AF156: 100 | AG156: 29.327163 | AH156: 100 | AI156: 78.06149 | AJ156: 60.681624 | AK156: 34.600654 | AL156: 86.171463 | AM156: 72.907154 | AN156: 100 | AO156: 27.615347 | AP156: 45.79782 | AQ156: 0.95604817 | AR156: 71.617942 | AS156: 1.0054167 | AT156: 79.329237 | AU156: 93.886463 | AV156: 9.128148 | AW156: 0
B157: 148 | C157: 10 | D157: SUCHITEPEQUEZ | E157: 1012 | F157: San Gabriel | G157: 4.1822237 | H157: 98.178763 | I157: 0 | J157: 58.333333 | K157: 38.75928 | L157: 100 | M157: 61.98794 | N157: 36.909369 | O157: 40.055568 | P157: 96.44 | Q157: 96.674446 | R157: 68.012112 | S157: 40.625 | T157: 70.003601 | U157: 53.872414 | V157: 98.398418 | W157: 74.975904 | X157: 1.0270726 | Y157: 90.544327 | Z157: 44.465908 | AA157: 76.194236 | AB157: 88.001558 | AC157: 18.128849 | AD157: 0 | AE157: 10.291 | AF157: 100 | AG157: 5.0412631 | AH157: 100 | AI157: 78.06149 | AJ157: 60.681624 | AK157: 34.600654 | AL157: 94.846708 | AM157: 72.907154 | AN157: 100 | AO157: 41.755442 | AP157: 58.105741 | AQ157: 1.2187354 | AR157: 99.297 | AS157: 1.0054167 | AT157: 72.394092 | AU157: 93.886463 | AV157: 1.0592835 | AW157: 0
B158: 149 | C158: 10 | D158: SUCHITEPEQUEZ | E158: 1013 | F158: Chicacao | G158: 72.443791 | H158: 100 | I158: 0 | J158: 58.333333 | K158: 33.350346 | L158: 100 | M158: 61.98794 | N158: 40.796002 | O158: 43.017984 | P158: 89.83 | Q158: 73.950279 | R158: 47.960258 | S158: 9.2592593 | T158: 21.050495 | U158: 53.872414 | V158: 40.874134 | W158: 67.13253 | X158: 2.5529434 | Y158: 77.901894 | Z158: 39.373639 | AA158: 73.301094 | AB158: 20.109566 | AC158: 24.020921 | AD158: 3.5273369 | AE158: 14.35124 | AF158: 60.115928 | AG158: 20.561343 | AH158: 100 | AI158: 78.06149 | AJ158: 60.681624 | AK158: 34.600654 | AL158: 85.996818 | AM158: 72.907154 | AN158: 100 | AO158: 68.093322 | AP158: 81.030944 | AQ158: 0.52951438 | AR158: 29.370303 | AS158: 1.0054167 | AT158: 59.476427 | AU158: 93.886463 | AV158: 6.2157499 | AW158: 0
B159: 150 | C159: 10 | D159: SUCHITEPEQUEZ | E159: 1014 | F159: Patulul | G159: 3.5158003 | H159: 96.38642 | I159: 71.774248 | J159: 58.333333 | K159: 28.442583 | L159: 100 | M159: 61.98794 | N159: 50.743231 | O159: 50.595148 | P159: 93.5 | Q159: 71.281663 | R159: 20.063444 | S159: 6.9277108 | T159: 32.170308 | U159: 53.872414 | V159: 71.735448 | W159: 65.638554 | X159: 5.9472644 | Y159: 85.837038 | Z159: 33.03336 | AA159: 85.570533 | AB159: 65.025068 | AC159: 21.137532 | AD159: 7.6992754 | AE159: 7.9435759 | AF159: 76.334642 | AG159: 46.747009 | AH159: 100 | AI159: 78.06149 | AJ159: 60.681624 | AK159: 34.600654 | AL159: 88.827411 | AM159: 72.907154 | AN159: 100 | AO159: 26.528221 | AP159: 44.851556 | AQ159: 0.3844853 | AR159: 82.652209 | AS159: 1.0054167 | AT159: 79.862428 | AU159: 93.886463 | AV159: 14.915802 | AW159: 0
B160: 151 | C160: 10 | D160: SUCHITEPEQUEZ | E160: 1015 | F160: Santa Bárbara | G160: 71.401966 | H160: 100 | I160: 100 | J160: 58.333333 | K160: 24.458845 | L160: 100 | M160: 61.98794 | N160: 48.588009 | O160: 48.957102 | P160: 91.83 | Q160: 70.445415 | R160: 43.143903 | S160: 3.90625 | T160: 19.694045 | U160: 53.872414 | V160: 62.335295 | W160: 65.638554 | X160: 3.9332883 | Y160: 76.018979 | Z160: 33.864324 | AA160: 77.990153 | AB160: 21.170362 | AC160: 24.320005 | AD160: 1.1820331 | AE160: 10.621612 | AF160: 80.081125 | AG160: 46.118531 | AH160: 100 | AI160: 78.06149 | AJ160: 60.681624 | AK160: 34.600654 | AL160: 92.384607 | AM160: 72.907154 | AN160: 100 | AO160: 43.900048 | AP160: 59.972464 | AQ160: 0.13165462 | AR160: 86.161012 | AS160: 1.0054167 | AT160: 71.34225 | AU160: 93.886463 | AV160: 14.706993 | AW160: 0
B161: 152 | C161: 10 | D161: SUCHITEPEQUEZ | E161: 1016 | F161: San Juan Bautista | G161: 0 | H161: 100 | I161: 100 | J161: 58.333333 | K161: 32.886539 | L161: 100 | M161: 61.98794 | N161: 51.222608 | O161: 50.96521 | P161: 92.5 | Q161: 77.073991 | R161: 39.414967 | S161: 6.7307692 | T161: 24.090675 | U161: 53.872414 | V161: 83.866005 | W161: 66.385542 | X161: 14.058873 | Y161: 99.017447 | Z161: 33.316903 | AA161: 81.312127 | AB161: 5.4327566 | AC161: 26.263491 | AE161: 9.8005085 | AF161: 100 | AG161: 21.192201 | AH161: 100 | AI161: 78.06149 | AJ161: 60.681624 | AK161: 34.600654 | AL161: 90.284106 | AM161: 72.907154 | AN161: 100 | AO161: 38.573733 | AP161: 55.336295 | AQ161: 0.4516701 | AR161: 79.47305 | AS161: 1.0054167 | AT161: 73.954592 | AU161: 93.886463 | AV161: 6.4253492 | AW161: 0
B162: 153 | C162: 10 | D162: SUCHITEPEQUEZ | E162: 1017 | F162: Santo Tomás La Unión | G162: 29.899528 | H162: 100 | I162: 64.218186 | J162: 58.333333 | K162: 7.7686809 | L162: 100 | M162: 61.98794 | N162: 37.244735 | O162: 40.311186 | P162: 96.51 | Q162: 97.386364 | R162: 55.414517 | S162: 12.5 | T162: 60.471776 | U162: 53.872414 | V162: 75.514215 | W162: 68.253012 | X162: 10.160928 | Y162: 83.012665 | Z162: 40.040708 | AA162: 100 | AB162: 94.122162 | AC162: 21.199979 | AD162: 7.5376884 | AE162: 7.7860701 | AF162: 100 | AG162: 26.013914 | AH162: 100 | AI162: 78.06149 | AJ162: 60.681624 | AK162: 34.600654 | AL162: 80.164724 | AM162: 72.907154 | AN162: 100 | AO162: 25.506516 | AP162: 43.962236 | AQ162: 0.50658977 | AR162: 51.742053 | AS162: 1.0054167 | AT162: 80.363534 | AU162: 93.886463 | AV162: 8.0273384 | AW162: 0
B163: 154 | C163: 10 | D163: SUCHITEPEQUEZ | E163: 1018 | F163: Zunilito | G163: 88.104417 | H163: 100 | I163: 53.152696 | J163: 58.333333 | K163: 52.518593 | L163: 100 | M163: 61.98794 | N163: 34.546022 | O163: 38.25421 | P163: 98.73 | Q163: 97.944835 | R163: 68.761588 | S163: 5.3571429 | T163: 29.211041 | U163: 53.872414 | V163: 66.012494 | W163: 65.638554 | X163: 1.6531618 | Y163: 94.579146 | Z163: 67.965853 | AA163: 87.495409 | AB163: 56.291515 | AC163: 20.898901 | AD163: 6.8728522 | AE163: 11.575715 | AF163: 100 | AG163: 15.858529 | AH163: 100 | AI163: 78.06149 | AJ163: 60.681624 | AK163: 34.600654 | AL163: 95.749229 | AM163: 72.907154 | AN163: 100 | AO163: 50.089106 | AP163: 65.359587 | AQ163: 0.33381348 | AR163: 100 | AS163: 1.0054167 | AT163: 68.306767 | AU163: 93.886463 | AV163: 4.6532643 | AW163: 0
B164: 155 | C164: 10 | D164: SUCHITEPEQUEZ | E164: 1019 | F164: Pueblo Nuevo | G164: 49.919752 | H164: 100 | I164: 39.211986 | J164: 58.333333 | K164: 34.099315 | L164: 100 | M164: 61.98794 | N164: 32.674875 | O164: 36.82801 | P164: 97.04 | Q164: 97.354915 | R164: 39.291816 | S164: 18.75 | T164: 50.473186 | U164: 53.872414 | V164: 57.922918 | W164: 67.879518 | X164: 12.276776 | Y164: 95.251616 | Z164: 54.983324 | AA164: 82.270233 | AB164: 62.083224 | AC164: 20.897533 | AD164: 18.518519 | AE164: 7.1233224 | AF164: 95.0938 | AG164: 11.803012 | AH164: 100 | AI164: 78.06149 | AJ164: 60.681624 | AK164: 34.600654 | AL164: 89.724212 | AM164: 72.907154 | AN164: 100 | AO164: 21.207418 | AP164: 40.220185 | AQ164: 1.746729 | AR164: 90.032152 | AS164: 1.0054167 | AT164: 82.472067 | AU164: 93.886463 | AV164: 3.3058396 | AW164: 0
B165: 156 | C165: 10 | D165: SUCHITEPEQUEZ | E165: 1020 | F165: Río Bravo | G165: 40.221661 | H165: 100 | I165: 87.768441 | J165: 58.333333 | K165: 30.029101 | L165: 100 | M165: 61.98794 | N165: 47.919578 | O165: 48.44762 | P165: 91.48 | Q165: 58.208255 | R165: 40.956754 | S165: 79.545455 | T165: 29.924617 | U165: 53.872414 | V165: 83.88004 | W165: 69.373494 | X165: 2.2917998 | Y165: 84.89558 | Z165: 40.807019 | AA165: 70.670254 | AB165: 44.80974 | AC165: 26.141177 | AD165: 0 | AE165: 9.519799 | AF165: 87.150149 | AG165: 52.967961 | AH165: 100 | AI165: 78.06149 | AJ165: 60.681624 | AK165: 34.600654 | AL165: 93.779569 | AM165: 72.907154 | AN165: 100 | AO165: 36.752832 | AP165: 53.751334 | AQ165: 3.7458529 | AR165: 96.441061 | AS165: 1.0054167 | AT165: 74.84767 | AU165: 93.886463 | AV165: 16.982681 | AW165: 0
B166: 157 | C166: 10 | D166: SUCHITEPEQUEZ | E166: 1021 | F166: San José La Máquina | G166: 69.855458 | H166: 100 | I166: 0 | J166: 58.333333 | K166: 17.097396 | L166: 100 | M166: 61.98794 | N166: 24.073715 | O166: 19.761891 | P166: 94.52 | Q166: 15.013203 | R166: 32.383689 | S166: 6.122449 | T166: 47.465989 | U166: 53.872414 | V166: 78.742742 | W166: 70.120482 | X166: 1.3339356 | Y166: 93.503194 | Z166: 41.614461 | AA166: 81.276726 | AB166: 69.427953 | AC166: 25.371312 | AD166: 2.0325203 | AE166: 11.876246 | AF166: 84.132204 | AG166: 8.7252677 | AH166: 100 | AI166: 78.06149 | AJ166: 60.681624 | AK166: 34.600654 | AL166: 93.819585 | AM166: 72.907154 | AN166: 100 | AO166: 52.03858 | AP166: 67.056462 | AQ166: 0.36129622 | AR166: 89.595542 | AS166: 1.0054167 | AT166: 67.350629 | AU166: 93.886463 | AV166: 2.283275 | AW166: 0
B167: 158 | C167: 11 | D167: RETALHULEU | E167: 1101 | F167: Retalhuleu | G167: 7.360421 | H167: 97.817261 | I167: 0 | J167: 33.333333 | K167: 27.412104 | L167: 100 | M167: 35.460801 | N167: 28.63404 | O167: 33.748059 | P167: 95.59 | Q167: 59.254215 | R167: 59.218668 | S167: 9.9246231 | T167: 47.64115 | U167: 53.872414 | V167: 99.976816 | W167: 68.62069 | X167: 40.115081 | Y167: 100 | Z167: 76.666324 | AA167: 100 | AB167: 100 | AC167: 38.069411 | AD167: 9.0065989 | AE167: 9.1420841 | AF167: 36.695709 | AG167: 80.85328 | AH167: 100 | AI167: 71.815077 | AJ167: 50.732525 | AK167: 31.309514 | AL167: 73.4296 | AM167: 69.866667 | AN167: 100 | AO167: 28.617921 | AP167: 39.43459 | AQ167: 0.53719027 | AR167: 36.090332 | AS167: 5.9818609 | AT167: 85.135043 | AU167: 93.886463 | AV167: 27.546919 | AW167: 0
B168: 159 | C168: 11 | D168: RETALHULEU | E168: 1102 | F168: San Sebastián | G168: 73.257013 | H168: 100 | I168: 7.2689512 | J168: 33.333333 | K168: 37.730069 | L168: 100 | M168: 35.460801 | N168: 30.294432 | O168: 35.01362 | P168: 98.43 | Q168: 45.955091 | R168: 54.450244 | S168: 42.857143 | T168: 51.97798 | U168: 53.872414 | V168: 80.487205 | W168: 72.758621 | X168: 4.4355256 | Y168: 96.960068 | Z168: 44.371795 | AA168: 91.406896 | AB168: 75.64038 | AC168: 33.850122 | AD168: 2.9895366 | AE168: 10.026843 | AF168: 69.361433 | AG168: 32.371541 | AH168: 100 | AI168: 71.815077 | AJ168: 50.732525 | AK168: 31.309514 | AL168: 89.541782 | AM168: 69.866667 | AN168: 100 | AO168: 33.806995 | AP168: 43.251019 | AQ168: 3.9231819 | AR168: 86.280402 | AS168: 5.9818609 | AT168: 83.199479 | AU168: 93.886463 | AV168: 10.659907 | AW168: 0
B169: 160 | C169: 11 | D169: RETALHULEU | E169: 1103 | F169: Santa Cruz Muluá | G169: 61.238416 | H169: 100 | I169: 73.934662 | J169: 33.333333 | K169: 31.919904 | L169: 100 | M169: 35.460801 | N169: 30.7817 | O169: 35.385019 | P169: 92.92 | Q169: 65.672609 | R169: 30.181902 | S169: 17.96875 | T169: 36.864432 | U169: 53.872414 | V169: 65.627664 | W169: 71.37931 | X169: 8.7652347 | Y169: 86.511258 | Z169: 76.260552 | AA169: 76.263633 | AB169: 59.752792 | AC169: 41.025798 | AD169: 0 | AE169: 6.9266549 | AF169: 100 | AG169: 57.439718 | AH169: 100 | AI169: 71.815077 | AJ169: 50.732525 | AK169: 31.309514 | AL169: 90.468748 | AM169: 69.866667 | AN169: 100 | AO169: 15.624526 | AP169: 29.878285 | AQ169: 0.6561177 | AR169: 100 | AS169: 5.9818609 | AT169: 89.981679 | AU169: 93.886463 | AV169: 19.391578 | AW169: 0
B170: 161 | C170: 11 | D170: RETALHULEU | E170: 1104 | F170: San Martín Zapotitlán | G170: 62.212342 | H170: 100 | I170: 15.268689 | J170: 33.333333 | K170: 20.385736 | L170: 100 | M170: 35.460801 | N170: 31.567509 | O170: 35.983968 | P170: 97.11 | Q170: 79.948774 | R170: 59.253392 | S170: 35.416667 | T170: 52.379536 | U170: 53.872414 | V170: 80.468083 | W170: 69.310345 | X170: 18.331639 | Y170: 95.000917 | Z170: 61.371317 | AA170: 100 | AB170: 92.5852 | AC170: 39.298856 | AD170: 1.9047619 | AE170: 11.119286 | AF170: 82.067068 | AG170: 100 | AH170: 100 | AI170: 71.815077 | AJ170: 50.732525 | AK170: 31.309514 | AL170: 94.948205 | AM170: 69.866667 | AN170: 100 | AO170: 40.214122 | AP170: 47.963295 | AQ170: 1.770321 | AR170: 100 | AS170: 5.9818609 | AT170: 80.809571 | AU170: 93.886463 | AV170: 72.960005 | AW170: 0
B171: 162 | C171: 11 | D171: RETALHULEU | E171: 1105 | F171: San Felipe | G171: 68.925949 | H171: 100 | I171: 0 | J171: 33.333333 | K171: 36.448488 | L171: 100 | M171: 35.460801 | N171: 30.805701 | O171: 35.403313 | P171: 98.05 | Q171: 87.441817 | R171: 51.283886 | S171: 48.4375 | T171: 50.59593 | U171: 53.872414 | V171: 80.098618 | W171: 68.965517 | X171: 2.3218964 | Y171: 87.81736 | Z171: 44.253453 | AA171: 91.379541 | AB171: 63.575019 | AC171: 35.524758 | AD171: 4.3668122 | AE171: 12.318125 | AF171: 81.371216 | AG171: 31.908763 | AH171: 100 | AI171: 71.815077 | AJ171: 50.732525 | AK171: 31.309514 | AL171: 91.050666 | AM171: 69.866667 | AN171: 100 | AO171: 47.245259 | AP171: 53.134514 | AQ171: 2.457002 | AR171: 84.196651 | AS171: 5.9818609 | AT171: 78.186903 | AU171: 93.886463 | AV171: 10.498714 | AW171: 0
B172: 163 | C172: 11 | D172: RETALHULEU | E172: 1106 | F172: San Andrés Villa Seca | G172: 79.800372 | H172: 100 | I172: 85.769576 | J172: 33.333333 | K172: 36.864511 | L172: 100 | M172: 35.460801 | N172: 32.962567 | O172: 37.04729 | P172: 93.16 | Q172: 30.707914 | R172: 52.027617 | S172: 6.0546875 | T172: 25.810353 | U172: 53.872414 | V172: 70.107432 | W172: 71.724138 | X172: 3.9271427 | Y172: 86.250038 | Z172: 41.499838 | AA172: 79.155432 | AB172: 54.08586 | AC172: 51.036965 | AD172: 3.058104 | AE172: 13.042205 | AF172: 56.69342 | AG172: 70.203319 | AH172: 100 | AI172: 71.815077 | AJ172: 50.732525 | AK172: 31.309514 | AL172: 87.486955 | AM172: 69.866667 | AN172: 100 | AO172: 51.491959 | AP172: 56.257851 | AQ172: 0.60156139 | AR172: 64.883135 | AS172: 5.9818609 | AT172: 76.602852 | AU172: 93.886463 | AV172: 23.837357 | AW172: 0
B173: 164 | C173: 11 | D173: RETALHULEU | E173: 1107 | F173: Champerico | G173: 25.651028 | H173: 83.880401 | I173: 70.774299 | J173: 33.333333 | K173: 35.965052 | L173: 100 | M173: 35.460801 | N173: 15.686268 | O173: 23.879184 | P173: 93.62 | Q173: 40.04399 | R173: 36.78329 | S173: 6.0096154 | T173: 33.343418 | U173: 53.872414 | V173: 87.918722 | W173: 69.655172 | X173: 6.5659605 | Y173: 100 | Z173: 45.817877 | AA173: 80.813953 | AB173: 67.674898 | AC173: 48.773034 | AD173: 1.2254902 | AE173: 8.1627108 | AF173: 91.811095 | AG173: 55.481568 | AH173: 100 | AI173: 71.815077 | AJ173: 50.732525 | AK173: 31.309514 | AL173: 84.179744 | AM173: 69.866667 | AN173: 100 | AO173: 22.87394 | AP173: 35.210041 | AQ173: 0.40170189 | AR173: 77.550112 | AS173: 5.9818609 | AT173: 87.277592 | AU173: 93.886463 | AV173: 18.709522 | AW173: 0
... B214: 205 | C214: 13 | D214: HUEHUETENANGO | E214: 1309 | F214: San Ildefonso Ixtahuacán | G214: 100 | H214: 100 | I214: 0 | J214: 0 | K214: 16.577054 | L214: 100 | M214: 43.473794 | N214: 42.453106 | O214: 6.486943 | P214: 72.44 | Q214: 40.931864 | R214: 45.48835 | S214: 10.597826 | T214: 18.430105 | U214: 52.58623 | V214: 8.4046846 | W214: 71.368421 | X214: 4.4459566 | Y214: 45.537563 | Z214: 38.104042 | AA214: 63.769893 | AB214: 8.4919184 | AC214: 9.1322338 | AD214: 1.2437811 | AE214: 9.932451 | AF214: 61.152834 | AG214: 7.5803305 | AH214: 100 | AI214: 51.612693 | AJ214: 17.11144 | AK214: 5.192261 | AL214: 93.752774 | AM214: 28.888889 | AN214: 100 | AO214: 100 | AP214: 58.108381 | AQ214: 0.47177661 | AR214: 89.677141 | AS214: 0.63432736 | AT214: 55.049349 | AU214: 93.886463 | AV214: 3.4811109 | AW214: 0
B215: 206 | C215: 13 | D215: HUEHUETENANGO | E215: 1310 | F215: Santa Bárbara | G215: 100 | H215: 100 | I215: 87.852931 | J215: 0 | K215: 7.9274307 | L215: 100 | M215: 43.473794 | N215: 51.983922 | O215: 11.751429 | P215: 74.91 | Q215: 20.152927 | R215: 60.949042 | S215: 10.606061 | T215: 9.2451267 | U215: 52.58623 | V215: 6.4900739 | W215: 65.403509 | X215: 5.0404553 | Y215: 37.954595 | Z215: 33.102357 | AA215: 67.709118 | AB215: 0 | AC215: 12.147766 | AE215: 10.902317 | AF215: 68.067519 | AG215: 7.4951079 | AH215: 100 | AI215: 51.612693 | AJ215: 17.11144 | AK215: 5.192261 | AL215: 89.711089 | AM215: 28.888889 | AN215: 100 | AO215: 100 | AP215: 63.782441 | AQ215: 0.47751512 | AR215: 61.742174 | AS215: 0.63432736 | AT215: 50.158684 | AU215: 93.886463 | AV215: 3.4350527 | AW215: 0
B216: 207 | C216: 13 | D216: HUEHUETENANGO | E216: 1311 | F216: La Libertad | G216: 100 | H216: 100 | I216: 47.395284 | J216: 0 | K216: 30.561248 | L216: 100 | M216: 43.473794 | N216: 44.014039 | O216: 2.2061704 | P216: 82.98 | Q216: 59.626773 | R216: 46.748591 | S216: 11.538462 | T216: 24.184139 | U216: 52.58623 | V216: 35.838593 | W216: 57.052632 | X216: 5.2797975 | Y216: 59.960072 | Z216: 30.902444 | AA216: 59.016492 | AB216: 0.29636739 | AC216: 11.510135 | AD216: 11.363636 | AE216: 10.762497 | AF216: 67.617689 | AG216: 8.9674347 | AH216: 100 | AI216: 51.612693 | AJ216: 17.11144 | AK216: 5.192261 | AL216: 85.410274 | AM216: 28.888889 | AN216: 100 | AO216: 100 | AP216: 62.964448 | AQ216: 0.67693324 | AR216: 36.831882 | AS216: 0.63432736 | AT216: 50.86374 | AU216: 93.886463 | AV216: 4.2307662 | AW216: 0
B217: 208 | C217: 13 | D217: HUEHUETENANGO | E217: 1312 | F217: La Democracia | G217: 100 | H217: 98.876404 | I217: 57.606563 | J217: 0 | K217: 36.787827 | L217: 100 | M217: 43.473794 | N217: 45.643197 | O217: 13.734476 | P217: 89.9 | Q217: 70.317989 | R217: 69.089872 | S217: 30.514706 | T217: 25.53451 | U217: 52.58623 | V217: 37.051869 | W217: 52.877193 | X217: 5.2309939 | Y217: 69.62464 | Z217: 40.788295 | AA217: 87.94454 | AB217: 27.033778 | AC217: 9.9358997 | AD217: 4.4742729 | AE217: 7.9668396 | AF217: 56.878594 | AG217: 12.58785 | AH217: 100 | AI217: 51.612693 | AJ217: 17.11144 | AK217: 5.192261 | AL217: 85.843908 | AM217: 28.888889 | AN217: 100 | AO217: 99.416859 | AP217: 46.608853 | AQ217: 0.87064149 | AR217: 61.654101 | AS217: 0.63432736 | AT217: 64.961183 | AU217: 93.886463 | AV217: 6.1874059 | AW217: 0
B218: 209 | C218: 13 | D218: HUEHUETENANGO | E218: 1313 | F218: San Miguel Acatán | G218: 100 | H218: 100 | I218: 72.523537 | J218: 0 | K218: 26.414173 | L218: 100 | M218: 43.473794 | N218: 57.267751 | O218: 24.311063 | P218: 76.79 | Q218: 58.306998 | R218: 32.214244 | S218: 6.9078947 | T218: 6.4628157 | U218: 52.58623 | V218: 2.3451736 | W218: 72.561404 | X218: 4.8038391 | Y218: 21.00443 | Z218: 31.029314 | AA218: 52.718163 | AB218: 2.2484754 | AC218: 17.181155 | AD218: 0 | AE218: 10.690449 | AF218: 77.701273 | AG218: 11.116172 | AH218: 100 | AI218: 51.612693 | AJ218: 17.11144 | AK218: 5.192261 | AL218: 76.166287 | AM218: 28.888889 | AN218: 100 | AO218: 100 | AP218: 62.542937 | AQ218: 0.33661391 | AR218: 0 | AS218: 0.63432736 | AT218: 51.227055 | AU218: 93.886463 | AV218: 5.3920432 | AW218: 0
B219: 210 | C219: 13 | D219: HUEHUETENANGO | E219: 1314 | F219: San Rafael La Independencia | G219: 100 | H219: 100 | I219: 87.692182 | J219: 0 | K219: 26.855935 | L219: 100 | M219: 43.473794 | N219: 58.615134 | O219: 25.919203 | P219: 88.38 | Q219: 67.048897 | R219: 39.21035 | S219: 14.0625 | T219: 10.823058 | U219: 52.58623 | V219: 9.3003186 | W219: 68.385965 | X219: 7.7754031 | Y219: 23.086029 | Z219: 36.214145 | AA219: 56.11137 | AB219: 0 | AC219: 14.609179 | AD219: 0 | AE219: 5.2710244 | AF219: 88.865076 | AG219: 9.6308847 | AH219: 100 | AI219: 51.612693 | AJ219: 17.11144 | AK219: 5.192261 | AL219: 79.966369 | AM219: 28.888889 | AN219: 100 | AO219: 57.316744 | AP219: 30.837372 | AQ219: 0.85158389 | AR219: 65.873383 | AS219: 0.63432736 | AT219: 78.555158 | AU219: 93.886463 | AV219: 4.5893252 | AW219: 0
B220: 211 | C220: 13 | D220: HUEHUETENANGO | E220: 1315 | F220: Todos Santos Cuchumatán | G220: 100 | H220: 100 | I220: 72.501179 | J220: 0 | K220: 38.528306 | L220: 100 | M220: 43.473794 | N220: 52.39639 | O220: 12.718602 | P220: 95.45 | Q220: 58.460391 | R220: 29.043612 | S220: 8.6666667 | T220: 20.14942 | U220: 52.58623 | V220: 11.449045 | W220: 64.210526 | X220: 4.4174566 | Y220: 40.630937 | Z220: 24.881451 | AA220: 49.856761 | AB220: 6.7828282 | AC220: 12.922131 | AD220: 0 | AE220: 8.3215456 | AF220: 83.930085 | AG220: 7.1636412 | AH220: 100 | AI220: 51.612693 | AJ220: 17.11144 | AK220: 5.192261 | AL220: 88.998199 | AM220: 28.888889 | AN220: 100 | AO220: 100 | AP220: 48.68401 | AQ220: 0.23624967 | AR220: 73.419868 | AS220: 0.63432736 | AT220: 63.172535 | AU220: 93.886463 | AV220: 3.2559128 | AW220: 0
B221: 212 | C221: 13 | D221: HUEHUETENANGO | E221: 1316 | F221: San Juan Atitán | G221: 100 | H221: 100 | I221: 99.363089 | J221: 0 | K221: 16.879984 | L221: 33.333333 | M221: 43.473794 | N221: 48.124086 | O221: 8.8093947 | P221: 83.86 | Q221: 61.902474 | R221: 48.56604 | S221: 17.96875 | T221: 4.1235556 | U221: 52.58623 | V221: 4.8488164 | W221: 71.964912 | X221: 5.8252456 | Y221: 4.9463787 | Z221: 23.940365 | AA221: 54.075102 | AB221: 0 | AC221: 10.999525 | AE221: 6.645678 | AF221: 92.304487 | AG221: 6.1730665 | AH221: 100 | AI221: 51.612693 | AJ221: 17.11144 | AK221: 5.192261 | AL221: 87.772846 | AM221: 28.888889 | AN221: 100 | AO221: 78.78449 | AP221: 38.879586 | AQ221: 0.94370906 | AR221: 79.282378 | AS221: 0.63432736 | AT221: 71.6233 | AU221: 93.886463 | AV221: 2.7205604 | AW221: 0
B222: 213 | C222: 13 | D222: HUEHUETENANGO | E222: 1317 | F222: Santa Eulalia | G222: 100 | H222: 100 | I222: 20.126199 | J222: 0 | K222: 26.182062 | L222: 100 | M222: 43.473794 | N222: 59.075605 | O222: 26.340472 | P222: 73.15 | Q222: 32.34487 | R222: 29.056891 | S222: 5.1369863 | T222: 12.980514 | U222: 52.58623 | V222: 10.851885 | W222: 64.210526 | X222: 4.3506715 | Y222: 30.222941 | Z222: 30.995502 | AA222: 63.395976 | AB222: 0 | AC222: 11.325012 | AD222: 5.4945055 | AE222: 12.61635 | AF222: 68.11837 | AG222: 6.9756124 | AH222: 100 | AI222: 51.612693 | AJ222: 17.11144 | AK222: 5.192261 | AL222: 80.252954 | AM222: 28.888889 | AN222: 100 | AO222: 100 | AP222: 73.810149 | AQ222: 0.20836491 | AR222: 0 | AS222: 0.63432736 | AT222: 41.515461 | AU222: 93.886463 | AV222: 3.1542933 | AW222: 0
B223: 214 | C223: 13 | D223: HUEHUETENANGO | E223: 1318 | F223: San Mateo Ixtatán | G223: 100 | H223: 100 | I223: 100 | J223: 0 | K223: 13.474946 | L223: 33.333333 | M223: 43.473794 | N223: 59.379901 | O223: 29.097057 | P223: 74.87 | Q223: 63.777619 | R223: 38.927685 | S223: 1.4285714 | T223: 3.8007524 | U223: 52.58623 | V223: 15.079341 | W223: 58.842105 | X223: 5.3153136 | Y223: 22.342601 | Z223: 29.169127 | AA223: 63.507099 | AB223: 0 | AC223: 13.174871 | AD223: 0 | AE223: 15.989861 | AF223: 71.187843 | AG223: 4.8610733 | AH223: 100 | AI223: 51.612693 | AJ223: 17.11144 | AK223: 5.192261 | AL223: 80.860173 | AM223: 28.888889 | AN223: 100 | AO223: 100 | AP223: 93.546389 | AQ223: 0.094357905 | AR223: 0 | AS223: 0.63432736 | AT223: 24.504126 | AU223: 93.886463 | AV223: 2.0114987 | AW223: 0
...

Sheet ICL 2024 (datos serie original)
D2: ÍNDICE DE COMPETITIVIDAD LOCAL
D4: Fundación para el Desarrollo de Guatemala - FUNDESA -
F5: Fuente: | G5: PNC | H5: PNC | I5: OJ | J5: COPADEH | K5: SEGEPLAN | L5: SEGEPLAN | M5: DGC | N5: SEGEPLAN | O5: SEGEPLAN | P5: MEM | Q5: INE | R5: INE | S5: SIT | T5: INE | U5: INE | V5: INE | W5: INE | X5: MINFIN | Y5: MSPAS | Z5: MINFIN | AA5: MINEDUC | AB5: MINEDUC | AC5: INTECAP | AD5: MINEDUC | AE5: SAT | AF5: MINFIN | AG5: IGSS | AH5: IGSS | AI5: IGSS | AJ5: INE | AK5: INE / IGSS | AL5: IGM | AM5: SIB | AN5: SIB | AO5: SIB | AP5: SIB | AQ5: FUNDESA | AR5: BANGUAT | AS5: INGUAT | AT5: Doing Business | AU5: Doing Business | AV5: IGSS | AW5: MINFIN
F6: Año: | G6: 2023 | H6: 2023 | I6: 2023 | J6: 2023 | K6: 2021 | L6: 2023 | M6: 2023 | N6: 2023 | O6: 2023 | P6: 2023 | Q6: 2018 | R6: 2018 | S6: 2023 | T6: 2019 | U6: 2023 | V6: 2023 | W6: 2023 | X6: 2023 | Y6: 2015 | Z6: 2023 | AA6: 2023 | AB6: 2023 | AC6: 2023 | AD6: 2023 | AE6: 2023 | AF6: 2023 | AG6: 2023 | AH6: 2023 | AI6: 2023 | AJ6: 2023 | AK6: 2023 | AL6: 2023 | AM6: 2023 | AN6: 2023 | AO6: 2023 | AP6: 2023 | AQ6: 2023 | AR6: 2023 | AS6: 2023 | AT6: 2019 | AU6: 2019 | AV6: 2023 | AW6: 2023
F7: Desagregación: | G7: municipal | H7: municipal | I7: municipal | J7: departamental | K7: municipal | L7: municipal | M7: municipal | N7: municipal | O7: municipal | P7: municipal | Q7: municipal | R7: municipal | S7: municipal | T7: municipal | U7: regional | V7: municipal | W7: municipal | X7: municipal | Y7: municipal | Z7: municipal | AA7: municipal | AB7: municipal | AC7: municipal | AD7: municipal | AE7: departamental | AF7: municipal | AG7: municipal | AH7: departamental | AI7: departamental | AJ7: departamental | AK7: departamental | AL7: municipal | AM7: departamental | AN7: departamental | AO7: departamental | AP7: departamental | AQ7: municipal | AR7: municipal | AS7: departamental | AT7: nacional | AU7: nacional | AV7: municipal | AW7: municipal
G8: 1.1 | H8: 1.2 | I8: 1.3 | J8: 1.4 | K8: 1.5 | L8: 1.6 | M8: 2.1 | N8: 2.2 | O8: 2.3 | P8: 2.4 | Q8: 2.5 | R8: 2.6 | S8: 3.1 | T8: 3.2 | U8: 4.1 | V8: 4.2 | W8: 4.3 | X8: 5.1 | Y8: 5.2 | Z8: 6.1 | AA8: 6.2 | AB8: 6.3 | AC8: 6.4 | AD8: 6.5 | AE8: 7.1 | AF8: 7.2 | AG8: 8.1 | AH8: 8.2 | AI8: 8.3 | AJ8: 8.4 | AK8: 8.5 | AL8: 8.6 | AM8: 9.1 | AN8: 9.2 | AO8: 9.3 | AP8: 9.4 | AQ8: 10.1 | AR8: 10.2 | AS8: 10.3 | AT8: 11.1 | AU8: 11.2 | AV8: 11.3 | AW8: 12.1
B9: NO. | C9: CÓDIGO DEPARTAMENTO | D9: DEPARTAMENTO | E9: CÓDIGO MUNICIPIO | F9: MUNICIPIO | G9: Extorsiones por 100,000 habitantes | H9: Homicidios por 100,000 habitantes | I9: Faltas por 100,000 habitantes | J9: Casos por Conflictividad | K9: Ranking Gestión Municipal | L9: PDM-OT (finalizado, en proceso, interés) | M9: Brecha de la RED VIAL (% avance PDV 2032) | N9: Distancia (Km) Promedio a Aeropuertos | O9: Distancia (Km) Promedio a Puertos | P9: Tasa de Electrificación (% hogares) | Q9: Cobertura de Agua y Saneamiento | R9: Déficit de Vivienda (% hogares) | S9: Radiobases de Telefonía Celular por Km2 | T9: Usuarios de Internet (% Población) | U9: Tasa de Inflación | V9: Tasa de Pobreza (% Población) | W9: Coeficiente de GINI | X9: Gasto Público en Salud, per cápita (al año) | Y9: Tasa de Desnutrición Crónica | Z9: Gasto Público en Educación, per cápita (al año) | AA9: Tasa Neta de Cobertura (todos niveles) | AB9: Alumnos por Docente (todos niveles) | AC9: Capacitación Técnica (% de la PEA) | AD9: % de LOGRO Graduandos (Mate y Lectura) | AE9: Carga Tributaria Local (% PIB) | AF9: Inversión Pública (% Presupuesto Local) | AG9: % de la PEA afiliada al IGSS | AH9: Afiliados por Patrono Particular | AI9: Peso del Gobierno en la contratación | AJ9: Salario Mínimo como No. veces Ingreso Medio | AK9: Ingreso Medio como % del Salario Formal | AL9: Deportados por 100,000 habitantes | AM9: Km2 a cargo de cada Agencia | AN9: Agentes Bancarios por 100,000 hab. | AO9: Depósitos en relación al PIB per cápita | AP9: Cartera de Créditos en relación al PIB | AQ9: PIB local (US$ al año por Km2) | AR9: Remesas como % del PIB | AS9: Turistas por 1,000 habitantes | AT9: Costo Iniciar un Negocio (% PIB per cápita) | AU9: Tiempo Iniciar un Negocio (días) | AV9: Fuerza Laboral Sector Servicios (% de la PEA) | AW9: Inversión I+D (% presupuesto local)
B10: 271 | C10: 16 | D10: ALTA_VERAPAZ | E10: 1613 | F10: Chisec | G10: 35.624246 | H10: 1.8268844 | I10: 47.498995 | J10: 70 | K10: 43.465054 | L10: 100 | M10: 0.43726577 | N10: 246.3155 | O10: 306.285 | P10: 0.6218 | Q10: 0.16261144 | R10: 0.37476872 | S10: 0.082352941 | T10: 0.049928752 | U10: 0.1190014 | V10: 0.99502535 | W10: 0.25138462 | X10: 85.79944 | Y10: 0.41872372 | Z10: 867.0721 | AA10: 0.50866117 | AB10: 23.020071 | AC10: 0.028370526 | AD10: 0.0066666667 | AE10: 0.012830779 | AF10: 0.32016752 | AG10: 0.08455563 | AH10: 45.900196 | AI10: 0.41654229 | AJ10: 1.7416573 | AK10: 0.38475859 | AL10: 436.62538 | AM10: 99.83908 | AN10: 108.10042 | AO10: 0.36982248 | AP10: 0.14352446 | AQ10: 315323.71 | AR10: 0.45625694 | AS10: 41.455623 | AT10: 0.31162196 | AU10: 15 | AV10: 0.055514347 | AW10: 0
B11: 334 | C11: 22 | D11: JUTIAPA | E11: 2211 | F11: Comapa | G11: 74.523581 | H11: 5.323113 | I11: 23.954008 | J11: 6 | K11: 19.574089 | L11: 100 | M11: 0.47943085 | N11: 315.1325 | O11: 280.20067 | P11: 0.8468 | Q11: 0.44009314 | R11: 0.5972303 | S11: 0.28030303 | T11: 0.10555733 | U11: 0.1047337 | V11: 0.99210512 | W11: 0.32029412 | X11: 135.58214 | Y11: 0.67203453 | Z11: 1321.4804 | AA11: 0.67381383 | AB11: 13.608696 | AC11: 0.035734054 | AD11: 0.0035087719 | AE11: 0.025943957 | AF11: 0.42869224 | AG11: 0.028228131 | AH11: 31.715302 | AI11: 0.50527368 | AJ11: 1.3210327 | AK11: 0.46538338 | AL11: 463.11083 | AM11: 42.355263 | AN11: 255.16085 | AO11: 0.86066456 | AP11: 0.28007831 | AQ11: 610702.03 | AR11: 0.60573938 | AS11: 328.25268 | AT11: 0.35558687 | AU11: 15 | AV11: 0.020535675 | AW11: 0
B12: 266 | C12: 16 | D12: ALTA_VERAPAZ | E12: 1608 | F12: Senahú | G12: 9.8624193 | H12: 0.98624193 | I12: 32.545984 | J12: 70 | K12: 41.305196 | L12: 100 | M12: 0.43726577 | N12: 307.725 | O12: 264.92333 | P12: 0.2522 | Q12: 0.24576118 | R12: 0.60141912 | S12: 0.053571429 | T12: 0.018482174 | U12: 0.1190014 | V12: 0.99040508 | W12: 0.45015385 | X12: 124.96288 | Y12: 0.5494606 | Z12: 922.32207 | AA12: 0.56693078 | AB12: 25.824966 | AC12: 0.032204321 | AD12: 0 | AE12: 0.018234592 | AF12: 0.31586956 | AG12: 0.039561639 | AH12: 45.900196 | AI12: 0.41654229 | AJ12: 1.7416573 | AK12: 0.38475859 | AL12: 71.009419 | AM12: 99.83908 | AN12: 108.10042 | AO12: 0.52557699 | AP12: 0.20397126 | AQ12: 519865.33 | AR12: 0.10545314 | AS12: 41.455623 | AT12: 0.44286474 | AU12: 15 | AV12: 0.025973889 | AW12: 0
B13: 225 | C13: 13 | D13: HUEHUETENANGO | E13: 1329 | F13: San Gaspar Ixchil | G13: 0 | H13: 0 | I13: 317.96502 | J13: 48 | K13: 31.632417 | L13: 100 | M13: 0.43473794 | N13: 402.317 | O13: 507.59167 | P13: 0.5078 | Q13: 0.33287951 | R13: 0.61222139 | S13: 0.25806452 | T13: 0.022164033 | U13: 0.092155147 | V13: 0.99003208 | W13: 0.31017544 | X13: 87.608022 | Y13: 0.78858413 | Z13: 972.40567 | AA13: 0.60420532 | AB13: 22.72093 | AC13: 0.016645053 | AE13: 0.013049228 | AF13: 0.66307159 | AG13: 0.023788198 | AH13: 27.522244 | AI13: 0.53548577 | AJ13: 1.9738722 | AK13: 0.29258884 | AL13: 439.53989 | AM13: 74 | AN13: 136.65571 | AO13: 0.54343388 | AP13: 0.12723773 | AQ13: 998976.81 | AR13: 0.31308117 | AS13: 16.783914 | AT13: 0.26343117 | AU13: 15 | AV13: 0.019048731 | AW13: 0
B14: 275 | C14: 16 | D14: ALTA_VERAPAZ | E14: 1617 | F14: Raxruhá | G14: 19.265039 | H14: 2.4081298 | I14: 113.1821 | J14: 70 | K14: 39.522496 | L14: 100 | M14: 0.43726577 | N14: 252.5 | O14: 293 | P14: 0.5897 | Q14: 0.13755819 | R14: 0.41880402 | S14: 0.049090909 | T14: 0.043755719 | U14: 0.1190014 | V14: 0.98968211 | W14: 0.25138462 | X14: 131.29854 | Y14: 0.40501006 | Z14: 1311.1168 | AA14: 0.55678651 | AB14: 17.083333 | AC14: 0.027193837 | AD14: 0 | AE14: 0.012666156 | AF14: 0.42518373 | AG14: 0.041358036 | AH14: 45.900196 | AI14: 0.41654229 | AJ14: 1.7416573 | AK14: 0.38475859 | AL14: 142.07966 | AM14: 99.83908 | AN14: 108.10042 | AO14: 0.36507754 | AP14: 0.141683 | AQ14: 187250.18 | AR14: 0.14656296 | AS14: 41.455623 | AT14: 0.30762375 | AU14: 15 | AV14: 0.027153299 | AW14: 0
B15: 215 | C15: 13 | D15: HUEHUETENANGO | E15: 1319 | F15: Colotenango | G15: 2.2027887 | H15: 2.2027887 | I15: 182.83146 | J15: 48 | K15: 11.693678 | L15: 100 | M15: 0.43473794 | N15: 397.355 | O15: 502.62967 | P15: 0.7873 | Q15: 0.60490212 | R15: 0.58906077 | S15: 0.1971831 | T15: 0.020684186 | U15: 0.092155147 | V15: 0.9861102 | W15: 0.26842105 | X15: 153.325 | Y15: 0.77908311 | Z15: 1036.8895 | AA15: 0.48263012 | AB15: 18.279904 | AC15: 0.030736082 | AD15: 0 | AE15: 0.017979244 | AF15: 0.37017114 | AG15: 0.047526099 | AH15: 27.522244 | AI15: 0.53548577 | AJ15: 1.9738722 | AK15: 0.29258884 | AL15: 411.92149 | AM15: 74 | AN15: 136.65571 | AO15: 0.74874394 | AP15: 0.17530832 | AQ15: 1344001.4 | AR15: 0.40425902 | AS15: 16.783914 | AT15: 0.36295583 | AU15: 15 | AV15: 0.038057185 | AW15: 0
B16: 270 | C16: 16 | D16: ALTA_VERAPAZ | E16: 1612 | F16: Santa María Cahabón | G16: 11.008821 | H16: 0 | I16: 57.796309 | J16: 70 | K16: 44.690887 | L16: 100 | M16: 0.43726577 | N16: 322.0555 | O16: 275.67967 | P16: 0.2658 | Q16: 0.23665328 | R16: 0.32913536 | S16: 0.0525 | T16: 0.051122212 | U16: 0.1190014 | V16: 0.98596823 | W16: 0.37415385 | X16: 126.93474 | Y16: 0.46717864 | Z16: 1271.9717 | AA16: 0.57144656 | AB16: 15.810685 | AC16: 0.031931969 | AD16: 0 | AE16: 0.017240152 | AF16: 0.31340016 | AG16: 0.042524899 | AH16: 45.900196 | AI16: 0.41654229 | AJ16: 1.7416573 | AK16: 0.38475859 | AL16: 148.61908 | AM16: 99.83908 | AN16: 108.10042 | AO16: 0.49691416 | AP16: 0.1928475 | AQ16: 331022.68 | AR16: 0.20867151 | AS16: 41.455623 | AT16: 0.4187127 | AU16: 15 | AV16: 0.027919395 | AW16: 0
B17: 209 | C17: 13 | D17: HUEHUETENANGO | E17: 1313 | F17: San Miguel Acatán | G17: 0 | H17: 0 | I17: 86.822042 | J17: 48 | K17: 26.414173 | L17: 100 | M17: 0.43473794 | N17: 360.612 | O17: 439.82067 | P17: 0.7679 | Q17: 0.58306998 | R17: 0.73205899 | S17: 0.13815789 | T17: 0.032314079 | U17: 0.092155147 | V17: 0.98475637 | W17: 0.27438596 | X17: 111.62663 | Y17: 0.85086855 | Z17: 886.09865 | AA17: 0.42174531 | AB17: 18.926174 | AC17: 0.03436231 | AD17: 0 | AE17: 0.016035673 | AF17: 0.46620764 | AG17: 0.044464689 | AH17: 27.522244 | AI17: 0.53548577 | AJ17: 1.9738722 | AK17: 0.29258884 | AL17: 651.16531 | AM17: 74 | AN17: 136.65571 | AO17: 0.6678041 | AP17: 0.15635734 | AQ17: 571467.53 | AR17: 0.56997038 | AS17: 16.783914 | AT17: 0.32372 | AU17: 15 | AV17: 0.035605718 | AW17: 0
B18: 264 | C18: 16 | D18: ALTA_VERAPAZ | E18: 1606 | F18: San Miguel Tucurú | G18: 9.4937911 | H18: 5.6962746 | I18: 28.481373 | J18: 70 | K18: 51.592802 | L18: 100 | M18: 0.43726577 | N18: 272.7925 | O18: 256.1 | P18: 0.5185 | Q18: 0.49546269 | R18: 0.50622078 | S18: 0.23958333 | T18: 0.032487753 | U18: 0.1190014 | V18: 0.98387401 | W18: 0.52030769 | X18: 156.48969 | Y18: 0.53391845 | Z18: 1149.1085 | AA18: 0.58171416 | AB18: 20.497006 | AC18: 0.085038578 | AD18: 0 | AE18: 0.011501913 | AF18: 0.38243162 | AG18: 0.081617973 | AH18: 45.900196 | AI18: 0.41654229 | AJ18: 1.7416573 | AK18: 0.38475859 | AL18: 214.55968 | AM18: 99.83908 | AN18: 108.10042 | AO18: 0.33152047 | AP18: 0.12865983 | AQ18: 1498299.7 | AR18: 0.20098594 | AS18: 41.455623 | AT18: 0.2793477 | AU18: 15 | AV18: 0.053585651 | AW18: 0
B19: 231 | C19: 14 | D19: QUICHE | E19: 1402 | F19: Chiché | G19: 6.1156469 | H19: 0 | I19: 51.982999 | J19: 36 | K19: 7.9181467 | L19: 100 | M19: 0.34911013 | N19: 297.0815 | O19: 365.95433 | P19: 0.8907 | Q19: 0.44697741 | R19: 0.61462211 | S19: 0.15972222 | T19: 0.12280219 | U19: 0.092155147 | V19: 0.98180176 | W19: 0.3712 | X19: 205.48221 | Y19: 0.73892442 | Z19: 1216.3998 | AA19: 0.49181818 | AB19: 13.871795 | AC19: 0.01823365 | AD19: 0.076923077 | AE19: 0.011483077 | AF19: 0.39953288 | AG19: 0.055133844 | AH19: 37.557522 | AI19: 0.63198058 | AJ19: 2.1749175 | AK19: 0.25596181 | AL19: 259.91499 | AM19: 110.23684 | AN19: 147.57576 | AO19: 0.43496424 | AP19: 0.15456896 | AQ19: 592394.02 | AR19: 0.38629871 | AS19: 24.561948 | AT19: 0.29248199 | AU19: 15 | AV19: 0.047964819 | AW19: 0
B20: 269 | C20: 16 | D20: ALTA_VERAPAZ | E20: 1611 | F20: Lanquín | G20: 7.3080718 | H20: 3.6540359 | I20: 73.080718 | J20: 70 | K20: 37.64839 | L20: 100 | M20: 0.43726577 | N20: 268.1255 | O20: 284.92333 | P20: 0.3723 | Q20: 0.17195345 | R20: 0.61328112 | S20: 0.052884615 | T20: 0.018927906 | U20: 0.1190014 | V20: 0.97836536 | W20: 0.33323077 | X20: 327.14254 | Y20: 0.55311757 | Z20: 1224.2492 | AA20: 0.56721978 | AB20: 14.523121 | AC20: 0.0319913 | AD20: 0 | AE20: 0.015651664 | AF20: 0.58507458 | AG20: 0.17931322 | AH20: 45.900196 | AI20: 0.41654229 | AJ20: 1.7416573 | AK20: 0.38475859 | AL20: 153.46951 | AM20: 99.83908 | AN20: 108.10042 | AO20: 0.45112904 | AP20: 0.17507874 | AQ20: 264066.32 | AR20: 0.19562758 | AS20: 41.455623 | AT20: 0.38013297 | AU20: 15 | AV20: 0.11772671 | AW20: 0
B21: 318 | C21: 21 | D21: JALAPA | E21: 2102 | F21: San Pedro Pinula | G21: 22.613918 | H21: 16.332274 | I21: 38.946191 | J21: 9 | K21: 35.803646 | L21: 100 | M21: 0.50636672 | N21: 278.3865 | O21: 237.92667 | P21: 0.7338 | Q21: 0.37112635 | R21: 0.58709478 | S21: 0.16489362 | T21: 0.072276593 | U21: 0.1047337 | V21: 0.97609431 | W21: 0.36371429 | X21: 95.854003 | Y21: 0.77941547 | Z21: 1236.8372 | AA21: 0.51339672 | AB21: 16.437736 | AC21: 0.030457067 | AD21: 0 | AE21: 0.013819366 | AF21: 0.45896288 | AG21: 0.026792976 | AH21: 37.364198 | AI21: 0.50876481 | AJ21: 1.7737309 | AK21: 0.36014543 | AL21: 379.41128 | AM21: 52.897436 | AN21: 165.25012 | AO21: 0.65500395 | AP21: 0.19574407 | AQ21: 589152.68 | AR21: 0.26752714 | AS21: 88.821031 | AT21: 0.27413576 | AU21: 15 | AV21: 0.018556343 | AW21: 0
B22: 221 | C22: 13 | D22: HUEHUETENANGO | E22: 1325 | F22: San Sebastián Coatán | G22: 0 | H22: 0 | I22: 57.21042 | J22: 48 | K22: 17.937069 | L22: 100 | M22: 0.43473794 | N22: 364.8935 | O22: 438.98167 | P22: 0.856 | Q22: 0.65008452 | R22: 0.62932657 | S22: 0.06547619 | T22: 0.13352912 | U22: 0.092155147 | V22: 0.97286723 | W22: 0.28035088 | X22: 85.650464 | Y22: 0.71257602 | Z22: 830.41321 | AA22: 0.44160458 | AB22: 12.886288 | AC22: 0.050501679 | AD22: 0 | AE22: 0.010543466 | AF22: 0.55463416 | AG22: 0.066956784 | AH22: 27.522244 | AI22: 0.53548577 | AJ22: 1.9738722 | AK22: 0.29258884 | AL22: 614.05851 | AM22: 74 | AN22: 136.65571 | AO22: 0.43908167 | AP22: 0.10280506 | AQ22: 559404.27 | AR22: 0.35340038 | AS22: 16.783914 | AT22: 0.21284613 | AU22: 15 | AV22: 0.053616576 | AW22: 0
B23: 212 | C23: 13 | D23: HUEHUETENANGO | E23: 1316 | F23: San Juan Atitán | G23: 0 | H23: 0 | I23: 26.433049 | J23: 48 | K23: 16.879984 | L23: 50 | M23: 0.43473794 | N23: 388.422 | O23: 501.67733 | P23: 0.8386 | Q23: 0.61902474 | R23: 0.59605342 | S23: 0.359375 | T23: 0.020617778 | U23: 0.092155147 | V23: 0.96848269 | W23: 0.28035088 | X23: 135.36101 | Y23: 0.96488071 | Z23: 683.66079 | AA23: 0.43260082 | AB23: 23.286585 | AC23: 0.02199905 | AE23: 0.009968517 | AF23: 0.55382692 | AG23: 0.024692266 | AH23: 27.522244 | AI23: 0.53548577 | AJ23: 1.9738722 | AK23: 0.29258884 | AL23: 336.07734 | AM23: 74 | AN23: 136.65571 | AO23: 0.41513796 | AP23: 0.097198966 | AQ23: 1568709.8 | AR23: 0.18287049 | AS23: 16.783914 | AT23: 0.20123935 | AU23: 15 | AV23: 0.019772675 | AW23: 0
B24: 246 | C24: 14 | D24: QUICHE | E24: 1417 | F24: San Bartolomé Jocotenango | G24: 18.577002 | H24: 0 | I24: 80.500341 | J24: 36 | K24: 17.957939 | L24: 50 | M24: 0.34911013 | N24: 312.1175 | O24: 407.48333 | P24: 0.633 | Q24: 0.55454545 | R24: 0.75462489 | S24: 0.032520325 | T24: 0.06861106 | U24: 0.092155147 | V24: 0.9668542 | W24: 0.2368 | X24: 351.33472 | Y24: 0.7433624 | Z24: 1226.4233 | AA24: 0.61989305 | AB24: 19.065789 | AC24: 0.02433987 | AE24: 0.011249723 | AF24: 0.80016665 | AG24: 0.039744187 | AH24: 37.557522 | AI24: 0.63198058 | AJ24: 2.1749175 | AK24: 0.25596181 | AL24: 123.84668 | AM24: 110.23684 | AN24: 147.57576 | AO24: 0.42612507 | AP24: 0.15142787 | AQ24: 349576.76 | AR24: 0.18032661 | AS24: 24.561948 | AT24: 0.28653829 | AU24: 15 | AV24: 0.034576271 | AW24: 0
B25: 272 | C25: 16 | D25: ALTA_VERAPAZ | E25: 1614 | F25: Chahal | G25: 22.711051 | H25: 16.222179 | I25: 103.82195 | J25: 70 | K25: 15.089238 | L25: 100 | M25: 0.43726577 | N25: 297.445 | O25: 273.41067 | P25: 0.4031 | Q25: 0.30274408 | R25: 0.42178767 | S25: 0.017857143 | T25: 0.04824476 | U25: 0.1190014 | V25: 0.96293471 | W25: 0.34492308 | X25: 377.86419 | Y25: 0.5037484 | Z25: 1267.1291 | AA25: 0.59237357 | AB25: 15.788043 | AC25: 0.038887551 | AD25: 0 | AE25: 0.015647872 | AF25: 0.47330994 | AG25: 0.068340793 | AH25: 45.900196 | AI25: 0.41654229 | AJ25: 1.7416573 | AK25: 0.38475859 | AL25: 246.57712 | AM25: 99.83908 | AN25: 108.10042 | AO25: 0.45101975 | AP25: 0.17503632 | AQ25: 92075.889 | AR25: 0.31423571 | AS25: 41.455623 | AT25: 0.38004088 | AU25: 15 | AV25: 0.044868621 | AW25: 0
B26: 202 | C26: 13 | D26: HUEHUETENANGO | E26: 1306 | F26: San Pedro Necta | G26: 0 | H26: 7.1304637 | I26: 209.16027 | J26: 48 | K26: 18.253691 | L26: 100 | M26: 0.43473794 | N26: 405.021 | O26: 524.24967 | P26: 0.8502 | Q26: 0.56108215 | R26: 0.57895812 | S26: 0.092436975 | T26: 0.1106648 | U26: 0.092155147 | V26: 0.96063165 | W26: 0.36385965 | X26: 652.94181 | Y26: 0.70201934 | Z26: 1414.2282 | AA26: 0.58333939 | AB26: 15.565891 | AC26: 0.021262394 | AD26: 0.0093457944 | AE26: 0.016915962 | AF26: 0.44990928 | AG26: 0.044216153 | AH26: 27.522244 | AI26: 0.53548577 | AJ26: 1.9738722 | AK26: 0.29258884 | AL26: 399.30597 | AM26: 74 | AN26: 136.65571 | AO26: 0.70446364 | AP26: 0.16494068 | AQ26: 789881.93 | AR26: 0.36870271 | AS26: 16.783914 | AT26: 0.34149082 | AU26: 15 | AV26: 0.0354067 | AW26: 0
B27: 258 | C27: 15 | D27: BAJA_VERAPAZ | E27: 1508 | F27: Purulhá | G27: 40.066481 | H27: 1.4839437 | I27: 40.066481 | J27: 32 | K27: 30.134727 | L27: 100 | M27: 0.37542968 | N27: 246.4095 | O27: 286.164 | P27: 0.4036 | Q27: 0.34816995 | R27: 0.42100294 | S27: 0.088709677 | T27: 0.084881581 | U27: 0.1190014 | V27: 0.95992373 | W27: 0.41352941 | X27: 134.02421 | Y27: 0.76714772 | Z27: 1037.8867 | AA27: 0.57591757 | AB27: 18.377717 | AC27: 0.035057947 | AD27: 0 | AE27: 0.013513219 | AF27: 0.39381894 | AG27: 0.03638533 | AH27: 35.793893 | AI27: 0.54168703 | AJ27: 1.4097436 | AK27: 0.42958808 | AL27: 127.61916 | AM27: 100.77419 | AN27: 169.73495 | AO27: 0.76114696 | AP27: 0.3123441 | AQ27: 537204.88 | AR27: 0.1429159 | AS27: 27.282788 | AT27: 0.38590076 | AU27: 15 | AV27: 0.029809582 | AW27: 0
B28: 238 | C28: 14 | D28: QUICHE | E28: 1409 | F28: San Pedro Jocopilas | G28: 10.225733 | H28: 0 | I28: 40.902932 | J28: 36 | K28: 18.190797 | L28: 25 | M28: 0.34911013 | N28: 295.003 | O28: 380.35533 | P28: 0.9086 | Q28: 0.29201817 | R28: 0.766803 | S28: 0.051903114 | T28: 0.050310607 | U28: 0.092155147 | V28: 0.95979878 | W28: 0.416 | X28: 84.821488 | Y28: 0.70563953 | Z28: 1062.3388 | AA28: 0.47475735 | AB28: 15.775 | AC28: 0.021937488 | AD28: 0 | AE28: 0.0095673605 | AF28: 0.4014067 | AG28: 0.027533739 | AH28: 37.557522 | AI28: 0.63198058 | AJ28: 2.1749175 | AK28: 0.25596181 | AL28: 140.60383 | AM28: 110.23684 | AN28: 147.57576 | AO28: 0.36239935 | AP28: 0.12878228 | AQ28: 211879.73 | AR28: 0.17410968 | AS28: 24.561948 | AT28: 0.24368735 | AU28: 15 | AV28: 0.023953541 | AW28: 0
B29: 206 | C29: 13 | D29: HUEHUETENANGO | E29: 1310 | F29: Santa Bárbara | G29: 0 | H29: 0 | I29: 52.330906 | J29: 48 | K29: 7.9274307 | L29: 100 | M29: 0.43473794 | N29: 376.6825 | O29: 489.93767 | P29: 0.7491 | Q29: 0.20152927 | R29: 0.49305816 | S29: 0.21212121 | T29: 0.046225633 | U29: 0.092155147 | V29: 0.95781452 | W29: 0.34596491 | X29: 117.12487 | Y29: 0.73052238 | Z29: 945.29817 | AA29: 0.54167295 | AB29: 23.413681 | AC29: 0.024295533 | AE29: 0.016353475 | AF29: 0.40840512 | AG29: 0.029980432 | AH29: 27.522244 | AI29: 0.53548577 | AJ29: 1.9738722 | AK29: 0.29258884 | AL29: 283.45907 | AM29: 74 | AN29: 136.65571 | AO29: 0.68103894 | AP29: 0.1594561 | AQ29: 802918.3 | AR29: 0.25303131 | AS29: 16.783914 | AT29: 0.33013563 | AU29: 15 | AV29: 0.024007248 | AW29: 0
B30: 336 | C30: 22 | D30: JUTIAPA | E30: 2213 | F30: Conguaco | G30: 46.233612 | H30: 3.3024008 | I30: 29.721608 | J30: 6 | K30: 30.059082 | L30: 100 | M30: 0.47943085 | N30: 313.7795 | O30: 276.48533 | P30: 0.718 | Q30: 0.46615453 | R30: 0.54912977 | S30: 0.2109375 | T30: 0.048314124 | U30: 0.1047337 | V30: 0.95022593 | W30: 0.32029412 | X30: 126.81095 | Y30: 0.59866831 | Z30: 1091.1287 | AA30: 0.59861279 | AB30: 15.308483 | AC30: 0.039806843 | AD30: 0.018779343 | AE30: 0.027804099 | AF30: 0.47408988 | AG30: 0.026512901 | AH30: 31.715302 | AI30: 0.50527368 | AJ30: 1.3210327 | AK30: 0.46538338 | AL30: 290.61127 | AM30: 42.355263 | AN30: 255.16085 | AO30: 0.92237292 | AP30: 0.3001595 | AQ30: 473616.26 | AR30: 0.40736711 | AS30: 328.25268 | AT30: 0.38108191 | AU30: 15 | AV30: 0.019287863 | AW30: 0
B31: 303 | C31: 19 | D31: ZACAPA | E31: 1909 | F31: La Unión | G31: 0 | H31: 46.196489 | I31: 0 | J31: 0 | K31: 31.273152 | L31: 100 | M31: 0.44316415 | N31: 276.0155 | O31: 209.05633 | P31: 0.7054 | Q31: 0.49740971 | R31: 0.54547711 | S31: 0.046692607 | T31: 0.071501899 | U31: 0.10188915 | V31: 0.94861475 | W31: 0.39906667 | X31: 194.48254 | Y31: 0.83100559 | Z31: 1250.3655 | AA31: 0.50986623 | AB31: 16.664251 | AC31: 0.0927778 | AD31: 0 | AE31: 0.10894072 | AF31: 0.4195141 | AG31: 0.047375168 | AH31: 60.470032 | AI31: 0.27677797 | AJ31: 1.2819367 | AK31: 0.55223913 | AL31: 292.57776 | AM31: 38.985507 | AN31: 275.08671 | AO31: 0.67440804 | AP31: 0.30490463 | AQ31: 425196.93 | AR31: 0.69444625 | AS31: 143.83431 | AT31: 0.27203513 | AU31: 15 | AV31: 0.027064886 | AW31: 0
B32: 205 | C32: 13 | D32: HUEHUETENANGO | E32: 1309 | F32: San Ildefonso Ixtahuacán | G32: 0 | H32: 0 | I32: 255.39456 | J32: 48 | K32: 16.577054 | L32: 100 | M32: 0.43473794 | N32: 405.67 | O32: 510.94467 | P32: 0.7244 | Q32: 0.40931864 | R32: 0.62165201 | S32: 0.21195652 | T32: 0.092150526 | U32: 0.092155147 | V32: 0.94536955 | W32: 0.28631579 | X32: 103.31053 | Y32: 0.6766833 | Z32: 1088.1304 | AA32: 0.51015914 | AB32: 18.268817 | AC32: 0.018264468 | AD32: 0.0074626866 | AE32: 0.014898677 | AF32: 0.366917 | AG32: 0.030321322 | AH32: 27.522244 | AI32: 0.53548577 | AJ32: 1.9738722 | AK32: 0.29258884 | AL32: 173.73779 | AM32: 74 | AN32: 136.65571 | AO32: 0.62045399 | AP32: 0.14527095 | AQ32: 793491.96 | AR32: 0.14129144 | AS32: 16.783914 | AT32: 0.3007669 | AU32: 15 | AV32: 0.02428022 | AW32: 0
B33: 265 | C33: 16 | D33: ALTA_VERAPAZ | E33: 1607 | F33: Panzós | G33: 14.366096 | H33: 2.3943493 | I33: 29.929367 | J33: 70 | K33: 32.703103 | L33: 100 | M33: 0.43726577 | N33: 283.837 | O33: 236.11933 | P33: 0.4115 | Q33: 0.4054416 | R33: 0.43925662 | S33: 0.066974596 | T33: 0.039722255 | U33: 0.1190014 | V33: 0.94189971 | W33: 0.39169231 | X33: 169.27224 | Y33: 0.47632108 | Z33: 996.45673 | AA33: 0.56716 | AB33: 22.054422 | AC33: 0.032101931 | AD33: 0.0053191489 | AE33: 0.0094660601 | AF33: 0.31740235 | AG33: 0.091971821 | AH33: 45.900196 | AI33: 0.41654229 | AJ33: 1.7416573 | AK33: 0.38475859 | AL33: 183.16772 | AM33: 99.83908 | AN33: 108.10042 | AO33: 0.27284094 | AP33: 0.10588688 | AQ33: 640169.5 | AR33: 0.14121008 | AS33: 41.455623 | AT33: 0.22990282 | AU33: 15 | AV33: 0.06038339 | AW33: 0
B34: 321 | C34: 21 | D34: JALAPA | E34: 2105 | F34: San Carlos Alzatate | G34: 22.457779 | H34: 13.474668 | I34: 112.2889 | J34: 9 | K34: 43.291887 | L34: 100 | M34: 0.50636672 | N34: 283.5855 | O34: 258.39267 | P34: 0.8547 | Q34: 0.51119821 | R34: 0.53423655 | S34: 0.049723757 | T34: 0.076985268 | U34: 0.1047337 | V34: 0.9417251 | W34: 0.32571429 | X34: 351.89939 | Y34: 0.7360393 | Z34: 1202.5782 | AA34: 0.65590027 | AB34: 13.577713 | AC34: 0.029445476 | AD34: 0.007518797 | AE34: 0.016854558 | AF34: 0.52553827 | AG34: 0.025268938 | AH34: 37.364198 | AI34: 0.50876481 | AJ34: 1.7737309 | AK34: 0.36014543 | AL34: 278.47646 | AM34: 52.897436 | AN34: 165.25012 | AO34: 0.79886459 | AP34: 0.23873597 | AQ34: 280681.88 | AR34: 0.23948336 | AS34: 88.821031 | AT34: 0.33434508 | AU34: 15 | AV34: 0.017500821 | AW34: 0
B35: 210 | C35: 13 | D35: HUEHUETENANGO | E35: 1314 | F35: San Rafael La Independencia | G35: 0 | H35: 0 | I35: 52.692591 | J35: 48 | K35: 26.855935 | L35: 100 | M35: 0.43473794 | N35: 356.514 | O35: 433.40367 | P35: 0.8838 | Q35: 0.67048897 | R35: 0.67386909 | S35: 0.28125 | T35: 0.054115291 | U35: 0.092155147 | V35: 0.93954793 | W35: 0.31614035 | X35: 180.67675 | Y35: 0.83608919 | Z35: 1034.161 | AA35: 0.44889096 | AB35: 20.097222 | AC35: 0.029218358 | AD35: 0 | AE35: 0.0079065366 | AF35: 0.53319046 | AG35: 0.038523539 | AH35: 27.522244 | AI35: 0.53548577 | AJ35: 1.9738722 | AK35: 0.29258884 | AL35: 548.00295 | AM35: 74 | AN35: 136.65571 | AO35: 0.32926698 | AP35: 0.077093431 | AQ35: 1417380.8 | AR35: 0.23650647 | AS35: 16.783914 | AT35: 0.15961313 | AU35: 15 | AV35: 0.030848259 | AW35: 0
B36: 254 | C36: 15 | D36: BAJA_VERAPAZ | E36: 1504 | F36: Cubulco | G36: 29.377683 | H36: 1.6320935 | I36: 19.585122 | J36: 32 | K36: 40.421856 | L36: 100 | M36: 0.37542968 | N36: 247.6885 | O36: 285.19933 | P36: 0.8355 | Q36: 0.49019687 | R36: 0.65243396 | S36: 0.078828829 | T36: 0.078095673 | U36: 0.1190014 | V36: 0.93844989 | W36: 0.31014706 | X36: 147.94587 | Y36: 0.57932459 | Z36: 1321.8468 | AA36: 0.54370878 | AB36: 14.413986 | AC36: 0.030546054 | AD36: 0.04950495 | AE36: 0.011149669 | AF36: 0.60696922 | AG36: 0.035367176 | AH36: 35.793893 | AI36: 0.54168703 | AJ36: 1.4097436 | AK36: 0.42958808 | AL36: 683.84717 | AM36: 100.77419 | AN36: 169.73495 | AO36: 0.62801739 | AP36: 0.25771308 | AQ36: 330657.14 | AR36: 0.63186877 | AS36: 27.282788 | AT36: 0.3184042 | AU36: 15 | AV36: 0.028975435 | AW36: 0
B37: 273 | C37: 16 | D37: ALTA_VERAPAZ | E37: 1615 | F37: Fray Bartolomé De Las Casas | G37: 11.042945 | H37: 6.1349693 | I37: 130.06135 | J37: 70 | K37: 39.695823 | L37: 100 | M37: 0.43726577 | N37: 276.068 | O37: 286.41233 | P37: 0.4999 | Q37: 0.23793213 | R37: 0.53246287 | S37: 0.046846847 | T37: 0.068920245 | U37: 0.1190014 | V37: 0.93765544 | W37: 0.31569231 | X37: 445.36634 | Y37: 0.40501006 | Z37: 1038.9609 | AA37: 0.5377513 | AB37: 17.920596 | AC37: 0.029604031 | AD37: 0.032085561 | AE37: 0.011648693 | AF37: 0.26904852 | AG37: 0.11097093 | AH37: 45.900196 | AI37: 0.41654229 | AJ37: 1.7416573 | AK37: 0.38475859 | AL37: 504.29448 | AM37: 99.83908 | AN37: 108.10042 | AO37: 0.33575113 | AP37: 0.13030171 | AQ37: 198000.86 | AR37: 0.47841953 | AS37: 41.455623 | AT37: 0.28291256 | AU37: 15 | AV37: 0.072857106 | AW37: 0
B38: 213 | C38: 13 | D38: HUEHUETENANGO | E38: 1317 | F38: Santa Eulalia | G38: 1.895519 | H38: 0 | I38: 204.71605 | J38: 48 | K38: 26.182062 | L38: 100 | M38: 0.43473794 | N38: 355.1135 | O38: 431.72267 | P38: 0.7315 | Q38: 0.3234487 | R38: 0.75832018 | S38: 0.10273973 | T38: 0.06490257 | U38: 0.092155147 | V38: 0.92946275 | W38: 0.35789474 | X38: 101.09639 | Y38: 0.78541712 | Z38: 885.13307 | AA38: 0.5071678 | AB38: 20.788462 | AC38: 0.022650025 | AD38: 0.032967033 | AE38: 0.018924526 | AF38: 0.40871022 | AG38: 0.027902449 | AH38: 27.522244 | AI38: 0.53548577 | AJ38: 1.9738722 | AK38: 0.29258884 | AL38: 540.22291 | AM38: 74 | AN38: 136.65571 | AO38: 0.7881101 | AP38: 0.18452537 | AQ38: 360799.86 | AR38: 0.55804837 | AS38: 16.783914 | AT38: 0.38203869 | AU38: 15 | AV38: 0.022343274 | AW38: 0
B39: 211 | C39: 13 | D39: HUEHUETENANGO | E39: 1315 | F39: Todos Santos Cuchumatán | G39: 0 | H39: 0 | I39: 86.872347 | J39: 48 | K39: 38.528306 | L39: 100 | M39: 0.43473794 | N39: 375.428 | O39: 486.07833 | P39: 0.9545 | Q39: 0.58460391 | R39: 0.75843063 | S39: 0.17333333 | T39: 0.1007471 | U39: 0.092155147 | V39: 0.92558121 | W39: 0.35789474 | X39: 102.64827 | Y39: 0.71152035 | Z39: 710.53519 | AA39: 0.39885409 | AB39: 18.448763 | AC39: 0.025844261 | AD39: 0 | AE39: 0.012482318 | AF39: 0.50358051 | AG39: 0.028654565 | AH39: 27.522244 | AI39: 0.53548577 | AJ39: 1.9738722 | AK39: 0.29258884 | AL39: 302.81218 | AM39: 74 | AN39: 136.65571 | AO39: 0.51982499 | AP39: 0.12171002 | AQ39: 406604.63 | AR39: 0.20632053 | AS39: 16.783914 | AT39: 0.25198669 | AU39: 15 | AV39: 0.022945541 | AW39: 0
B40: 245 | C40: 14 | D40: QUICHE | E40: 1416 | F40: Sacapulas | G40: 1.7712282 | H40: 5.3136845 | I40: 21.254738 | J40: 36 | K40: 18.713247 | L40: 100 | M40: 0.34911013 | N40: 295.071 | O40: 369.349 | P40: 0.8481 | Q40: 0.58030099 | R40: 0.62542183 | S40: 0.18309859 | T40: 0.069839527 | U40: 0.092155147 | V40: 0.92200785 | W40: 0.288 | X40: 301.8414 | Y40: 0.71784399 | Z40: 1340.8288 | AA40: 0.55504445 | AB40: 15.082865 | AC40: 0.016106827 | AD40: 0.01 | AE40: 0.010334142 | AF40: 0.35987401 | AG40: 0.029893643 | AH40: 37.557522 | AI40: 0.63198058 | AJ40: 2.1749175 | AK40: 0.25596181 | AL40: 345.38949 | AM40: 110.23684 | AN40: 147.57576 | AO40: 0.39144406 | AP40: 0.13910362 | AQ40: 768272.53 | AR40: 0.46197364 | AS40: 24.561948 | AT40: 0.26321781 | AU40: 15 | AV40: 0.026006588 | AW40: 0
B41: 217 | C41: 13 | D41: HUEHUETENANGO | E41: 1321 | F41: Tectitán | G41: 0 | H41: 0 | I41: 49.726504 | J41: 48 | K41: 17.863616 | L41: 75 | M41: 0.43473794 | N41: 444.7285 | O41: 533.26867 | P41: 0.8248 | Q41: 0.60115132 | R41: 0.60628132 | S41: 0.35294118 | T41: 0.11155312 | U41: 0.092155147 | V41: 0.92073989 | W41: 0.23859649 | X41: 417.58512 | Y41: 0.75796975 | Z41: 1243.3504 | AA41: 0.5543054 | AB41: 14.901235 | AC41: 0.034474836 | AD41: 0 | AE41: 0.0091013923 | AF41: 0.53331817 | AG41: 0.095003284 | AH41: 27.522244 | AI41: 0.53548577 | AJ41: 1.9738722 | AK41: 0.29258884 | AL41: 339.79778 | AM41: 74 | AN41: 136.65571 | AO41: 0.37902663 | AP41: 0.088743985 | AQ41: 736798.82 | AR41: 0.16881157 | AS41: 16.783914 | AT41: 0.18373427 | AU41: 15 | AV41: 0.076075201 | AW41: 0
... B58: 249 | C58: 14 | D58: QUICHE | E58: 1420 | F58: Playa Grande-Ixcán | G58: 24.655484 | H58: 4.4027649 | I58: 54.594285 | J58: 36 | K58: 20.850714 | L58: 100 | M58: 0.34911013 | N58: 332.2275 | O58: 388.55367 | P58: 0.843 | Q58: 0.0992172 | R58: 0.35838285 | S58: 0.10474308 | T58: 0.085510501 | U58: 0.092155147 | V58: 0.88268186 | W58: 0.1984 | X58: 597.44562 | Y58: 0.53477713 | Z58: 1467.8739 | AA58: 0.60659122 | AB58: 15.275353 | AC58: 0.018985162 | AD58: 0.025943396 | AE58: 0.013902788 | AF58: 0.29982328 | AG58: 0.058322922 | AH58: 37.557522 | AI58: 0.63198058 | AJ58: 2.1749175 | AK58: 0.25596181 | AL58: 567.95668 | AM58: 110.23684 | AN58: 147.57576 | AO58: 0.52661977 | AP58: 0.18713968 | AQ58: 241771.97 | AR58: 1.0219996 | AS58: 24.561948 | AT58: 0.3541137 | AU58: 15 | AV58: 0.050739223 | AW58: 0
B59: 237 | C59: 14 | D59: QUICHE | E59: 1408 | F59: San Antonio Ilotenango | G59: 3.0922416 | H59: 0 | I59: 68.029314 | J59: 36 | K59: 33.389587 | L59: 100 | M59: 0.34911013 | N59: 302.331 | O59: 384.85833 | P59: 0.9547 | Q59: 0.59515408 | R59: 0.63438649 | S59: 0.2875 | T59: 0.1169795 | U59: 0.092155147 | V59: 0.88240409 | W59: 0.3008 | X59: 253.48098 | Y59: 0.69898256 | Z59: 1040.7742 | AA59: 0.57929021 | AB59: 18.161972 | AC59: 0.017963266 | AE59: 0.0067621047 | AF59: 0.54174663 | AG59: 0.035462058 | AH59: 37.557522 | AI59: 0.63198058 | AJ59: 2.1749175 | AK59: 0.25596181 | AL59: 290.67071 | AM59: 110.23684 | AN59: 147.57576 | AO59: 0.25613985 | AP59: 0.091021896 | AQ59: 1790599.9 | AR59: 0.25439982 | AS59: 24.561948 | AT59: 0.17223552 | AU59: 15 | AV59: 0.030850945 | AW59: 0
B60: 239 | C60: 14 | D60: QUICHE | E60: 1410 | F60: Cunén | G60: 8.1554427 | H60: 2.0388607 | I60: 93.787591 | J60: 36 | K60: 20.061972 | L60: 25 | M60: 0.34911013 | N60: 295.274 | O60: 363.81633 | P60: 0.8861 | Q60: 0.47996112 | R60: 0.60595639 | S60: 0.21875 | T60: 0.086794299 | U60: 0.092155147 | V60: 0.88192065 | W60: 0.384 | X60: 223.7927 | Y60: 0.79994671 | Z60: 1559.2547 | AA60: 0.62402991 | AB60: 12.975265 | AC60: 0.023934175 | AD60: 0 | AE60: 0.011487373 | AF60: 0.34216348 | AG60: 0.05062495 | AH60: 37.557522 | AI60: 0.63198058 | AJ60: 2.1749175 | AK60: 0.25596181 | AL60: 267.09075 | AM60: 110.23684 | AN60: 147.57576 | AO60: 0.43512698 | AP60: 0.15462679 | AQ60: 799310.6 | AR60: 0.3971122 | AS60: 24.561948 | AT60: 0.29259142 | AU60: 15 | AV60: 0.044042214 | AW60: 0
B61: 235 | C61: 14 | D61: QUICHE | E61: 1406 | F61: Santo Tomás Chichicastenango | G61: 3.8755434 | H61: 0.6459239 | I61: 56.841303 | J61: 36 | K61: 26.343553 | L61: 25 | M61: 0.34911013 | N61: 379.284 | O61: 354.33133 | P61: 0.983 | Q61: 0.5838234 | R61: 0.62395493 | S61: 0.22 | T61: 0.061168993 | U61: 0.092155147 | V61: 0.88155889 | W61: 0.2688 | X61: 115.9016 | Y61: 0.80327519 | Z61: 1030.6591 | AA61: 0.53249601 | AB61: 17.143774 | AC61: 0.016061324 | AD61: 0.078767123 | AE61: 0.014576818 | AF61: 0.33094537 | AG61: 0.02958843 | AH61: 37.557522 | AI61: 0.63198058 | AJ61: 2.1749175 | AK61: 0.25596181 | AL61: 296.47907 | AM61: 110.23684 | AN61: 147.57576 | AO61: 0.55215119 | AP61: 0.19621253 | AQ61: 795316.08 | AR61: 0.55935874 | AS61: 24.561948 | AT61: 0.37128174 | AU61: 15 | AV61: 0.025741062 | AW61: 0
B62: 333 | C62: 22 | D62: JUTIAPA | E62: 2210 | F62: Zapotitlán | G62: 112.22295 | H62: 28.055737 | I62: 9.3519125 | J62: 6 | K62: 26.661425 | L62: 100 | M62: 0.47943085 | N62: 315.6435 | O62: 271.64967 | P62: 0.8876 | Q62: 0.55588092 | R62: 0.71686713 | S62: 0.071428571 | T62: 0.15440007 | U62: 0.1047337 | V62: 0.88006542 | W62: 0.27176471 | X62: 430.05485 | Y62: 0.3081381 | Z62: 1659.0976 | AA62: 0.56661367 | AB62: 10.73494 | AC62: 0.033925322 | AD62: 0.045454545 | AE62: 0.015350164 | AF62: 0.5667358 | AG62: 0.041913112 | AH62: 31.715302 | AI62: 0.50527368 | AJ62: 1.3210327 | AK62: 0.46538338 | AL62: 458.24371 | AM62: 42.355263 | AN62: 255.16085 | AO62: 0.50922618 | AP62: 0.16571288 | AQ62: 461617.71 | AR62: 0.35462895 | AS62: 328.25268 | AT62: 0.21038875 | AU62: 15 | AV62: 0.030491359 | AW62: 0
B63: 198 | C63: 13 | D63: HUEHUETENANGO | E63: 1302 | F63: Chiantla | G63: 2.1104393 | H63: 1.0552196 | I63: 86.528011 | J63: 48 | K63: 24.328518 | L63: 100 | M63: 0.43473794 | N63: 336.432 | O63: 447.08233 | P63: 0.8661 | Q63: 0.36182033 | R63: 0.55010654 | S63: 0.12778905 | T63: 0.11666508 | U63: 0.092155147 | V63: 0.87590246 | W63: 0.3877193 | X63: 147.6327 | Y63: 0.60067519 | Z63: 1251.0602 | AA63: 0.57077684 | AB63: 15.890877 | AC63: 0.019421112 | AD63: 0.033707865 | AE63: 0.012015916 | AF63: 0.2487059 | AG63: 0.052999555 | AH63: 27.522244 | AI63: 0.53548577 | AJ63: 1.9738722 | AK63: 0.29258884 | AL63: 269.08101 | AM63: 74 | AN63: 136.65571 | AO63: 0.50040172 | AP63: 0.11716233 | AQ63: 604582.63 | AR63: 0.17648743 | AS63: 16.783914 | AT63: 0.2425712 | AU63: 15 | AV63: 0.042440131 | AW63: 0
B64: 223 | C64: 13 | D64: HUEHUETENANGO | E64: 1327 | F64: Aguacatán | G64: 1.6546703 | H64: 0 | I64: 120.79093 | J64: 48 | K64: 25.197874 | L64: 100 | M64: 0.43473794 | N64: 319.7435 | O64: 397.50267 | P64: 0.8676 | Q64: 0.47248768 | R64: 0.6828781 | S64: 0.13 | T64: 0.10833126 | U64: 0.092155147 | V64: 0.87522813 | W64: 0.31614035 | X64: 157.06794 | Y64: 0.67246063 | Z64: 1073.9379 | AA64: 0.50007877 | AB64: 14.833333 | AC64: 0.018368025 | AD64: 0.091666667 | AE64: 0.013561366 | AF64: 0.34196246 | AG64: 0.045221213 | AH64: 27.522244 | AI64: 0.53548577 | AJ64: 1.9738722 | AK64: 0.29258884 | AL64: 388.84752 | AM64: 74 | AN64: 136.65571 | AO64: 0.56476181 | AP64: 0.13223138 | AQ64: 561391.96 | AR64: 0.28784362 | AS64: 16.783914 | AT64: 0.27376995 | AU64: 15 | AV64: 0.036211516 | AW64: 0
B65: 200 | C65: 13 | D65: HUEHUETENANGO | E65: 1304 | F65: Cuilco | G65: 0 | H65: 0 | I65: 136.11416 | J65: 48 | K65: 27.187762 | L65: 100 | M65: 0.43473794 | N65: 431.555 | O65: 536.82967 | P65: 0.8294 | Q65: 0.49265417 | R65: 0.66447322 | S65: 0.079391892 | T65: 0.11676546 | U65: 0.092155147 | V65: 0.87380882 | W65: 0.34596491 | X65: 207.66306 | Y65: 0.55317012 | Z65: 903.43848 | AA65: 0.50755497 | AB65: 18.89141 | AC65: 0.025024803 | AD65: 0.15584416 | AE65: 0.016370329 | AF65: 0.33533318 | AG65: 0.033275366 | AH65: 27.522244 | AI65: 0.53548577 | AJ65: 1.9738722 | AK65: 0.29258884 | AL65: 420.05123 | AM65: 74 | AN65: 136.65571 | AO65: 0.68174081 | AP65: 0.15962043 | AQ65: 266442.12 | AR65: 0.37534747 | AS65: 16.783914 | AT65: 0.33047586 | AU65: 15 | AV65: 0.026645712 | AW65: 0
B66: 242 | C66: 14 | D66: QUICHE | E66: 1413 | F66: Santa María Nebaj | G66: 4.9898955 | H66: 2.4949477 | I66: 79.838327 | J66: 36 | K66: 18.698889 | L66: 75 | M66: 0.34911013 | N66: 315.316 | O66: 385.59767 | P66: 0.7993 | Q66: 0.6646043 | R66: 0.70229242 | S66: 0.10166667 | T66: 0.098999526 | U66: 0.092155147 | V66: 0.86757856 | W66: 0.3968 | X66: 765.08158 | Y66: 0.86873547 | Z66: 1492.8199 | AA66: 0.64267342 | AB66: 13.440098 | AC66: 0.018770549 | AD66: 0.018595041 | AE66: 0.012686621 | AF66: 0.48339585 | AG66: 0.068692518 | AH66: 37.557522 | AI66: 0.63198058 | AJ66: 2.1749175 | AK66: 0.25596181 | AL66: 552.63092 | AM66: 110.23684 | AN66: 147.57576 | AO66: 0.48055294 | AP66: 0.17076936 | AQ66: 315438.85 | AR66: 0.90743347 | AS66: 24.561948 | AT66: 0.32313709 | AU66: 15 | AV66: 0.059760466 | AW66: 0
B67: 310 | C67: 20 | D67: CHIQUIMULA | E67: 2005 | F67: Camotán | G67: 9.5957011 | H67: 20.790686 | I67: 17.592119 | J67: 5 | K67: 43.827183 | L67: 100 | M67: 0.39358975 | N67: 306.7675 | O67: 246.88867 | P67: 0.6446 | Q67: 0.41224566 | R67: 0.50295966 | S67: 0.15086207 | T67: 0.086505246 | U67: 0.10188915 | V67: 0.86659648 | W67: 0.41333333 | X67: 201.68777 | Y67: 0.8123792 | Z67: 1455.1101 | AA67: 0.54136286 | AB67: 20.080134 | AC67: 0.094495316 | AD67: 0.090909091 | AE67: 0.052661608 | AF67: 0.41697216 | AG67: 0.067664411 | AH67: 25.322196 | AI67: 0.44190206 | AJ67: 1.5146039 | AK67: 0.42232287 | AL67: 382.22876 | AM67: 34.941176 | AN67: 191.16296 | AO67: 1.0675267 | AP67: 0.33319466 | AQ67: 508264.2 | AR67: 0.76818017 | AS67: 606.24802 | AT67: 0.40455887 | AU67: 15 | AV67: 0.049878968 | AW67: 0
B68: 75 | C68: 6 | D68: SANTA_ROSA | E68: 604 | F68: Casillas | G68: 71.771239 | H68: 26.442035 | I68: 37.774336 | J68: 2 | K68: 40.694596 | L68: 100 | M68: 0.47100536 | N68: 294.381 | O68: 284.03 | P68: 0.9335 | Q68: 0.59781537 | R68: 0.41169246 | S68: 0.16756757 | T68: 0.2321233 | U68: 0.1047337 | V68: 0.86575168 | W68: 0.32410256 | X68: 520.98093 | Y68: 0.26050999 | Z68: 1159.0018 | AA68: 0.65703774 | AB68: 15.211356 | AC68: 0.039899571 | AD68: 0.0089285714 | AE68: 0.0085127412 | AF68: 0.42381447 | AG68: 0.04541065 | AH68: 36.09571 | AI68: 0.40277399 | AJ68: 1.6325573 | AK68: 0.41024827 | AL68: 498.62124 | AM68: 45.461538 | AN68: 226.51271 | AO68: 0.25183566 | AP68: 0.1207774 | AQ68: 753956.23 | AR68: 0.23345512 | AS68: 143.94115 | AT68: 0.14480048 | AU68: 15 | AV68: 0.027093145 | AW68: 0
B69: 268 | C69: 16 | D69: ALTA_VERAPAZ | E69: 1610 | F69: San Juan Chamelco | G69: 82.62659 | H69: 1.5589923 | I69: 23.384884 | J69: 70 | K69: 51.260911 | L69: 100 | M69: 0.43726577 | N69: 254.7815 | O69: 341.007 | P69: 0.549 | Q69: 0.42873283 | R69: 0.67441796 | S69: 0.2875 | T69: 0.12782178 | U69: 0.1190014 | V69: 0.86499758 | W69: 0.35076923 | X69: 109.4136 | Y69: 0.53483269 | Z69: 1296.83 | AA69: 0.65797946 | AB69: 16.423469 | AC69: 0.023467879 | AD69: 0.02173913 | AE69: 0.0070419174 | AF69: 0.49654028 | AG69: 0.042838177 | AH69: 45.900196 | AI69: 0.41654229 | AJ69: 1.7416573 | AK69: 0.38475859 | AL69: 115.36543 | AM69: 99.83908 | AN69: 108.10042 | AO69: 0.2029697 | AP69: 0.078770543 | AQ69: 3576718.7 | AR69: 0.066162834 | AS69: 41.455623 | AT69: 0.17102751 | AU69: 15 | AV69: 0.028125075 | AW69: 0
B70: 332 | C70: 22 | D70: JUTIAPA | E70: 2209 | F70: El Adelanto | G70: 70.947144 | H70: 0 | I70: 47.298096 | J70: 6 | K70: 25.087958 | L70: 100 | M70: 0.47943085 | N70: 313.1915 | O70: 269.19467 | P70: 0.8901 | Q70: 0.53833107 | R70: 0.5810836 | S70: 0.29032258 | T70: 0.17050964 | U70: 0.1047337 | V70: 0.8630698 | W70: 0.29117647 | X70: 902.50657 | Y70: 0.34188656 | Z70: 1270.1881 | AA70: 0.69607429 | AB70: 13.741667 | AC70: 0.037539227 | AD70: 0.0087719298 | AE70: 0.015311892 | AF70: 0.62209872 | AG70: 0.048475793 | AH70: 31.715302 | AI70: 0.50527368 | AJ70: 1.3210327 | AK70: 0.46538338 | AL70: 437.50739 | AM70: 42.355263 | AN70: 255.16085 | AO70: 0.50795655 | AP70: 0.16529972 | AQ70: 991747.18 | AR70: 0.33773721 | AS70: 328.25268 | AT70: 0.2098642 | AU70: 15 | AV70: 0.035265642 | AW70: 0
B71: 337 | C71: 22 | D71: JUTIAPA | E71: 2214 | F71: Moyuta | G71: 107.95533 | H71: 11.776945 | I71: 72.624492 | J71: 6 | K71: 49.56413 | L71: 100 | M71: 0.47943085 | N71: 316.3605 | O71: 276.01533 | P71: 0.8771 | Q71: 0.58504536 | R71: 0.5697786 | S71: 0.21842105 | T71: 0.13735843 | U71: 0.1047337 | V71: 0.86286433 | W71: 0.32029412 | X71: 212.89974 | Y71: 0.38884094 | Z71: 1217.0939 | AA71: 0.64698562 | AB71: 13.330484 | AC71: 0.034829638 | AD71: 0.0081967213 | AE71: 0.013994016 | AF71: 0.60596275 | AG71: 0.050937187 | AH71: 31.715302 | AI71: 0.50527368 | AJ71: 1.3210327 | AK71: 0.46538338 | AL71: 365.08528 | AM71: 42.355263 | AN71: 255.16085 | AO71: 0.46423736 | AP71: 0.15107258 | AQ71: 533295.4 | AR71: 0.25757361 | AS71: 328.25268 | AT71: 0.19180144 | AU71: 15 | AV71: 0.03705628 | AW71: 0
... B79: 274 | C79: 16 | D79: ALTA_VERAPAZ | E79: 1616 | F79: Santa Catalina La Tinta | G79: 44.177045 | H79: 2.1036688 | I79: 494.36217 | J79: 70 | K79: 36.517345 | L79: 100 | M79: 0.43726577 | N79: 284.001 | O79: 246.523 | P79: 0.6107 | Q79: 0.51005188 | R79: 0.51372341 | S79: 0.073333333 | T79: 0.11071609 | U79: 0.1190014 | V79: 0.84011656 | W79: 0.304 | X79: 434.14448 | Y79: 0.48820625 | Z79: 1150.6649 | AA79: 0.67126261 | AB79: 16.329193 | AC79: 0.03440787 | AD79: 0 | AE79: 0.015607636 | AF79: 0.349052 | AG79: 0.053740849 | AH79: 45.900196 | AI79: 0.41654229 | AJ79: 1.7416573 | AK79: 0.38475859 | AL79: 84.146752 | AM79: 99.83908 | AN79: 108.10042 | AO79: 0.44986003 | AP79: 0.17458625 | AQ79: 318914.24 | AR79: 0.10696014 | AS79: 41.455623 | AT79: 0.37906367 | AU79: 15 | AV79: 0.03528314 | AW79: 0
B80: 226 | C80: 13 | D80: HUEHUETENANGO | E80: 1330 | F80: Santiago Chimaltenango | G80: 0 | H80: 0 | I80: 20.056157 | J80: 48 | K80: 23.536878 | L80: 50 | M80: 0.43473794 | N80: 402.2955 | O80: 513.46933 | P80: 0.8911 | Q80: 0.65065243 | R80: 0.40883375 | S80: 0.47058824 | T80: 0.030084236 | U80: 0.092155147 | V80: 0.83511955 | W80: 0.22666667 | X80: 79.532087 | Y80: 0.86670357 | Z80: 1013.4963 | AA80: 0.53034521 | AB80: 18.676471 | AC80: 0.019643777 | AE80: 0.014413475 | AF80: 0.61318 | AG80: 0.022715549 | AH80: 27.522244 | AI80: 0.53548577 | AJ80: 1.9738722 | AK80: 0.29258884 | AL80: 213.93234 | AM80: 74 | AN80: 136.65571 | AO80: 0.60024783 | AP80: 0.14053995 | AQ80: 2307056.6 | AR80: 0.16831352 | AS80: 16.783914 | AT80: 0.2909719 | AU80: 15 | AV80: 0.018189792 | AW80: 0
B81: 309 | C81: 20 | D81: CHIQUIMULA | E81: 2004 | F81: Jocotán | G81: 1.3010161 | H81: 31.224386 | I81: 53.34166 | J81: 5 | K81: 35.80569 | L81: 100 | M81: 0.39358975 | N81: 305.9055 | O81: 246.02667 | P81: 0.563 | Q81: 0.34180543 | R81: 0.42543732 | S81: 0.21621622 | T81: 0.064153104 | U81: 0.10188915 | V81: 0.82981212 | W81: 0.31333333 | X81: 110.86047 | Y81: 0.93135757 | Z81: 1221.308 | AA81: 0.53602105 | AB81: 18.262765 | AC81: 0.080239193 | AD81: 0.0027247956 | AE81: 0.053796449 | AF81: 0.31363419 | AG81: 0.073693604 | AH81: 25.322196 | AI81: 0.44190206 | AJ81: 1.5146039 | AK81: 0.42232287 | AL81: 297.93269 | AM81: 34.941176 | AN81: 191.16296 | AO81: 1.0905316 | AP81: 0.3403749 | AQ81: 958736.12 | AR81: 0.61167027 | AS81: 606.24802 | AT81: 0.41327698 | AU81: 15 | AV81: 0.0543234 | AW81: 0
B82: 241 | C82: 14 | D82: QUICHE | E82: 1412 | F82: Joyabaj | G82: 1.7665192 | H82: 1.7665192 | I82: 71.544026 | J82: 36 | K82: 32.353232 | L82: 100 | M82: 0.34911013 | N82: 259.761 | O82: 289.83233 | P82: 0.8596 | Q82: 0.46321296 | R82: 0.56010335 | S82: 0.30263158 | T82: 0.072312462 | U82: 0.092155147 | V82: 0.8281408 | W82: 0.3264 | X82: 394.43112 | Y82: 0.61798934 | Z82: 779.68599 | AA82: 0.42450725 | AB82: 20.673997 | AC82: 0.027952216 | AD82: 0 | AE82: 0.0089419015 | AF82: 0.45337791 | AG82: 0.042531555 | AH82: 37.557522 | AI82: 0.63198058 | AJ82: 2.1749175 | AK82: 0.25596181 | AL82: 705.72441 | AM82: 110.23684 | AN82: 147.57576 | AO82: 0.33870776 | AP82: 0.12036324 | AQ82: 1247533 | AR82: 0.8167679 | AS82: 24.561948 | AT82: 0.22775647 | AU82: 15 | AV82: 0.037001199 | AW82: 0
B83: 111 | C83: 8 | D83: TOTONICAPAN | E83: 807 | F83: Santa Lucía La Reforma | G83: 7.6751861 | H83: 3.8375931 | I83: 3.8375931 | J83: 7 | K83: 38.162924 | L83: 100 | M83: 0.74679342 | N83: 298.7255 | O83: 392.55133 | P83: 0.9082 | Q83: 0.32500785 | R83: 0.7075283 | S83: 0.036764706 | T83: 0.060058331 | U83: 0.090740344 | V83: 0.82598628 | W83: 0.43487179 | X83: 190.26545 | Y83: 0.69345412 | Z83: 841.00698 | AA83: 0.54205965 | AB83: 15.353791 | AC83: 0.035154711 | AE83: 0.017369108 | AF83: 0.5775834 | AG83: 0.030319084 | AH83: 29.603175 | AI83: 0.61125586 | AJ83: 2.1645085 | AK83: 0.25384661 | AL83: 80.589454 | AM83: 34.225806 | AN83: 153.57203 | AO83: 0.332208 | AP83: 0.1186732 | AQ83: 518132.03 | AR83: 0.0908816 | AS83: 8.9557651 | AT83: 0.28212815 | AU83: 15 | AV83: 0.027611064 | AW83: 0
B84: 259 | C84: 16 | D84: ALTA_VERAPAZ | E84: 1601 | F84: Cobán | G84: 87.552405 | H84: 4.6301753 | I84: 134.69601 | J84: 70 | K84: 58.786189 | L84: 75 | M84: 0.43726577 | N84: 247.053 | O84: 334.317 | P84: 0.6046 | Q84: 0.39099965 | R84: 0.49851169 | S84: 0.090525328 | T84: 0.1969424 | U84: 0.1190014 | V84: 0.81808698 | W84: 0.40923077 | X84: 697.76826 | Y84: 0.39495337 | Z84: 1852.6149 | AA84: 0.6476911 | AB84: 14.484129 | AC84: 0.02475642 | AD84: 0.1039644 | AE84: 0.0051564408 | AF84: 0.15779166 | AG84: 0.18194886 | AH84: 45.900196 | AI84: 0.41654229 | AJ84: 1.7416573 | AK84: 0.38475859 | AL84: 298.01492 | AM84: 99.83908 | AN84: 108.10042 | AO84: 0.14862447 | AP84: 0.057679694 | AQ84: 678840.38 | AR84: 0.12515135 | AS84: 41.455623 | AT84: 0.12523481 | AU84: 15 | AV84: 0.11945712 | AW84: 0
B85: 323 | C85: 21 | D85: JALAPA | E85: 2107 | F85: Mataquescuintla | G85: 56.095737 | H85: 27.009058 | I85: 39.474778 | J85: 9 | K85: 35.353458 | L85: 100 | M85: 0.50636672 | N85: 294.686 | O85: 276.48167 | P85: 0.8991 | Q85: 0.53081974 | R85: 0.52665547 | S85: 0.1533101 | T85: 0.14200532 | U85: 0.1047337 | V85: 0.81583387 | W85: 0.40714286 | X85: 148.12718 | Y85: 0.47713782 | Z85: 1093.0655 | AA85: 0.62114442 | AB85: 11.790698 | AC85: 0.025733155 | AD85: 0.024193548 | AE85: 0.0074944208 | AF85: 0.43061968 | AG85: 0.051294963 | AH85: 37.364198 | AI85: 0.50876481 | AJ85: 1.7737309 | AK85: 0.36014543 | AL85: 452.92113 | AM85: 52.897436 | AN85: 165.25012 | AO85: 0.35521712 | AP85: 0.10615454 | AQ85: 860639.05 | AR85: 0.17319293 | AS85: 88.821031 | AT85: 0.14866737 | AU85: 15 | AV85: 0.035525987 | AW85: 0
B86: 311 | C86: 20 | D86: CHIQUIMULA | E86: 2006 | F86: Olopa | G86: 0 | H86: 9.7062249 | I86: 16.177042 | J86: 5 | K86: 25.751808 | L86: 100 | M86: 0.39358975 | N86: 325.0925 | O86: 265.21367 | P86: 0.8136 | Q86: 0.39954217 | R86: 0.54452046 | S86: 0.08974359 | T86: 0.069852465 | U86: 0.10188915 | V86: 0.80640819 | W86: 0.40666667 | X86: 247.37113 | Y86: 0.92496088 | Z86: 1247.3085 | AA86: 0.54129558 | AB86: 19.572881 | AC86: 0.060534071 | AD86: 0 | AE86: 0.051521518 | AF86: 0.44544659 | AG86: 0.056733787 | AH86: 25.322196 | AI86: 0.44190206 | AJ86: 1.5146039 | AK86: 0.42232287 | AL86: 449.72175 | AM86: 34.941176 | AN86: 191.16296 | AO86: 1.0444155 | AP86: 0.32598121 | AQ86: 381904.47 | AR86: 0.88425629 | AS86: 606.24802 | AT86: 0.39580043 | AU86: 15 | AV86: 0.041821434 | AW86: 0
B87: 76 | C87: 6 | D87: SANTA_ROSA | E87: 605 | F87: San Rafael Las Flores | G87: 41.943376 | H87: 27.962251 | I87: 139.81125 | J87: 2 | K87: 50.250399 | L87: 100 | M87: 0.47100536 | N87: 294.8255 | O87: 278.727 | P87: 0.8775 | Q87: 0.65461266 | R87: 0.40723186 | S87: 0.25 | T87: 0.17154841 | U87: 0.1047337 | V87: 0.80558928 | W87: 0.28307692 | X87: 459.33559 | Y87: 0.34271537 | Z87: 1403.055 | AA87: 0.64616534 | AB87: 10.679012 | AC87: 0.041813326 | AD87: 0 | AE87: 0.0048035906 | AF87: 0.56163629 | AG87: 0.11091723 | AH87: 36.09571 | AI87: 0.40277399 | AJ87: 1.6325573 | AK87: 0.41024827 | AL87: 300.5942 | AM87: 45.461538 | AN87: 226.51271 | AO87: 0.14210645 | AP87: 0.068152571 | AQ87: 1590108.3 | AR87: 0.079416325 | AS87: 143.94115 | AT87: 0.081708371 | AU87: 15 | AV87: 0.066176029 | AW87: 0
B88: 218 | C88: 13 | D88: HUEHUETENANGO | E88: 1322 | F88: Concepción Huista | G88: 0 | H88: 0 | I88: 425.65004 | J88: 48 | K88: 17.158218 | L88: 100 | M88: 0.43473794 | N88: 381.1165 | O88: 473.57167 | P88: 0.9289 | Q88: 0.65232722 | R88: 0.41789255 | S88: 0.21008403 | T88: 0.092578884 | U88: 0.092155147 | V88: 0.79543878 | W88: 0.26245614 | X88: 204.90244 | Y88: 0.74319039 | Z88: 1186.9172 | AA88: 0.57751397 | AB88: 19.597156 | AC88: 0.021469467 | AD88: 0 | AE88: 0.01347831 | AF88: 0.43515371 | AG88: 0.039700651 | AH88: 27.522244 | AI88: 0.53548577 | AJ88: 1.9738722 | AK88: 0.29258884 | AL88: 768.02073 | AM88: 74 | AN88: 136.65571 | AO88: 0.56130295 | AP88: 0.13142153 | AQ88: 509278.22 | AR88: 0.56504393 | AS88: 16.783914 | AT88: 0.27209325 | AU88: 15 | AV88: 0.031790848 | AW88: 0
B89: 229 | C89: 13 | D89: HUEHUETENANGO | E89: 1333 | F89: Petatán | G89: 0 | H89: 0 | I89: 206.18557 | J89: 48 | K89: 28.669284 | L89: 100 | M89: 0.43473794 | N89: 464.425 | O89: 515.56333 | P89: 0.9994 | Q89: 0.82986627 | R89: 0.80758201 | S89: 0.23529412 | T89: 0.23010309 | U89: 0.092155147 | V89: 0.79543878 | W89: 0.26245614 | X89: 71.788859 | Y89: 0.74319039 | Z89: 1092.6595 | AA89: 0.59322034 | AB89: 20.073529 | AC89: 0.01862185 | AD89: 0 | AE89: 0.020742202 | AF89: 0.64846962 | AG89: 0.037827448 | AH89: 27.522244 | AI89: 0.53548577 | AJ89: 1.9738722 | AK89: 0.29258884 | AL89: 178.69416 | AM89: 74 | AN89: 136.65571 | AO89: 0.86380705 | AP89: 0.2022488 | AQ89: 779707.25 | AR89: 0.20232011 | AS89: 16.783914 | AT89: 0.41873301 | AU89: 15 | AV89: 0.030290855 | AW89: 0
B90: 338 | C90: 22 | D90: JUTIAPA | E90: 2215 | F90: Pasaco | G90: 132.53225 | H90: 26.50645 | I90: 44.177417 | J90: 6 | K90: 27.963344 | L90: 100 | M90: 0.47943085 | N90: 346.3595 | O90: 292.37567 | P90: 0.9998 | Q90: 0.72071862 | R90: 0.52600951 | S90: 0.097402597 | T90: 0.10364022 | U90: 0.1047337 | V90: 0.7942793 | W90: 0.35426471 | X90: 173.17555 | Y90: 0.22743527 | Z90: 1683.7624 | AA90: 0.68201754 | AB90: 10.317536 | AC90: 0.034738615 | AD90: 0 | AE90: 0.012379989 | AF90: 0.46972653 | AG90: 0.10893868 | AH90: 31.715302 | AI90: 0.50527368 | AJ90: 1.3210327 | AK90: 0.46538338 | AL90: 485.95158 | AM90: 42.355263 | AN90: 255.16085 | AO90: 0.41069363 | AP90: 0.13364832 | AQ90: 165224.3 | AR90: 0.30330385 | AS90: 328.25268 | AT90: 0.16967965 | AU90: 15 | AV90: 0.079251771 | AW90: 0
B91: 260 | C91: 16 | D91: ALTA_VERAPAZ | E91: 1602 | F91: Santa Cruz Verapaz | G91: 114.16131 | H91: 0 | I91: 156.63994 | J91: 70 | K91: 43.610445 | L91: 100 | M91: 0.43726577 | N91: 246.3565 | O91: 318.098 | P91: 0.8456 | Q91: 0.65059347 | R91: 0.48185977 | S91: 0.60416667 | T91: 0.15820634 | U91: 0.1190014 | V91: 0.78527422 | W91: 0.52030769 | X91: 126.98196 | Y91: 0.5266045 | Z91: 1078.1878 | AA91: 0.56791355 | AB91: 17.653747 | AC91: 0.026466446 | AD91: 0.11764706 | AE91: 0.0099435072 | AF91: 0.34485955 | AG91: 0.090394075 | AH91: 45.900196 | AI91: 0.41654229 | AJ91: 1.7416573 | AK91: 0.38475859 | AL91: 161.94977 | AM91: 99.83908 | AN91: 108.10042 | AO91: 0.28660244 | AP91: 0.11122758 | AQ91: 2479010.3 | AR91: 0.13114973 | AS91: 41.455623 | AT91: 0.24149861 | AU91: 15 | AV91: 0.059347533 | AW91: 0
B92: 228 | C92: 13 | D92: HUEHUETENANGO | E92: 1332 | F92: Unión Cantinil | G92: 0 | H92: 0 | I92: 15.908368 | J92: 48 | K92: 26.70673 | L92: 100 | M92: 0.43473794 | N92: 401 | O92: 485.33333 | P92: 0.9532 | Q92: 0.48362573 | R92: 0.54183509 | S92: 0.44186047 | T92: 0.21773253 | U92: 0.092155147 | V92: 0.78338013 | W92: 0.36385965 | X92: 264.1116 | Y92: 0.5373351 | Z92: 1087.4424 | AA92: 0.53102126 | AB92: 13.85 | AC92: 0.021952089 | AD92: 0 | AE92: 0.016197124 | AF92: 0.66602468 | AG92: 0.043593288 | AH92: 27.522244 | AI92: 0.53548577 | AJ92: 1.9738722 | AK92: 0.29258884 | AL92: 238.62552 | AM92: 74 | AN92: 136.65571 | AO92: 0.67452772 | AP92: 0.15793159 | AQ92: 1023273.2 | AR92: 0.21097385 | AS92: 16.783914 | AT92: 0.3269793 | AU92: 15 | AV92: 0.034907931 | AW92: 0
B93: 232 | C93: 14 | D93: QUICHE | E93: 1403 | F93: Chinique | G93: 28.465699 | H93: 0 | I93: 135.21207 | J93: 36 | K93: 20.331129 | L93: 100 | M93: 0.34911013 | N93: 294.218 | O93: 329.90333 | P93: 0.8698 | Q93: 0.60018257 | R93: 0.57923954 | S93: 0.265625 | T93: 0.10646171 | U93: 0.092155147 | V93: 0.77633867 | W93: 0.3072 | X93: 259.8435 | Y93: 0.6301938 | Z93: 1484.6318 | AA93: 0.62075174 | AB93: 11.165992 | AC93: 0.018855861 | AD93: 0.0625 | AE93: 0.0099016205 | AF93: 0.49448103 | AG93: 0.043299071 | AH93: 37.557522 | AI93: 0.63198058 | AJ93: 2.1749175 | AK93: 0.25596181 | AL93: 284.65699 | AM93: 110.23684 | AN93: 147.57576 | AO93: 0.37506069 | AP93: 0.13328162 | AQ93: 664195.21 | AR93: 0.36480583 | AS93: 24.561948 | AT93: 0.25220118 | AU93: 15 | AV93: 0.037668915 | AW93: 0
B94: 324 | C94: 22 | D94: JUTIAPA | E94: 2201 | F94: Jutiapa | G94: 106.64328 | H94: 23.106045 | I94: 53.321642 | J94: 6 | K94: 26.571756 | L94: 100 | M94: 0.47943085 | N94: 295.268 | O94: 254.33433 | P94: 0.9407 | Q94: 0.51944197 | R94: 0.47554619 | S94: 0.2483871 | T94: 0.19393674 | U94: 0.1047337 | V94: 0.77621482 | W94: 0.33485294 | X94: 1185.9882 | Y94: 0.49448829 | Z94: 1747.216 | AA94: 0.69840816 | AB94: 13.660272 | AC94: 0.034245179 | AD94: 0.031330252 | AE94: 0.015780957 | AF94: 0.1232284 | AG94: 0.15177734 | AH94: 31.715302 | AI94: 0.50527368 | AJ94: 1.3210327 | AK94: 0.46538338 | AL94: 505.96314 | AM94: 42.355263 | AN94: 255.16085 | AO94: 0.52351731 | AP94: 0.17036352 | AQ94: 960260.71 | AR94: 0.40254726 | AS94: 328.25268 | AT94: 0.21629319 | AU94: 15 | AV94: 0.11041646 | AW94: 0
B95: 110 | C95: 8 | D95: TOTONICAPAN | E95: 806 | F95: Santa María Chiquimula | G95: 5.0306028 | H95: 0 | I95: 15.091809 | J95: 7 | K95: 29.490478 | L95: 100 | M95: 0.74679342 | N95: 326.9085 | O95: 425.17167 | P95: 0.8803 | Q95: 0.4650442 | R95: 0.63858848 | S95: 0.475 | T95: 0.063570051 | U95: 0.090740344 | V95: 0.77375768 | W95: 0.22974359 | X95: 131.56243 | Y95: 0.77220923 | Z95: 1138.6732 | AA95: 0.53474625 | AB95: 17.013761 | AC95: 0.026624708 | AD95: 0.032258065 | AE95: 0.016253278 | AF95: 0.34634118 | AG95: 0.023929926 | AH95: 29.603175 | AI95: 0.61125586 | AJ95: 2.1645085 | AK95: 0.25384661 | AL95: 263.26821 | AM95: 34.225806 | AN95: 153.57203 | AO95: 0.31086623 | AP95: 0.11104938 | AQ95: 2154200.1 | AR95: 0.27781752 | AS95: 8.9557651 | AT95: 0.26400362 | AU95: 15 | AV95: 0.021792568 | AW95: 0
... B106: 149 | C106: 10 | D106: SUCHITEPEQUEZ | E106: 1013 | F106: Chicacao | G106: 62.356797 | H106: 2.9003161 | I106: 327.73572 | J106: 5 | K106: 33.350346 | L106: 100 | M106: 0.6198794 | N106: 410.71 | O106: 365.174 | P106: 0.8983 | Q106: 0.73950279 | R106: 0.60109199 | S106: 0.18518519 | T106: 0.10525247 | U106: 0.090740344 | V106: 0.73431813 | W106: 0.3286747 | X106: 59.322649 | Y106: 0.44689655 | Z106: 1124.3861 | AA106: 0.58640876 | AB106: 17.045623 | AC106: 0.048041842 | AD106: 0.021164021 | AE106: 0.02152686 | AF106: 0.36069557 | AG106: 0.082245373 | AH106: 47.938462 | AI106: 0.29744659 | AJ106: 1.4619585 | AK106: 0.51202056 | AL106: 384.29189 | AM106: 34.383562 | AN106: 203.85716 | AO106: 0.37237329 | AP106: 0.20257736 | AQ106: 888334.65 | AR106: 0.38251879 | AS106: 21.363477 | AT106: 0.27418203 | AU106: 15 | AV106: 0.040487569 | AW106: 0
B107: 99 | C107: 7 | D107: SOLOLA | E107: 714 | F107: Santa Cruz La Laguna | G107: 0 | H107: 0 | I107: 49.701789 | J107: 11 | K107: 31.957587 | L107: 100 | M107: 0.89624241 | N107: 386.375 | O107: 361.42267 | P107: 0.9567 | Q107: 0.72098022 | R107: 0.6351688 | S107: 0.91666667 | T107: 0.14102883 | U107: 0.090740344 | V107: 0.73406592 | W107: 0.20777778 | X107: 368.89841 | Y107: 0.81532885 | Z107: 1152.6814 | AA107: 0.6118898 | AB107: 13.326316 | AC107: 0.032323195 | AE107: 0.017441673 | AF107: 0.6631775 | AG107: 0.075583853 | AH107: 26.542222 | AI107: 0.56986459 | AJ107: 1.9765149 | AK107: 0.29559004 | AL107: 211.2326 | AM107: 25.878049 | AN107: 190.81544 | AO107: 0.46585845 | AP107: 0.2050432 | AQ107: 1539678.3 | AR107: 0.51457206 | AS107: 460.00321 | AT107: 0.33232379 | AU107: 15 | AV107: 0.067657456 | AW107: 0
B108: 77 | C108: 6 | D108: SANTA_ROSA | E108: 606 | F108: Oratorio | G108: 125.1833 | H108: 14.306663 | I108: 10.729997 | J108: 2 | K108: 29.600482 | L108: 50 | M108: 0.47100536 | N108: 297.7485 | O108: 271.181 | P108: 0.8733 | Q108: 0.76328425 | R108: 0.4647432 | S108: 0.17757009 | T108: 0.21299045 | U108: 0.1047337 | V108: 0.73337109 | W108: 0.34051282 | X108: 228.52492 | Y108: 0.29177119 | Z108: 1128.8311 | AA108: 0.69608494 | AB108: 16.919355 | AC108: 0.038359981 | AD108: 0 | AE108: 0.011546085 | AF108: 0.45990546 | AG108: 0.034673934 | AH108: 36.09571 | AI108: 0.40277399 | AJ108: 1.6325573 | AK108: 0.41024827 | AL108: 429.1999 | AM108: 45.461538 | AN108: 226.51271 | AO108: 0.34157223 | AP108: 0.163814 | AQ108: 507524.76 | AR108: 0.27255715 | AS108: 143.94115 | AT108: 0.19639721 | AU108: 15 | AV108: 0.020687348 | AW108: 0
B109: 340 | C109: 22 | D109: JUTIAPA | E109: 2217 | F109: Quesada | G109: 108.24313 | H109: 12.489592 | I109: 66.611157 | J109: 6 | K109: 45.79535 | L109: 100 | M109: 0.47943085 | N109: 295.4065 | O109: 259.409 | P109: 0.9623 | Q109: 0.78086972 | R109: 0.42972637 | S109: 0.4047619 | T109: 0.30499584 | U109: 0.1047337 | V109: 0.73322492 | W109: 0.29602941 | X109: 148.4772 | Y109: 0.22450062 | Z109: 1309.6851 | AA109: 0.74853431 | AB109: 9.8416667 | AC109: 0.032220855 | AD109: 0.0059171598 | AE109: 0.017265011 | AF109: 0.54050736 | AG109: 0.036150951 | AH109: 31.715302 | AI109: 0.50527368 | AJ109: 1.3210327 | AK109: 0.46538338 | AL109: 370.52456 | AM109: 42.355263 | AN109: 255.16085 | AO109: 0.5727493 | AP109: 0.18638464 | AQ109: 921938.72 | AR109: 0.32251397 | AS109: 328.25268 | AT109: 0.23663357 | AU109: 15 | AV109: 0.026299445 | AW109: 0
B110: 165 | C110: 11 | D110: RETALHULEU | E110: 1108 | F110: Nuevo San Carlos | G110: 86.46678 | H110: 2.33694 | I110: 88.80372 | J110: 8 | K110: 48.74668 | L110: 100 | M110: 0.35460801 | N110: 449.406 | O110: 403.87 | P110: 0.8987 | Q110: 0.46378518 | R110: 0.55826584 | S110: 0.65625 | T110: 0.18450141 | U110: 0.090740344 | V110: 0.732791 | W110: 0.31034483 | X110: 154.6743 | Y110: 0.37278742 | Z110: 1521.3648 | AA110: 0.68587919 | AB110: 11.9326 | AC110: 0.08168979 | AD110: 0 | AE110: 0.027918588 | AF110: 0.42845492 | AG110: 0.063456502 | AH110: 56.02459 | AI110: 0.3536643 | AJ110: 1.5788522 | AK110: 0.48746361 | AL110: 415.97532 | AM110: 37.12 | AN110: 233.2057 | AO110: 0.43664344 | AP110: 0.20071245 | AQ110: 2086196.5 | AR110: 0.41516476 | AS110: 82.777106 | AT110: 0.24451299 | AU110: 15 | AV110: 0.032749355 | AW110: 0
B111: 97 | C111: 7 | D111: SOLOLA | E111: 712 | F111: San Antonio Palopó | G111: 0 | H111: 0 | I111: 31.289111 | J111: 11 | K111: 30.43683 | L111: 100 | M111: 0.89624241 | N111: 337.596 | O111: 318.717 | P111: 0.9701 | Q111: 0.66080171 | R111: 0.43153724 | S111: 0.61764706 | T111: 0.1252816 | U111: 0.090740344 | V111: 0.72973266 | W111: 0.33611111 | X111: 113.77534 | Y111: 0.6749111 | Z111: 1283.814 | AA111: 0.53525027 | AB111: 13.657609 | AC111: 0.033771339 | AD111: 0 | AE111: 0.011800922 | AF111: 0.5768827 | AG111: 0.05367042 | AH111: 26.542222 | AI111: 0.56986459 | AJ111: 1.9765149 | AK111: 0.29559004 | AL111: 244.05507 | AM111: 25.878049 | AN111: 190.81544 | AO111: 0.31519677 | AP111: 0.13873089 | AQ111: 1594752.7 | AR111: 0.40225446 | AS111: 460.00321 | AT111: 0.22484809 | AU111: 15 | AV111: 0.048042061 | AW111: 0
B112: 79 | C112: 6 | D112: SANTA_ROSA | E112: 608 | F112: Chiquimulilla | G112: 157.23035 | H112: 26.953774 | I112: 86.85105 | J112: 2 | K112: 41.460317 | L112: 100 | M112: 0.47100536 | N112: 328.7965 | O112: 281.40367 | P112: 0.9083 | Q112: 0.57633367 | R112: 0.47911131 | S112: 0.23246493 | T112: 0.17524446 | U112: 0.1047337 | V112: 0.72676568 | W112: 0.35282051 | X112: 212.38168 | Y112: 0.2558787 | Z112: 1147.3004 | AA112: 0.74466828 | AB112: 11.585478 | AC112: 0.037729396 | AD112: 0.019950125 | AE112: 0.012071423 | AF112: 0.41161314 | AG112: 0.12936131 | AH112: 36.09571 | AI112: 0.40277399 | AJ112: 1.6325573 | AK112: 0.41024827 | AL112: 372.86054 | AM112: 45.461538 | AN112: 226.51271 | AO112: 0.35711349 | AP112: 0.1712674 | AQ112: 497253.73 | AR112: 0.24755294 | AS112: 143.94115 | AT112: 0.20533313 | AU112: 15 | AV112: 0.077180234 | AW112: 0
B113: 119 | C113: 9 | D113: QUETZALTENANGO | E113: 907 | F113: Cajolá | G113: 20.463498 | H113: 0 | I113: 71.622244 | J113: 15 | K113: 13.247542 | L113: 100 | M113: 0.65257159 | N113: 450.842 | O113: 425.88967 | P113: 0.9699 | Q113: 0.65500686 | R113: 0.55205927 | S113: 0.25 | T113: 0.091881107 | U113: 0.090740344 | V113: 0.72472236 | W113: 0.14882353 | X113: 113.66378 | Y113: 0.66067093 | Z113: 1098.8164 | AA113: 0.46634615 | AB113: 18.120879 | AC113: 0.10316167 | AE113: 0.03911123 | AF113: 0.54512292 | AG113: 0.051594135 | AH113: 30.21707 | AI113: 0.29344564 | AJ113: 1.7256073 | AK113: 0.39770323 | AL113: 506.47158 | AM113: 12.04321 | AN113: 203.22837 | AO113: 0.41960715 | AP113: 0.16378782 | AQ113: 2201494.5 | AR113: 0.46998983 | AS113: 58.126973 | AT113: 0.18816754 | AU113: 15 | AV113: 0.032808898 | AW113: 0
B114: 74 | C114: 6 | D114: SANTA_ROSA | E114: 603 | F114: Santa Rosa De Lima | G114: 95.350527 | H114: 22.702506 | I114: 208.86306 | J114: 2 | K114: 43.399224 | L114: 100 | M114: 0.47100536 | N114: 286.313 | O114: 275.962 | P114: 0.9626 | Q114: 0.65204737 | R114: 0.39415549 | S114: 0.44776119 | T114: 0.28178351 | U114: 0.1047337 | V114: 0.72388634 | W114: 0.31589744 | X114: 321.18821 | Y114: 0.29524466 | Z114: 1152.9185 | AA114: 0.61691375 | AB114: 15.451477 | AC114: 0.037675795 | AD114: 0.047058824 | AE114: 0.0084497206 | AF114: 0.46368412 | AG114: 0.042323928 | AH114: 36.09571 | AI114: 0.40277399 | AJ114: 1.6325573 | AK114: 0.41024827 | AL114: 472.21213 | AM114: 45.461538 | AN114: 226.51271 | AO114: 0.2499713 | AP114: 0.11988328 | AQ114: 1744870.4 | AR114: 0.21945359 | AS114: 143.94115 | AT114: 0.14372851 | AU114: 15 | AV114: 0.025251529 | AW114: 0
B115: 118 | C115: 9 | D115: QUETZALTENANGO | E115: 906 | F115: Cabricán | G115: 24.542458 | H115: 0 | I115: 14.024262 | J115: 15 | K115: 17.458307 | L115: 50 | M115: 0.65257159 | N115: 359.5205 | O115: 438.64167 | P115: 0.934 | Q115: 0.57525656 | R115: 0.620782 | S115: 0.33333333 | T115: 0.092805554 | U115: 0.090740344 | V115: 0.72293983 | W115: 0.33 | X115: 140.44137 | Y115: 0.68015974 | Z115: 1364.0225 | AA115: 0.53750383 | AB115: 12.392941 | AC115: 0.14854915 | AD115: 0.042105263 | AE115: 0.047047506 | AF115: 0.46547241 | AG115: 0.10515769 | AH115: 30.21707 | AI115: 0.29344564 | AJ115: 1.7256073 | AK115: 0.39770323 | AL115: 368.13688 | AM115: 12.04321 | AN115: 203.22837 | AO115: 0.50475195 | AP115: 0.19702291 | AQ115: 1602262.2 | AR115: 0.41093945 | AS115: 58.126973 | AT115: 0.22634966 | AU115: 15 | AV115: 0.066870158 | AW115: 0
B116: 100 | C116: 7 | D116: SOLOLA | E116: 715 | F116: San Pablo La Laguna | G116: 0 | H116: 0 | I116: 160.01969 | J116: 11 | K116: 22.122191 | L116: 100 | M116: 0.89624241 | N116: 404.241 | O116: 379.28867 | P116: 0.9636 | Q116: 0.60144509 | R116: 0.42941973 | S116: 0.58333333 | T116: 0.095519449 | U116: 0.090740344 | V116: 0.72166899 | W116: 0.22 | X116: 358.67815 | Y116: 0.767768 | Z116: 2044.857 | AA116: 0.7028436 | AB116: 12.567797 | AC116: 0.02615176 | AD116: 0 | AE116: 0.03313531 | AF116: 0.6166847 | AG116: 0.034524439 | AH116: 26.542222 | AI116: 0.56986459 | AJ116: 1.9765149 | AK116: 0.29559004 | AL116: 233.87494 | AM116: 25.878049 | AN116: 190.81544 | AO116: 0.8850277 | AP116: 0.3895366 | AQ116: 818105 | AR116: 1.0823602 | AS116: 460.00321 | AT116: 0.63134147 | AU116: 15 | AV116: 0.030903899 | AW116: 0
B117: 256 | C117: 15 | D117: BAJA_VERAPAZ | E117: 1506 | F117: Santa Cruz El Chol | G117: 36.784992 | H117: 0 | I117: 36.784992 | J117: 32 | K117: 37.870016 | L117: 100 | M117: 0.37542968 | N117: 231.5045 | O117: 275.796 | P117: 0.9159 | Q117: 0.77639625 | R117: 0.57226092 | S117: 0.14285714 | T117: 0.093341916 | U117: 0.1190014 | V117: 0.71936061 | W117: 0.35367647 | X117: 191.31499 | Y117: 0.32076288 | Z117: 1992.6899 | AA117: 0.58274824 | AB117: 12.45 | AC117: 0.029211785 | AD117: 0 | AE117: 0.0082416308 | AF117: 0.65455489 | AG117: 0.034454482 | AH117: 35.793893 | AI117: 0.54168703 | AJ117: 1.4097436 | AK117: 0.42958808 | AL117: 404.63491 | AM117: 100.77419 | AN117: 169.73495 | AO117: 0.46421894 | AP117: 0.19049678 | AQ117: 251776.98 | AR117: 0.27636457 | AS117: 27.282788 | AT117: 0.23535855 | AU117: 15 | AV117: 0.028227687 | AW117: 0
B118: 136 | C118: 9 | D118: QUETZALTENANGO | E118: 924 | F118: Palestina De Los Altos | G118: 9.5501862 | H118: 0 | I118: 482.2844 | J118: 15 | K118: 21.721592 | L118: 100 | M118: 0.65257159 | N118: 466.246 | O118: 441.29367 | P118: 0.965 | Q118: 0.50268176 | R118: 0.52836531 | S118: 0.375 | T118: 0.10032471 | U118: 0.090740344 | V118: 0.71713638 | W118: 0.25235294 | X118: 99.451017 | Y118: 0.59928115 | Z118: 1121.3505 | AA118: 0.57901444 | AB118: 17.549356 | AC118: 0.092560215 | AD118: 0.06122449 | AE118: 0.027419981 | AF118: 0.57845029 | AG118: 0.14677832 | AH118: 30.21707 | AI118: 0.29344564 | AJ118: 1.7256073 | AK118: 0.39770323 | AL118: 496.60968 | AM118: 12.04321 | AN118: 203.22837 | AO118: 0.29417689 | AP118: 0.11482786 | AQ118: 2523197.4 | AR118: 0.3230831 | AS118: 58.126973 | AT118: 0.13191992 | AU118: 15 | AV118: 0.093336867 | AW118: 0
B119: 230 | C119: 14 | D119: QUICHE | E119: 1401 | F119: Santa Cruz Del Quiché | G119: 28.30732 | H119: 5.8566869 | I119: 63.447441 | J119: 36 | K119: 34.745502 | L119: 100 | M119: 0.34911013 | N119: 295.3 | O119: 372.48633 | P119: 0.9369 | Q119: 0.44720822 | R119: 0.58847012 | S119: 0.5703125 | T119: 0.18058118 | U119: 0.092155147 | V119: 0.70976486 | W119: 0.2816 | X119: 1493.4369 | Y119: 0.66458818 | Z119: 3056.4568 | AA119: 0.68640499 | AB119: 11.941834 | AC119: 0.017423546 | AD119: 0.028017241 | AE119: 0.0076388833 | AF119: 0.11573993 | AG119: 0.23040406 | AH119: 37.557522 | AI119: 0.63198058 | AJ119: 2.1749175 | AK119: 0.25596181 | AL119: 319.18943 | AM119: 110.23684 | AN119: 147.57576 | AO119: 0.2893511 | AP119: 0.10282385 | AQ119: 3138363.6 | AR119: 0.31558186 | AS119: 24.561948 | AT119: 0.19456769 | AU119: 15 | AV119: 0.20044474 | AW119: 0
B120: 335 | C120: 22 | D120: JUTIAPA | E120: 2212 | F120: Jalpatagua | G120: 160.08538 | H120: 31.38929 | I120: 87.890012 | J120: 6 | K120: 17.148114 | L120: 100 | M120: 0.47943085 | N120: 304.5895 | O120: 272.221 | P120: 0.9314 | Q120: 0.72317022 | R120: 0.43690955 | S120: 0.26960784 | T120: 0.22951849 | U120: 0.1047337 | V120: 0.70770751 | W120: 0.38338235 | X120: 140.00622 | Y120: 0.39471023 | Z120: 1290.5264 | AA120: 0.78449883 | AB120: 12.17179 | AC120: 0.034368313 | AD120: 0.0094562648 | AE120: 0.011748821 | AF120: 0.46440069 | AG120: 0.049595749 | AH120: 31.715302 | AI120: 0.50527368 | AJ120: 1.3210327 | AK120: 0.46538338 | AL120: 442.58899 | AM120: 42.355263 | AN120: 255.16085 | AO120: 0.38975527 | AP120: 0.12683454 | AQ120: 739893.56 | AR120: 0.26215585 | AS120: 328.25268 | AT120: 0.16102888 | AU120: 15 | AV120: 0.036080398 | AW120: 0
B121: 124 | C121: 9 | D121: QUETZALTENANGO | E121: 912 | F121: San Martín Sacatepéquez | G121: 32.031682 | H121: 0 | I121: 49.503509 | J121: 15 | K121: 32.014387 | L121: 75 | M121: 0.65257159 | N121: 454.169 | O121: 429.21667 | P121: 0.9607 | Q121: 0.83638522 | R121: 0.64595925 | S121: 0.32 | T121: 0.093212195 | U121: 0.090740344 | V121: 0.70762436 | W121: 0.52411765 | X121: 82.137866 | Y121: 0.62948882 | Z121: 1331.4333 | AA121: 0.61075112 | AB121: 11.498282 | AC121: 0.059231357 | AD121: 0 | AE121: 0.03896147 | AF121: 0.44711709 | AG121: 0.043891207 | AH121: 30.21707 | AI121: 0.29344564 | AJ121: 1.7256073 | AK121: 0.39770323 | AL121: 230.04572 | AM121: 12.04321 | AN121: 203.22837 | AO121: 0.41800044 | AP121: 0.16316066 | AQ121: 1397716.4 | AR121: 0.21265784 | AS121: 58.126973 | AT121: 0.18744703 | AU121: 15 | AV121: 0.027910578 | AW121: 0
B122: 327 | C122: 22 | D122: JUTIAPA | E122: 2204 | F122: Agua Blanca | G122: 77.808036 | H122: 22.230868 | I122: 22.230868 | J122: 6 | K122: 47.925346 | L122: 100 | M122: 0.47943085 | N122: 293.658 | O122: 238.418 | P122: 0.992 | Q122: 0.76740179 | R122: 0.39975375 | S122: 0.11764706 | T122: 0.29583727 | U122: 0.1047337 | V122: 0.70462412 | W122: 0.33970588 | X122: 230.49947 | Y122: 0.27438964 | Z122: 1268.0848 | AA122: 0.67047308 | AB122: 10.897727 | AC122: 0.033762663 | AD122: 0.024590164 | AE122: 0.012786908 | AF122: 0.58064756 | AG122: 0.071061736 | AH122: 31.715302 | AI122: 0.50527368 | AJ122: 1.3210327 | AK122: 0.46538338 | AL122: 327.9053 | AM122: 42.355263 | AN122: 255.16085 | AO122: 0.42419277 | AP122: 0.13804123 | AQ122: 230374.45 | AR122: 0.21138718 | AS122: 328.25268 | AT122: 0.17525687 | AU122: 15 | AV122: 0.051696683 | AW122: 0
B123: 204 | C123: 13 | D123: HUEHUETENANGO | E123: 1308 | F123: San Pedro Soloma | G123: 0 | H123: 3.0137275 | I123: 122.05596 | J123: 48 | K123: 11.681621 | L123: 100 | M123: 0.43473794 | N123: 354.3215 | O123: 434.49367 | P123: 0.8898 | Q123: 0.60574442 | R123: 0.57040699 | S123: 0.28571429 | T123: 0.11226135 | U123: 0.092155147 | V123: 0.70293245 | W123: 0.30421053 | X123: 142.39064 | Y123: 0.63551224 | Z123: 802.92753 | AA123: 0.53247724 | AB123: 18.485496 | AC123: 0.029104484 | AD123: 0.054187192 | AE123: 0.0099758191 | AF123: 0.46532374 | AG123: 0.05729913 | AH123: 27.522244 | AI123: 0.53548577 | AJ123: 1.9738722 | AK123: 0.29258884 | AL123: 593.70432 | AM123: 74 | AN123: 136.65571 | AO123: 0.41544205 | AP123: 0.097270166 | AQ123: 1795774.3 | AR123: 0.32329026 | AS123: 16.783914 | AT123: 0.20138676 | AU123: 15 | AV123: 0.045883076 | AW123: 0
B124: 262 | C124: 16 | D124: ALTA_VERAPAZ | E124: 1604 | F124: Tactic | G124: 64.677077 | H124: 4.6197912 | I124: 219.44008 | J124: 70 | K124: 40.394805 | L124: 100 | M124: 0.43726577 | N124: 246.116 | O124: 304.663 | P124: 0.8535 | Q124: 0.77467316 | R124: 0.46711463 | S124: 0.42352941 | T124: 0.22445255 | U124: 0.1190014 | V124: 0.70192049 | W124: 0.48523077 | X124: 128.78815 | Y124: 0.56591699 | Z124: 981.89803 | AA124: 0.69504876 | AB124: 14.613565 | AC124: 0.022091051 | AD124: 0.053533191 | AE124: 0.0094342186 | AF124: 0.42495979 | AG124: 0.068921438 | AH124: 45.900196 | AI124: 0.41654229 | AJ124: 1.7416573 | AK124: 0.38475859 | AL124: 173.24217 | AM124: 99.83908 | AN124: 108.10042 | AO124: 0.27192318 | AP124: 0.10553071 | AQ124: 1695869.5 | AR124: 0.13310888 | AS124: 41.455623 | AT124: 0.22912948 | AU124: 15 | AV124: 0.045249839 | AW124: 0
B125: 319 | C125: 21 | D125: JALAPA | E125: 2103 | F125: San Luis Jilotepeque | G125: 58.593035 | H125: 25.634453 | I125: 36.620647 | J125: 9 | K125: 30.609997 | L125: 100 | M125: 0.50636672 | N125: 285.131 | O125: 245.528 | P125: 0.9333 | Q125: 0.7599476 | R125: 0.51922167 | S125: 0.12837838 | T125: 0.23213828 | U125: 0.1047337 | V125: 0.70179765 | W125: 0.40714286 | X125: 194.97198 | Y125: 0.45409423 | Z125: 1336.4649 | AA125: 0.66422704 | AB125: 9.3818565 | AC125: 0.023925381 | AD125: 0 | AE125: 0.011695953 | AF125: 0.60222981 | AG125: 0.033570565 | AH125: 37.364198 | AI125: 0.50876481 | AJ125: 1.7737309 | AK125: 0.36014543 | AL125: 428.46157 | AM125: 52.897436 | AN125: 165.25012 | AO125: 0.55435942 | AP125: 0.16566704 | AQ125: 303356.83 | AR125: 0.25569191 | AS125: 88.821031 | AT125: 0.23201347 | AU125: 15 | AV125: 0.023250382 | AW125: 0
B126: 91 | C126: 7 | D126: SOLOLA | E126: 706 | F126: Santa Catarina Ixtahuacán | G126: 3.1544746 | H126: 25.235797 | I126: 53.626069 | J126: 11 | K126: 26.279811 | L126: 50 | M126: 0.89624241 | N126: 404.989 | O126: 380.03667 | P126: 0.9134 | Q126: 0.68389956 | R126: 0.60772205 | S126: 0.19774011 | T126: 0.083798618 | U126: 0.090740344 | V126: 0.69692801 | W126: 0.25666667 | X126: 159.38268 | Y126: 0.85496289 | Z126: 1453.2381 | AA126: 0.54453608 | AB126: 12.100802 | AC126: 0.042943607 | AD126: 0 | AE126: 0.010823305 | AF126: 0.38603537 | AG126: 0.054687519 | AH126: 26.542222 | AI126: 0.56986459 | AJ126: 1.9765149 | AK126: 0.29559004 | AL126: 206.61809 | AM126: 25.878049 | AN126: 190.81544 | AO126: 0.28908512 | AP126: 0.12723809 | AQ126: 1325199.3 | AR126: 0.31233838 | AS126: 460.00321 | AT126: 0.20622114 | AU126: 15 | AV126: 0.048952498 | AW126: 0
B127: 93 | C127: 7 | D127: SOLOLA | E127: 708 | F127: Concepción | G127: 0 | H127: 0 | I127: 26.867276 | J127: 11 | K127: 45.139134 | L127: 100 | M127: 0.89624241 | N127: 380.012 | O127: 355.05967 | P127: 0.9868 | Q127: 0.68321014 | R127: 0.53137895 | S127: 0.1 | T127: 0.053062869 | U127: 0.090740344 | V127: 0.6935941 | W127: 0.14666667 | X127: 470.70258 | Y127: 0.82665286 | Z127: 1061.6751 | AA127: 0.66746526 | AB127: 17.858974 | AC127: 0.02876817 | AE127: 0.0086310933 | AF127: 0.7222614 | AG127: 0.066472889 | AH127: 26.542222 | AI127: 0.56986459 | AJ127: 1.9765149 | AK127: 0.29559004 | AL127: 362.70822 | AM127: 25.878049 | AN127: 190.81544 | AO127: 0.23053223 | AP127: 0.10146658 | AQ127: 863360.1 | AR127: 0.43724043 | AS127: 460.00321 | AT127: 0.16445197 | AU127: 15 | AV127: 0.05950195 | AW127: 0
B128: 112 | C128: 8 | D128: TOTONICAPAN | E128: 808 | F128: San Bartolo Aguas Calientes | G128: 7.9088896 | H128: 0 | I128: 94.906675 | J128: 7 | K128: 28.363304 | L128: 100 | M128: 0.74679342 | N128: 337.0875 | O128: 428.92667 | P128: 0.9314 | Q128: 0.52300613 | R128: 0.68953951 | S128: 0.48148148 | T128: 0.097832964 | U128: 0.090740344 | V128: 0.6922587 | W128: 0.50051282 | X128: 321.00827 | Y128: 0.6811806 | Z128: 1779.3747 | AA128: 0.60996134 | AB128: 14.041885 | AC128: 0.033103486 | AE128: 0.013896771 | AF128: 0.59669331 | AG128: 0.06187729 | AH128: 29.603175 | AI128: 0.61125586 | AJ128: 2.1645085 | AK128: 0.25384661 | AL128: 688.07339 | AM128: 34.225806 | AN128: 153.57203 | AO128: 0.26579479 | AP128: 0.094948704 | AQ128: 1582787.5 | AR128: 0.62082456 | AS128: 8.9557651 | AT128: 0.22572663 | AU128: 15 | AV128: 0.056350574 | AW128: 0
B129: 292 | C129: 18 | D129: IZABAL | E129: 1803 | F129: El Estor | G129: 32.927618 | H129: 12.93585 | I129: 42.335509 | J129: 53 | K129: 49.935608 | L129: 100 | M129: 0.39811044 | N129: 289.5965 | O129: 226.57667 | P129: 0.5032 | Q129: 0.45579632 | R129: 0.40103497 | S129: 0.016229282 | T129: 0.083177515 | U129: 0.10188915 | V129: 0.69063765 | W129: 0.39924051 | X129: 110.503 | Y129: 0.33745541 | Z129: 1504.3988 | AA129: 0.68201762 | AB129: 19.449261 | AC129: 0.087203046 | AD129: 0.016778523 | AE129: 0.034717862 | AF129: 0.34753388 | AG129: 0.15306527 | AH129: 51.41868 | AI129: 0.25109647 | AJ129: 1.2975811 | AK129: 0.53598674 | AL129: 225.78938 | AM129: 115.87179 | AN129: 237.4991 | AO129: 0.51300236 | AP129: 0.23241896 | AQ129: 88691.615 | AR129: 0.18766272 | AS129: 137.55428 | AT129: 0.25258135 | AU129: 15 | AV129: 0.074725091 | AW129: 0
B130: 170 | C130: 12 | D130: SAN_MARCOS | E130: 1204 | F130: Comitancillo | G130: 21.910338 | H130: 0 | I130: 36.51723 | J130: 22 | K130: 37.348448 | L130: 100 | M130: 0.92341807 | N130: 389.83 | O130: 462.208 | P130: 0.7754 | Q130: 0.41371834 | R130: 0.7216601 | S130: 0.32743363 | T130: 0.073460494 | U130: 0.090740344 | V130: 0.68847219 | W130: 0.17 | X130: 129.70817 | Y130: 0.82057429 | Z130: 1356.4218 | AA130: 0.55922343 | AB130: 13.472441 | AC130: 0.043671158 | AD130: 0.013029316 | AE130: 0.0111351 | AF130: 0.33078613 | AG130: 0.043595239 | AH130: 48.827423 | AI130: 0.46898059 | AJ130: 1.6723867 | AK130: 0.40442537 | AL130: 452.81365 | AM130: 42.122222 | AN130: 145.30427 | AO130: 0.37258077 | AP130: 0.11304963 | AQ130: 2090285.4 | AR130: 0.31436403 | AS130: 11.669067 | AT130: 0.26535306 | AU130: 15 | AV130: 0.02651133 | AW130: 0
B131: 131 | C131: 9 | D131: QUETZALTENANGO | E131: 919 | F131: El Palmar | G131: 53.017309 | H131: 0 | I131: 218.30656 | J131: 15 | K131: 9.9511977 | L131: 75 | M131: 0.65257159 | N131: 444.283 | O131: 398.747 | P131: 0.9576 | Q131: 0.83606423 | R131: 0.63206298 | S131: 0.10738255 | T131: 0.21646655 | U131: 0.090740344 | V131: 0.68844274 | W131: 0.60176471 | X131: 131.4037 | Y131: 0.41511182 | Z131: 1331.4545 | AA131: 0.66788574 | AB131: 14.047817 | AC131: 0.065156284 | AD131: 0.014925373 | AE131: 0.039130602 | AF131: 0.40493391 | AG131: 0.12897234 | AH131: 30.21707 | AI131: 0.29344564 | AJ131: 1.7256073 | AK131: 0.39770323 | AL131: 458.44379 | AM131: 12.04321 | AN131: 203.22837 | AO131: 0.41981498 | AP131: 0.16386894 | AQ131: 872107.26 | AR131: 0.42563226 | AS131: 58.126973 | AT131: 0.18826074 | AU131: 15 | AV131: 0.082013983 | AW131: 0
B132: 174 | C132: 12 | D132: SAN_MARCOS | E132: 1208 | F132: Sibinal | G132: 11.474469 | H132: 0 | I132: 22.948939 | J132: 22 | K132: 43.168064 | L132: 100 | M132: 0.92341807 | N132: 429.9125 | O132: 516.69567 | P132: 0.7859 | Q132: 0.55580357 | R132: 0.8161616 | S132: 0.051136364 | T132: 0.11365462 | U132: 0.090740344 | V132: 0.68648838 | W132: 0.245 | X132: 388.8085 | Y132: 0.73080748 | Z132: 1503.0052 | AA132: 0.60399937 | AB132: 13.7 | AC132: 0.03934724 | AD132: 0 | AE132: 0.0088194393 | AF132: 0.48272795 | AG132: 0.063976464 | AH132: 48.827423 | AI132: 0.46898059 | AJ132: 1.6723867 | AK132: 0.40442537 | AL132: 332.75961 | AM132: 42.122222 | AN132: 145.30427 | AO132: 0.2950987 | AP132: 0.089539774 | AQ132: 359499.63 | AR132: 0.1829746 | AS132: 11.669067 | AT132: 0.21017011 | AU132: 15 | AV132: 0.038905651 | AW132: 0
B133: 203 | C133: 13 | D133: HUEHUETENANGO | E133: 1307 | F133: Jacaltenango | G133: 0 | H133: 2.1879923 | I133: 87.519692 | J133: 48 | K133: 10.70685 | L133: 100 | M133: 0.43473794 | N133: 381.0315 | O133: 470.13167 | P133: 0.9378 | Q133: 0.87821612 | R133: 0.52778497 | S133: 0.070754717 | T133: 0.23098635 | U133: 0.092155147 | V133: 0.68616357 | W133: 0.31017544 | X133: 139.09779 | Y133: 0.56583814 | Z133: 1891.0309 | AA133: 0.71920422 | AB133: 14.885714 | AC133: 0.017617607 | AD133: 0.029268293 | AE133: 0.023858757 | AF133: 0.40827205 | AG133: 0.043435996 | AH133: 27.522244 | AI133: 0.53548577 | AJ133: 1.9738722 | AK133: 0.29258884 | AL133: 503.23823 | AM133: 74 | AN133: 136.65571 | AO133: 0.99359571 | AP133: 0.23263706 | AQ133: 341485.99 | AR133: 0.65538316 | AS133: 16.783914 | AT133: 0.48164844 | AU133: 15 | AV133: 0.034781978 | AW133: 0
B134: 308 | C134: 20 | D134: CHIQUIMULA | E134: 2003 | F134: San Juan Ermita | G134: 5.2377959 | H134: 5.2377959 | I134: 62.853551 | J134: 5 | K134: 56.452446 | L134: 100 | M134: 0.39358975 | N134: 297.9595 | O134: 238.08067 | P134: 0.7957 | Q134: 0.49129725 | R134: 0.50725223 | S134: 0.17391304 | T134: 0.15262937 | U134: 0.10188915 | V134: 0.68580163 | W134: 0.27333333 | X134: 229.44684 | Y134: 0.76504372 | Z134: 1483.9602 | AA134: 0.59716138 | AB134: 14.502128 | AC134: 0.057721473 | AD134: 0 | AE134: 0.046999616 | AF134: 0.39256087 | AG134: 0.046835595 | AH134: 25.322196 | AI134: 0.44190206 | AJ134: 1.5146039 | AK134: 0.42232287 | AL134: 460.92604 | AM134: 34.941176 | AN134: 191.16296 | AO134: 0.95274999 | AP134: 0.29737074 | AQ134: 438496.74 | AR134: 0.82674422 | AS134: 606.24802 | AT134: 0.36106211 | AU134: 15 | AV134: 0.034524961 | AW134: 0
B135: 121 | C135: 9 | D135: QUETZALTENANGO | E135: 909 | F135: San Juan Ostuncalco | G135: 35.543492 | H135: 0 | I135: 176.10185 | J135: 15 | K135: 15.003725 | L135: 100 | M135: 0.65257159 | N135: 448.68 | O135: 423.72767 | P135: 0.975 | Q135: 0.63132817 | R135: 0.49451127 | S135: 1.0909091 | T135: 0.11942613 | U135: 0.090740344 | V135: 0.67790982 | W135: 0.34294118 | X135: 119.59318 | Y135: 0.58661342 | Z135: 1162.6295 | AA135: 0.69084448 | AB135: 11.952984 | AC135: 0.062573464 | AD135: 0.033195021 | AE135: 0.030607622 | AF135: 0.38330744 | AG135: 0.055623031 | AH135: 30.21707 | AI135: 0.29344564 | AJ135: 1.7256073 | AK135: 0.39770323 | AL135: 357.05054 | AM135: 12.04321 | AN135: 203.22837 | AO135: 0.32837569 | AP135: 0.12817688 | AQ135: 7288225 | AR135: 0.25929324 | AS135: 58.126973 | AT135: 0.14725594 | AU135: 15 | AV135: 0.035370888 | AW135: 0
...

Sheet Sheet1
A1: ID | B1: mun | C1: gdppc | D1: enrollment | E1: success
A2: 101 | B2: Guatemala | C2: 24741.856 | D2: =_xlfn.XLOOKUP(A2,'ICL 2024 (datos serie original)'!$E$10:$E$349,'ICL 2024 (datos serie original)'!$AA$10:$AA$349) -> 0.9543537 | E2: =_xlfn.XLOOKUP(A2,'ICL 2024 (datos serie original)'!$E$10:$E$349,'ICL 2024 (datos serie original)'!$AD$10:$AD$349) -> 0.122015
A3: 509 | B3: San José | C3: 19358.512 | D3: =_xlfn.XLOOKUP(A3,'ICL 2024 (datos serie original)'!$E$10:$E$349,'ICL 2024 (datos serie original)'!$AA$10:$AA$349) -> 0.79403455 | E3: =_xlfn.XLOOKUP(A3,'ICL 2024 (datos serie original)'!$E$10:$E$349,'ICL 2024 (datos serie original)'!$AD$10:$AD$349) -> 0.005988024
A4: 102 | B4: Santa Catarina Pinula | C4: 18727.882 | D4: =_xlfn.XLOOKUP(A4,'ICL 2024 (datos serie original)'!$E$10:$E$349,'ICL 2024 (datos serie original)'!$AA$10:$AA$349) -> 1.0436466 | E4: =_xlfn.XLOOKUP(A4,'ICL 2024 (datos serie original)'!$E$10:$E$349,'ICL 2024 (datos serie original)'!$AD$10:$AD$349) -> 0.17862267
A5: 113 | B5: Fraijanes | C5: 16475.126 | D5: =_xlfn.XLOOKUP(A5,'ICL 2024 (datos serie original)'!$E$10:$E$349,'ICL 2024 (datos serie original)'!$AA$10:$AA$349) -> 0.92357088 | E5: =_xlfn.XLOOKUP(A5,'ICL 2024 (datos serie original)'!$E$10:$E$349,'ICL 2024 (datos serie original)'!$AD$10:$AD$349) -> 0.32561728
A6: 902 | B6: Salcajá | C6: 15497.367 | D6: =_xlfn.XLOOKUP(A6,'ICL 2024 (datos serie original)'!$E$10:$E$349,'ICL 2024 (datos serie original)'!$AA$10:$AA$349) -> 0.88267488 | E6: =_xlfn.XLOOKUP(A6,'ICL 2024 (datos serie original)'!$E$10:$E$349,'ICL 2024 (datos serie original)'!$AD$10:$AD$349) -> 0.035928144
A7: 501 | B7: Escuintla | C7: 14697.177 | D7: =_xlfn.XLOOKUP(A7,'ICL 2024 (datos serie original)'!$E$10:$E$349,'ICL 2024 (datos serie original)'!$AA$10:$AA$349) -> 0.84563542 | E7: =_xlfn.XLOOKUP(A7,'ICL 2024 (datos serie original)'!$E$10:$E$349,'ICL 2024 (datos serie original)'!$AD$10:$AD$349) -> 0.14906832
A8: 1801 | B8: Puerto Barrios | C8: 14660.225 | D8: =_xlfn.XLOOKUP(A8,'ICL 2024 (datos serie original)'!$E$10:$E$349,'ICL 2024 (datos serie original)'!$AA$10:$AA$349) -> 0.79538412 | E8: =_xlfn.XLOOKUP(A8,'ICL 2024 (datos serie original)'!$E$10:$E$349,'ICL 2024 (datos serie original)'!$AD$10:$AD$349) -> 0.047794118
A9: 910 | B9: San Mateo | C9: 14304.28 | D9: =_xlfn.XLOOKUP(A9,'ICL 2024 (datos serie original)'!$E$10:$E$349,'ICL 2024 (datos serie original)'!$AA$10:$AA$349) -> 0.69785575 | E9: =_xlfn.XLOOKUP(A9,'ICL 2024 (datos serie original)'!$E$10:$E$349,'ICL 2024 (datos serie original)'!$AD$10:$AD$349) -> 0.08
A10: 511 | B10: Palín | C10: 13062.352 | D10: =_xlfn.XLOOKUP(A10,'ICL 2024 (datos serie original)'!$E$10:$E$349,'ICL 2024 (datos serie original)'!$AA$10:$AA$349) -> 0.75284463 | E10: =_xlfn.XLOOKUP(A10,'ICL 2024 (datos serie original)'!$E$10:$E$349,'ICL 2024 (datos serie original)'!$AD$10:$AD$349) -> 0.037634409
A11: 308 | B11: San Lucas Sacatepéquez | C11: 12885.563 | D11: =_xlfn.XLOOKUP(A11,'ICL 2024 (datos serie original)'!$E$10:$E$349,'ICL 2024 (datos serie original)'!$AA$10:$AA$349) -> 1.0354023 | E11: =_xlfn.XLOOKUP(A11,'ICL 2024 (datos serie original)'!$E$10:$E$349,'ICL 2024 (datos serie original)'!$AD$10:$AD$349) -> 0.21914358
A12: 108 | B12: Mixco | C12: 12394.887 | D12: =_xlfn.XLOOKUP(A12,'ICL 2024 (datos serie original)'!$E$10:$E$349,'ICL 2024 (datos serie original)'!$AA$10:$AA$349) -> 0.81444986 | E12: =_xlfn.XLOOKUP(A12,'ICL 2024 (datos serie original)'!$E$10:$E$349,'ICL 2024 (datos serie original)'!$AD$10:$AD$349) -> 0.16623207
A13: 505 | B13: Masagua | C13: 12054.127 | D13: =_xlfn.XLOOKUP(A13,'ICL 2024 (datos serie original)'!$E$10:$E$349,'ICL 2024 (datos serie original)'!$AA$10:$AA$349) -> 0.80183486 | E13: =_xlfn.XLOOKUP(A13,'ICL 2024 (datos serie original)'!$E$10:$E$349,'ICL 2024 (datos serie original)'!$AD$10:$AD$349) -> 0
... A341: 715 | B341: San Pablo La Laguna | C341: 1208.4269 | D341: =_xlfn.XLOOKUP(A341,'ICL 2024 (datos serie original)'!$E$10:$E$349,'ICL 2024 (datos serie original)'!$AA$10:$AA$349) -> 0.7028436 | E341: =_xlfn.XLOOKUP(A341,'ICL 2024 (datos serie original)'!$E$10:$E$349,'ICL 2024 (datos serie original)'!$AD$10:$AD$349) -> 0
